Workbook
Name BRAND_EMAIL: 'Start Here'!$C$22
Name BRAND_NAME: 'Start Here'!$C$20
Name BRAND_PHONE: 'Start Here'!$C$21
Name BRAND_WEBSITE: 'Start Here'!$C$23

Sheet Start Here
B1: =IF(TRIM($C$20)="","HMO Compliance Tracker 2026",TRIM($C$20)) -> HMO Compliance Tracker 2026
B2: HMO compliance tracker for landlords and letting agents in England · Excel and Google Sheets
B3: Version 2.0 · Law as understood at October 2026 (England)
B5: START HERE: 5 STEPS
B6: 1 Add your properties | C6: Go to Properties and type one property per row (over the two SAMPLE rows). Each property name must be unique: the other sheets pick properties from this list.
B7: 2 Log your checks | C7: Go to Compliance Log. Pick a Property and a Check type, then enter the date it was last done. The tracker looks up how often it is needed, works out Next due and Days left, and colours the Status.
B8: 3 Record day-to-day safety | C8: Use Fire Safety Log for alarm, emergency-lighting and fire-door checks; Licence Conditions to work through each HMO licence condition and check room sizes; Tenancies & Renters Rights for deposits, Right to Rent, rent increases and pet requests; PRS Database Readiness to prepare for England's new landlord database.
B9: 4 Keep contractors to hand | C9: List your gas engineer, electrician and fire-alarm company on Contractors, and record certificate references and document links against each check in the Compliance Log.
B10: 5 Check the Dashboard weekly | C10: The Dashboard updates by itself: clear Reds first, then Ambers. The Reference sheet explains every check, how often it is normally needed, and the official source.
B11: To clear the SAMPLE data: on each sheet select the white input cells in the rows marked SAMPLE and press Delete. Leave the grey formula cells alone.
B13: COLOUR KEY
B14: Red: Overdue | C14: The due date has passed. Deal with these first.
B15: Amber: Due within 60 days | C15: Orange = due in 30 days or less (Due <=30). Yellow = due in 31 to 60 days (Due 31-60).
B16: Green: OK | C16: More than 60 days left.
B17: Grey: No date entered | C17: No last-done date has been entered yet, or the date is not recognised as a date.
B18: Amber is split into two shades so you can see what is most urgent.
B19: BRAND: change these 4 cells and the header line on every sheet updates (white-label copy)
B20: Business name | C20: HMO Compliance Tracker 2026 | D20: Shown at the top of every sheet.
B21: Phone | D21: Optional. Leave empty to hide.
B22: Email | D22: Optional. Leave empty to hide.
B23: Website | D23: Optional. Leave empty to hide.
B24: Header preview | C24: =IF(TRIM('Start Here'!$C$20)="","HMO Compliance Tracker 2026",TRIM('Start Here'!$C$20))&IF(TRIM('Start Here'!$C$21)="",""," | "&TRIM('Start Here'!$C$21))&IF(TRIM('Start Here'!$C$22)="",""," | "&TRIM('Start Here'!$C$22))&IF(TRIM('Start Here'!$C$23)="",""," | "&TRIM('Start Here'!$C$23)) -> HMO Compliance Tracker 2026
B26: ABOUT THIS VERSION
B27: Version | C27: 2.0 (October 2026)
B28: Law | C28: Law as understood at October 2026 (England)
B29: Coverage | C29: England only. Wales, Scotland and Northern Ireland have different rules.
B30: Support | C30: hello@innovateuk.uk
B32: IMPORTANT
B33: This tracker is an organisational tool, not legal advice. Check requirements with your local council and a qualified adviser.
B34: Independent product. Not affiliated with, endorsed by or connected to Innovate UK, UKRI, GOV.UK or any council. The Reference sheet links to the official sources used.
B36: USING GOOGLE SHEETS?
B37: Upload the .xlsx to Google Drive (or Google Sheets > File > Import > Upload) and open it with Google Sheets. Then choose File > Settings > Locale > United Kingdom so dates read dd/mm/yyyy. Everything works without add-ons or scripts.
B39: SHEETS IN THIS WORKBOOK (click to jump)
B40: Dashboard | C40: Totals, per-property summary and the next 15 deadlines. Automatic.
B41: PRS Database Readiness | C41: NEW: get every property ready for the new national landlord database (draft regulations).
B42: Properties | C42: Your properties: licence, occupancy, EPC, PRS Database reference, manager.
B43: Compliance Log | C43: One row per property and check. Next due, days left and status are automatic.
B44: Fire Safety Log | C44: Weekly alarm tests, emergency lighting, fire doors, drills and defects.
B45: Licence Conditions | C45: HMO licence condition checklists and the room-size calculator.
B46: Tenancies & Renters Rights | C46: Deposits, Right to Rent, written terms, Information Sheet, rent increases, pet requests.
B47: Contractors | C47: Who does what, with registration numbers.
B48: Reference | C48: What each check is, how often, the legal basis and the official link.

Sheet Dashboard
A1: =IF(TRIM('Start Here'!$C$20)="","HMO Compliance Tracker 2026",TRIM('Start Here'!$C$20))&IF(TRIM('Start Here'!$C$21)="",""," | "&TRIM('Start Here'!$C$21))&IF(TRIM('Start Here'!$C$22)="",""," | "&TRIM('Start Here'!$C$22))&IF(TRIM('Start Here'!$C$23)="",""," | "&TRIM('Start Here'!$C$23)) -> HMO Compliance Tracker 2026
B2: Dashboard
B3: ="Updates automatically from the Compliance Log, Properties and Fire Safety Log. As at "&TEXT(TODAY(),"dd/mm/yyyy") -> Updates automatically from the Compliance Log, Properties and Fire Safety Log. As at 02/10/2026
B5: PROPERTIES | D5: CHECKS TRACKED | F5: OVERDUE | H5: DUE <=30 DAYS | J5: DUE 31-60 DAYS | L5: OK
B6: =COUNTA(Properties!$A$6:$A$105) -> 2 | D6: =SUMPRODUCT(--('Compliance Log'!$H$6:$H$1005<>"")) -> 15 | F6: =SUMPRODUCT(--('Compliance Log'!$H$6:$H$1005="Overdue")) -> 3 | H6: =SUMPRODUCT(--('Compliance Log'!$H$6:$H$1005="Due <=30")) -> 2 | J6: =SUMPRODUCT(--('Compliance Log'!$H$6:$H$1005="Due 31-60")) -> 3 | L6: =SUMPRODUCT(--('Compliance Log'!$H$6:$H$1005="OK")) -> 6
B8: NO DATE ENTERED | D8: OPEN FIRE-SAFETY DEFECTS | F8: LICENCES EXPIRED / <=60 DAYS | H8: PROPERTIES OVER-OCCUPIED | J8: PRS DB: NOT YET READY | L8: PRS DB: EARLIEST DEADLINE
B9: =SUMPRODUCT(--('Compliance Log'!$H$6:$H$1005="No date")) -> 1 | D9: =SUMPRODUCT(--('Fire Safety Log'!$J$6:$J$1005="OPEN")) -> 1 | F9: =SUMPRODUCT((Properties!$H$6:$H$105="Expired")+(Properties!$H$6:$H$105="Expires <=30")+(Properties!$H$6:$H$105="Expires 31-60")) -> 1 | H9: =SUMPRODUCT(--(Properties!$K$6:$K$105="OVER")) -> 1 | J9: =SUMPRODUCT(('PRS Database Readiness'!$I$9:$I$108="Nearly")+('PRS Database Readiness'!$I$9:$I$108="Not ready")) -> 2 | L9: =IF(COUNT('PRS Database Readiness'!$AJ$9:$AJ$108)=0,"n/a",MIN('PRS Database Readiness'!$AJ$9:$AJ$108)) -> 46460
B11: NEXT 15 DEADLINES (soonest first, overdue items at the top)
B12: # | C12: Due date | D12: Days left | E12: Property | H12: Check | L12: Status
B13: =IF($P13="","",ROW()-ROW($B$12)) -> 1 | C13: =IF($P13="","",INDEX('Compliance Log'!$F$6:$F$1005,$P13)) -> 45962 | D13: =IF($P13="","",INDEX('Compliance Log'!$G$6:$G$1005,$P13)) -> -335 | E13: =IF($P13="","",INDEX('Compliance Log'!$A$6:$A$1005,$P13)) -> SAMPLE - 12 Acacia Road, Exampleton | H13: =IF($P13="","",INDEX('Compliance Log'!$B$6:$B$1005,$P13)) -> Portable appliance testing (PAT) | L13: =IF($P13="","",INDEX('Compliance Log'!$H$6:$H$1005,$P13)) -> Overdue | P13: =IFERROR(MATCH(SMALL('Compliance Log'!$M$6:$M$1005,ROW()-ROW($P$12)),'Compliance Log'!$M$6:$M$1005,0),"") -> 7
B14: =IF($P14="","",ROW()-ROW($B$12)) -> 2 | C14: =IF($P14="","",INDEX('Compliance Log'!$F$6:$F$1005,$P14)) -> 46242 | D14: =IF($P14="","",INDEX('Compliance Log'!$G$6:$G$1005,$P14)) -> -55 | E14: =IF($P14="","",INDEX('Compliance Log'!$A$6:$A$1005,$P14)) -> SAMPLE - Flat 3, 8 Demo Street, Sampleford | H14: =IF($P14="","",INDEX('Compliance Log'!$B$6:$B$1005,$P14)) -> Smoke & CO alarms - check | L14: =IF($P14="","",INDEX('Compliance Log'!$H$6:$H$1005,$P14)) -> Overdue | P14: =IFERROR(MATCH(SMALL('Compliance Log'!$M$6:$M$1005,ROW()-ROW($P$12)),'Compliance Log'!$M$6:$M$1005,0),"") -> 13
B15: =IF($P15="","",ROW()-ROW($B$12)) -> 3 | C15: =IF($P15="","",INDEX('Compliance Log'!$F$6:$F$1005,$P15)) -> 46272 | D15: =IF($P15="","",INDEX('Compliance Log'!$G$6:$G$1005,$P15)) -> -25 | E15: =IF($P15="","",INDEX('Compliance Log'!$A$6:$A$1005,$P15)) -> SAMPLE - 12 Acacia Road, Exampleton | H15: =IF($P15="","",INDEX('Compliance Log'!$B$6:$B$1005,$P15)) -> Gas Safety Certificate (CP12) | L15: =IF($P15="","",INDEX('Compliance Log'!$H$6:$H$1005,$P15)) -> Overdue | P15: =IFERROR(MATCH(SMALL('Compliance Log'!$M$6:$M$1005,ROW()-ROW($P$12)),'Compliance Log'!$M$6:$M$1005,0),"") -> 1
B16: =IF($P16="","",ROW()-ROW($B$12)) -> 4 | C16: =IF($P16="","",INDEX('Compliance Log'!$F$6:$F$1005,$P16)) -> 46312 | D16: =IF($P16="","",INDEX('Compliance Log'!$G$6:$G$1005,$P16)) -> 15 | E16: =IF($P16="","",INDEX('Compliance Log'!$A$6:$A$1005,$P16)) -> SAMPLE - 12 Acacia Road, Exampleton | H16: =IF($P16="","",INDEX('Compliance Log'!$B$6:$B$1005,$P16)) -> Emergency lighting - annual full-discharge test | L16: =IF($P16="","",INDEX('Compliance Log'!$H$6:$H$1005,$P16)) -> Due <=30 | P16: =IFERROR(MATCH(SMALL('Compliance Log'!$M$6:$M$1005,ROW()-ROW($P$12)),'Compliance Log'!$M$6:$M$1005,0),"") -> 5
B17: =IF($P17="","",ROW()-ROW($B$12)) -> 5 | C17: =IF($P17="","",INDEX('Compliance Log'!$F$6:$F$1005,$P17)) -> 46317 | D17: =IF($P17="","",INDEX('Compliance Log'!$G$6:$G$1005,$P17)) -> 20 | E17: =IF($P17="","",INDEX('Compliance Log'!$A$6:$A$1005,$P17)) -> SAMPLE - Flat 3, 8 Demo Street, Sampleford | H17: =IF($P17="","",INDEX('Compliance Log'!$B$6:$B$1005,$P17)) -> Fire extinguishers - service | L17: =IF($P17="","",INDEX('Compliance Log'!$H$6:$H$1005,$P17)) -> Due <=30 | P17: =IFERROR(MATCH(SMALL('Compliance Log'!$M$6:$M$1005,ROW()-ROW($P$12)),'Compliance Log'!$M$6:$M$1005,0),"") -> 14
B18: =IF($P18="","",ROW()-ROW($B$12)) -> 6 | C18: =IF($P18="","",INDEX('Compliance Log'!$F$6:$F$1005,$P18)) -> 46333 | D18: =IF($P18="","",INDEX('Compliance Log'!$G$6:$G$1005,$P18)) -> 36 | E18: =IF($P18="","",INDEX('Compliance Log'!$A$6:$A$1005,$P18)) -> SAMPLE - Flat 3, 8 Demo Street, Sampleford | H18: =IF($P18="","",INDEX('Compliance Log'!$B$6:$B$1005,$P18)) -> Electrical Installation Condition Report (EICR) | L18: =IF($P18="","",INDEX('Compliance Log'!$H$6:$H$1005,$P18)) -> Due 31-60 | P18: =IFERROR(MATCH(SMALL('Compliance Log'!$M$6:$M$1005,ROW()-ROW($P$12)),'Compliance Log'!$M$6:$M$1005,0),"") -> 10
B19: =IF($P19="","",ROW()-ROW($B$12)) -> 7 | C19: =IF($P19="","",INDEX('Compliance Log'!$F$6:$F$1005,$P19)) -> 46337 | D19: =IF($P19="","",INDEX('Compliance Log'!$G$6:$G$1005,$P19)) -> 40 | E19: =IF($P19="","",INDEX('Compliance Log'!$A$6:$A$1005,$P19)) -> SAMPLE - Flat 3, 8 Demo Street, Sampleford | H19: =IF($P19="","",INDEX('Compliance Log'!$B$6:$B$1005,$P19)) -> HMO licence renewal | L19: =IF($P19="","",INDEX('Compliance Log'!$H$6:$H$1005,$P19)) -> Due 31-60 | P19: =IFERROR(MATCH(SMALL('Compliance Log'!$M$6:$M$1005,ROW()-ROW($P$12)),'Compliance Log'!$M$6:$M$1005,0),"") -> 15
B20: =IF($P20="","",ROW()-ROW($B$12)) -> 8 | C20: =IF($P20="","",INDEX('Compliance Log'!$F$6:$F$1005,$P20)) -> 46342 | D20: =IF($P20="","",INDEX('Compliance Log'!$G$6:$G$1005,$P20)) -> 45 | E20: =IF($P20="","",INDEX('Compliance Log'!$A$6:$A$1005,$P20)) -> SAMPLE - 12 Acacia Road, Exampleton | H20: =IF($P20="","",INDEX('Compliance Log'!$B$6:$B$1005,$P20)) -> Fire Risk Assessment - review | L20: =IF($P20="","",INDEX('Compliance Log'!$H$6:$H$1005,$P20)) -> Due 31-60 | P20: =IFERROR(MATCH(SMALL('Compliance Log'!$M$6:$M$1005,ROW()-ROW($P$12)),'Compliance Log'!$M$6:$M$1005,0),"") -> 3
B21: =IF($P21="","",ROW()-ROW($B$12)) -> 9 | C21: =IF($P21="","",INDEX('Compliance Log'!$F$6:$F$1005,$P21)) -> 46421 | D21: =IF($P21="","",INDEX('Compliance Log'!$G$6:$G$1005,$P21)) -> 124 | E21: =IF($P21="","",INDEX('Compliance Log'!$A$6:$A$1005,$P21)) -> SAMPLE - 12 Acacia Road, Exampleton | H21: =IF($P21="","",INDEX('Compliance Log'!$B$6:$B$1005,$P21)) -> Fire alarm system - service | L21: =IF($P21="","",INDEX('Compliance Log'!$H$6:$H$1005,$P21)) -> OK | P21: =IFERROR(MATCH(SMALL('Compliance Log'!$M$6:$M$1005,ROW()-ROW($P$12)),'Compliance Log'!$M$6:$M$1005,0),"") -> 4
B22: =IF($P22="","",ROW()-ROW($B$12)) -> 10 | C22: =IF($P22="","",INDEX('Compliance Log'!$F$6:$F$1005,$P22)) -> 46423 | D22: =IF($P22="","",INDEX('Compliance Log'!$G$6:$G$1005,$P22)) -> 126 | E22: =IF($P22="","",INDEX('Compliance Log'!$A$6:$A$1005,$P22)) -> SAMPLE - 12 Acacia Road, Exampleton | H22: =IF($P22="","",INDEX('Compliance Log'!$B$6:$B$1005,$P22)) -> HMO licence renewal | L22: =IF($P22="","",INDEX('Compliance Log'!$H$6:$H$1005,$P22)) -> OK | P22: =IFERROR(MATCH(SMALL('Compliance Log'!$M$6:$M$1005,ROW()-ROW($P$12)),'Compliance Log'!$M$6:$M$1005,0),"") -> 8
B23: =IF($P23="","",ROW()-ROW($B$12)) -> 11 | C23: =IF($P23="","",INDEX('Compliance Log'!$F$6:$F$1005,$P23)) -> 46542 | D23: =IF($P23="","",INDEX('Compliance Log'!$G$6:$G$1005,$P23)) -> 245 | E23: =IF($P23="","",INDEX('Compliance Log'!$A$6:$A$1005,$P23)) -> SAMPLE - Flat 3, 8 Demo Street, Sampleford | H23: =IF($P23="","",INDEX('Compliance Log'!$B$6:$B$1005,$P23)) -> Gas Safety Certificate (CP12) | L23: =IF($P23="","",INDEX('Compliance Log'!$H$6:$H$1005,$P23)) -> OK | P23: =IFERROR(MATCH(SMALL('Compliance Log'!$M$6:$M$1005,ROW()-ROW($P$12)),'Compliance Log'!$M$6:$M$1005,0),"") -> 9
B24: =IF($P24="","",ROW()-ROW($B$12)) -> 12 | C24: =IF($P24="","",INDEX('Compliance Log'!$F$6:$F$1005,$P24)) -> 46572 | D24: =IF($P24="","",INDEX('Compliance Log'!$G$6:$G$1005,$P24)) -> 275 | E24: =IF($P24="","",INDEX('Compliance Log'!$A$6:$A$1005,$P24)) -> SAMPLE - 12 Acacia Road, Exampleton | H24: =IF($P24="","",INDEX('Compliance Log'!$B$6:$B$1005,$P24)) -> Fire extinguishers - service | L24: =IF($P24="","",INDEX('Compliance Log'!$H$6:$H$1005,$P24)) -> OK | P24: =IFERROR(MATCH(SMALL('Compliance Log'!$M$6:$M$1005,ROW()-ROW($P$12)),'Compliance Log'!$M$6:$M$1005,0),"") -> 6
... B27: =IF($P27="","",ROW()-ROW($B$12)) | C27: =IF($P27="","",INDEX('Compliance Log'!$F$6:$F$1005,$P27)) | D27: =IF($P27="","",INDEX('Compliance Log'!$G$6:$G$1005,$P27)) | E27: =IF($P27="","",INDEX('Compliance Log'!$A$6:$A$1005,$P27)) | H27: =IF($P27="","",INDEX('Compliance Log'!$B$6:$B$1005,$P27)) | L27: =IF($P27="","",INDEX('Compliance Log'!$H$6:$H$1005,$P27)) | P27: =IFERROR(MATCH(SMALL('Compliance Log'!$M$6:$M$1005,ROW()-ROW($P$12)),'Compliance Log'!$M$6:$M$1005,0),"")
B29: PROPERTY SUMMARY (from the Compliance Log)
B30: Property | G30: Overdue | H30: Due soon (<=60) | I30: OK | J30: No date | K30: Worst status | M30: Checks
B31: =IF(INDEX(Properties!$A$6:$A$105,ROW()-ROW($B$30))="","",INDEX(Properties!$A$6:$A$105,ROW()-ROW($B$30))) -> SAMPLE - 12 Acacia Road, Exampleton | G31: =IF($B31="","",SUMPRODUCT(('Compliance Log'!$A$6:$A$1005=$B31)*('Compliance Log'!$H$6:$H$1005="Overdue"))) -> 2 | H31: =IF($B31="","",SUMPRODUCT(('Compliance Log'!$A$6:$A$1005=$B31)*(('Compliance Log'!$H$6:$H$1005="Due <=30")+('Compliance Log'!$H$6:$H$1005="Due 31-60")))) -> 2 | I31: =IF($B31="","",SUMPRODUCT(('Compliance Log'!$A$6:$A$1005=$B31)*('Compliance Log'!$H$6:$H$1005="OK"))) -> 4 | J31: =IF($B31="","",SUMPRODUCT(('Compliance Log'!$A$6:$A$1005=$B31)*('Compliance Log'!$H$6:$H$1005="No date"))) -> 0 | K31: =IF($B31="","",IF($G31>0,"Overdue",IF(SUMPRODUCT(('Compliance Log'!$A$6:$A$1005=$B31)*('Compliance Log'!$H$6:$H$1005="Due <=30"))>0,"Due <=30",IF($H31>0,"Due 31-60",IF($J31>0,"No date",IF($I31>0,"OK","No checks")))))) -> Overdue | M31: =IF($B31="","",$G31+$H31+$I31+$J31) -> 8
B32: =IF(INDEX(Properties!$A$6:$A$105,ROW()-ROW($B$30))="","",INDEX(Properties!$A$6:$A$105,ROW()-ROW($B$30))) -> SAMPLE - Flat 3, 8 Demo Street, Sampleford | G32: =IF($B32="","",SUMPRODUCT(('Compliance Log'!$A$6:$A$1005=$B32)*('Compliance Log'!$H$6:$H$1005="Overdue"))) -> 1 | H32: =IF($B32="","",SUMPRODUCT(('Compliance Log'!$A$6:$A$1005=$B32)*(('Compliance Log'!$H$6:$H$1005="Due <=30")+('Compliance Log'!$H$6:$H$1005="Due 31-60")))) -> 3 | I32: =IF($B32="","",SUMPRODUCT(('Compliance Log'!$A$6:$A$1005=$B32)*('Compliance Log'!$H$6:$H$1005="OK"))) -> 2 | J32: =IF($B32="","",SUMPRODUCT(('Compliance Log'!$A$6:$A$1005=$B32)*('Compliance Log'!$H$6:$H$1005="No date"))) -> 1 | K32: =IF($B32="","",IF($G32>0,"Overdue",IF(SUMPRODUCT(('Compliance Log'!$A$6:$A$1005=$B32)*('Compliance Log'!$H$6:$H$1005="Due <=30"))>0,"Due <=30",IF($H32>0,"Due 31-60",IF($J32>0,"No date",IF($I32>0,"OK","No checks")))))) -> Overdue | M32: =IF($B32="","",$G32+$H32+$I32+$J32) -> 7
B33: =IF(INDEX(Properties!$A$6:$A$105,ROW()-ROW($B$30))="","",INDEX(Properties!$A$6:$A$105,ROW()-ROW($B$30))) | G33: =IF($B33="","",SUMPRODUCT(('Compliance Log'!$A$6:$A$1005=$B33)*('Compliance Log'!$H$6:$H$1005="Overdue"))) | H33: =IF($B33="","",SUMPRODUCT(('Compliance Log'!$A$6:$A$1005=$B33)*(('Compliance Log'!$H$6:$H$1005="Due <=30")+('Compliance Log'!$H$6:$H$1005="Due 31-60")))) | I33: =IF($B33="","",SUMPRODUCT(('Compliance Log'!$A$6:$A$1005=$B33)*('Compliance Log'!$H$6:$H$1005="OK"))) | J33: =IF($B33="","",SUMPRODUCT(('Compliance Log'!$A$6:$A$1005=$B33)*('Compliance Log'!$H$6:$H$1005="No date"))) | K33: =IF($B33="","",IF($G33>0,"Overdue",IF(SUMPRODUCT(('Compliance Log'!$A$6:$A$1005=$B33)*('Compliance Log'!$H$6:$H$1005="Due <=30"))>0,"Due <=30",IF($H33>0,"Due 31-60",IF($J33>0,"No date",IF($I33>0,"OK","No checks")))))) | M33: =IF($B33="","",$G33+$H33+$I33+$J33)
B34: =IF(INDEX(Properties!$A$6:$A$105,ROW()-ROW($B$30))="","",INDEX(Properties!$A$6:$A$105,ROW()-ROW($B$30))) | G34: =IF($B34="","",SUMPRODUCT(('Compliance Log'!$A$6:$A$1005=$B34)*('Compliance Log'!$H$6:$H$1005="Overdue"))) | H34: =IF($B34="","",SUMPRODUCT(('Compliance Log'!$A$6:$A$1005=$B34)*(('Compliance Log'!$H$6:$H$1005="Due <=30")+('Compliance Log'!$H$6:$H$1005="Due 31-60")))) | I34: =IF($B34="","",SUMPRODUCT(('Compliance Log'!$A$6:$A$1005=$B34)*('Compliance Log'!$H$6:$H$1005="OK"))) | J34: =IF($B34="","",SUMPRODUCT(('Compliance Log'!$A$6:$A$1005=$B34)*('Compliance Log'!$H$6:$H$1005="No date"))) | K34: =IF($B34="","",IF($G34>0,"Overdue",IF(SUMPRODUCT(('Compliance Log'!$A$6:$A$1005=$B34)*('Compliance Log'!$H$6:$H$1005="Due <=30"))>0,"Due <=30",IF($H34>0,"Due 31-60",IF($J34>0,"No date",IF($I34>0,"OK","No checks")))))) | M34: =IF($B34="","",$G34+$H34+$I34+$J34)
B35: =IF(INDEX(Properties!$A$6:$A$105,ROW()-ROW($B$30))="","",INDEX(Properties!$A$6:$A$105,ROW()-ROW($B$30))) | G35: =IF($B35="","",SUMPRODUCT(('Compliance Log'!$A$6:$A$1005=$B35)*('Compliance Log'!$H$6:$H$1005="Overdue"))) | H35: =IF($B35="","",SUMPRODUCT(('Compliance Log'!$A$6:$A$1005=$B35)*(('Compliance Log'!$H$6:$H$1005="Due <=30")+('Compliance Log'!$H$6:$H$1005="Due 31-60")))) | I35: =IF($B35="","",SUMPRODUCT(('Compliance Log'!$A$6:$A$1005=$B35)*('Compliance Log'!$H$6:$H$1005="OK"))) | J35: =IF($B35="","",SUMPRODUCT(('Compliance Log'!$A$6:$A$1005=$B35)*('Compliance Log'!$H$6:$H$1005="No date"))) | K35: =IF($B35="","",IF($G35>0,"Overdue",IF(SUMPRODUCT(('Compliance Log'!$A$6:$A$1005=$B35)*('Compliance Log'!$H$6:$H$1005="Due <=30"))>0,"Due <=30",IF($H35>0,"Due 31-60",IF($J35>0,"No date",IF($I35>0,"OK","No checks")))))) | M35: =IF($B35="","",$G35+$H35+$I35+$J35)
B36: =IF(INDEX(Properties!$A$6:$A$105,ROW()-ROW($B$30))="","",INDEX(Properties!$A$6:$A$105,ROW()-ROW($B$30))) | G36: =IF($B36="","",SUMPRODUCT(('Compliance Log'!$A$6:$A$1005=$B36)*('Compliance Log'!$H$6:$H$1005="Overdue"))) | H36: =IF($B36="","",SUMPRODUCT(('Compliance Log'!$A$6:$A$1005=$B36)*(('Compliance Log'!$H$6:$H$1005="Due <=30")+('Compliance Log'!$H$6:$H$1005="Due 31-60")))) | I36: =IF($B36="","",SUMPRODUCT(('Compliance Log'!$A$6:$A$1005=$B36)*('Compliance Log'!$H$6:$H$1005="OK"))) | J36: =IF($B36="","",SUMPRODUCT(('Compliance Log'!$A$6:$A$1005=$B36)*('Compliance Log'!$H$6:$H$1005="No date"))) | K36: =IF($B36="","",IF($G36>0,"Overdue",IF(SUMPRODUCT(('Compliance Log'!$A$6:$A$1005=$B36)*('Compliance Log'!$H$6:$H$1005="Due <=30"))>0,"Due <=30",IF($H36>0,"Due 31-60",IF($J36>0,"No date",IF($I36>0,"OK","No checks")))))) | M36: =IF($B36="","",$G36+$H36+$I36+$J36)
B37: =IF(INDEX(Properties!$A$6:$A$105,ROW()-ROW($B$30))="","",INDEX(Properties!$A$6:$A$105,ROW()-ROW($B$30))) | G37: =IF($B37="","",SUMPRODUCT(('Compliance Log'!$A$6:$A$1005=$B37)*('Compliance Log'!$H$6:$H$1005="Overdue"))) | H37: =IF($B37="","",SUMPRODUCT(('Compliance Log'!$A$6:$A$1005=$B37)*(('Compliance Log'!$H$6:$H$1005="Due <=30")+('Compliance Log'!$H$6:$H$1005="Due 31-60")))) | I37: =IF($B37="","",SUMPRODUCT(('Compliance Log'!$A$6:$A$1005=$B37)*('Compliance Log'!$H$6:$H$1005="OK"))) | J37: =IF($B37="","",SUMPRODUCT(('Compliance Log'!$A$6:$A$1005=$B37)*('Compliance Log'!$H$6:$H$1005="No date"))) | K37: =IF($B37="","",IF($G37>0,"Overdue",IF(SUMPRODUCT(('Compliance Log'!$A$6:$A$1005=$B37)*('Compliance Log'!$H$6:$H$1005="Due <=30"))>0,"Due <=30",IF($H37>0,"Due 31-60",IF($J37>0,"No date",IF($I37>0,"OK","No checks")))))) | M37: =IF($B37="","",$G37+$H37+$I37+$J37)
B38: =IF(INDEX(Properties!$A$6:$A$105,ROW()-ROW($B$30))="","",INDEX(Properties!$A$6:$A$105,ROW()-ROW($B$30))) | G38: =IF($B38="","",SUMPRODUCT(('Compliance Log'!$A$6:$A$1005=$B38)*('Compliance Log'!$H$6:$H$1005="Overdue"))) | H38: =IF($B38="","",SUMPRODUCT(('Compliance Log'!$A$6:$A$1005=$B38)*(('Compliance Log'!$H$6:$H$1005="Due <=30")+('Compliance Log'!$H$6:$H$1005="Due 31-60")))) | I38: =IF($B38="","",SUMPRODUCT(('Compliance Log'!$A$6:$A$1005=$B38)*('Compliance Log'!$H$6:$H$1005="OK"))) | J38: =IF($B38="","",SUMPRODUCT(('Compliance Log'!$A$6:$A$1005=$B38)*('Compliance Log'!$H$6:$H$1005="No date"))) | K38: =IF($B38="","",IF($G38>0,"Overdue",IF(SUMPRODUCT(('Compliance Log'!$A$6:$A$1005=$B38)*('Compliance Log'!$H$6:$H$1005="Due <=30"))>0,"Due <=30",IF($H38>0,"Due 31-60",IF($J38>0,"No date",IF($I38>0,"OK","No checks")))))) | M38: =IF($B38="","",$G38+$H38+$I38+$J38)
B39: =IF(INDEX(Properties!$A$6:$A$105,ROW()-ROW($B$30))="","",INDEX(Properties!$A$6:$A$105,ROW()-ROW($B$30))) | G39: =IF($B39="","",SUMPRODUCT(('Compliance Log'!$A$6:$A$1005=$B39)*('Compliance Log'!$H$6:$H$1005="Overdue"))) | H39: =IF($B39="","",SUMPRODUCT(('Compliance Log'!$A$6:$A$1005=$B39)*(('Compliance Log'!$H$6:$H$1005="Due <=30")+('Compliance Log'!$H$6:$H$1005="Due 31-60")))) | I39: =IF($B39="","",SUMPRODUCT(('Compliance Log'!$A$6:$A$1005=$B39)*('Compliance Log'!$H$6:$H$1005="OK"))) | J39: =IF($B39="","",SUMPRODUCT(('Compliance Log'!$A$6:$A$1005=$B39)*('Compliance Log'!$H$6:$H$1005="No date"))) | K39: =IF($B39="","",IF($G39>0,"Overdue",IF(SUMPRODUCT(('Compliance Log'!$A$6:$A$1005=$B39)*('Compliance Log'!$H$6:$H$1005="Due <=30"))>0,"Due <=30",IF($H39>0,"Due 31-60",IF($J39>0,"No date",IF($I39>0,"OK","No checks")))))) | M39: =IF($B39="","",$G39+$H39+$I39+$J39)
B40: =IF(INDEX(Properties!$A$6:$A$105,ROW()-ROW($B$30))="","",INDEX(Properties!$A$6:$A$105,ROW()-ROW($B$30))) | G40: =IF($B40="","",SUMPRODUCT(('Compliance Log'!$A$6:$A$1005=$B40)*('Compliance Log'!$H$6:$H$1005="Overdue"))) | H40: =IF($B40="","",SUMPRODUCT(('Compliance Log'!$A$6:$A$1005=$B40)*(('Compliance Log'!$H$6:$H$1005="Due <=30")+('Compliance Log'!$H$6:$H$1005="Due 31-60")))) | I40: =IF($B40="","",SUMPRODUCT(('Compliance Log'!$A$6:$A$1005=$B40)*('Compliance Log'!$H$6:$H$1005="OK"))) | J40: =IF($B40="","",SUMPRODUCT(('Compliance Log'!$A$6:$A$1005=$B40)*('Compliance Log'!$H$6:$H$1005="No date"))) | K40: =IF($B40="","",IF($G40>0,"Overdue",IF(SUMPRODUCT(('Compliance Log'!$A$6:$A$1005=$B40)*('Compliance Log'!$H$6:$H$1005="Due <=30"))>0,"Due <=30",IF($H40>0,"Due 31-60",IF($J40>0,"No date",IF($I40>0,"OK","No checks")))))) | M40: =IF($B40="","",$G40+$H40+$I40+$J40)
B41: =IF(INDEX(Properties!$A$6:$A$105,ROW()-ROW($B$30))="","",INDEX(Properties!$A$6:$A$105,ROW()-ROW($B$30))) | G41: =IF($B41="","",SUMPRODUCT(('Compliance Log'!$A$6:$A$1005=$B41)*('Compliance Log'!$H$6:$H$1005="Overdue"))) | H41: =IF($B41="","",SUMPRODUCT(('Compliance Log'!$A$6:$A$1005=$B41)*(('Compliance Log'!$H$6:$H$1005="Due <=30")+('Compliance Log'!$H$6:$H$1005="Due 31-60")))) | I41: =IF($B41="","",SUMPRODUCT(('Compliance Log'!$A$6:$A$1005=$B41)*('Compliance Log'!$H$6:$H$1005="OK"))) | J41: =IF($B41="","",SUMPRODUCT(('Compliance Log'!$A$6:$A$1005=$B41)*('Compliance Log'!$H$6:$H$1005="No date"))) | K41: =IF($B41="","",IF($G41>0,"Overdue",IF(SUMPRODUCT(('Compliance Log'!$A$6:$A$1005=$B41)*('Compliance Log'!$H$6:$H$1005="Due <=30"))>0,"Due <=30",IF($H41>0,"Due 31-60",IF($J41>0,"No date",IF($I41>0,"OK","No checks")))))) | M41: =IF($B41="","",$G41+$H41+$I41+$J41)
B42: =IF(INDEX(Properties!$A$6:$A$105,ROW()-ROW($B$30))="","",INDEX(Properties!$A$6:$A$105,ROW()-ROW($B$30))) | G42: =IF($B42="","",SUMPRODUCT(('Compliance Log'!$A$6:$A$1005=$B42)*('Compliance Log'!$H$6:$H$1005="Overdue"))) | H42: =IF($B42="","",SUMPRODUCT(('Compliance Log'!$A$6:$A$1005=$B42)*(('Compliance Log'!$H$6:$H$1005="Due <=30")+('Compliance Log'!$H$6:$H$1005="Due 31-60")))) | I42: =IF($B42="","",SUMPRODUCT(('Compliance Log'!$A$6:$A$1005=$B42)*('Compliance Log'!$H$6:$H$1005="OK"))) | J42: =IF($B42="","",SUMPRODUCT(('Compliance Log'!$A$6:$A$1005=$B42)*('Compliance Log'!$H$6:$H$1005="No date"))) | K42: =IF($B42="","",IF($G42>0,"Overdue",IF(SUMPRODUCT(('Compliance Log'!$A$6:$A$1005=$B42)*('Compliance Log'!$H$6:$H$1005="Due <=30"))>0,"Due <=30",IF($H42>0,"Due 31-60",IF($J42>0,"No date",IF($I42>0,"OK","No checks")))))) | M42: =IF($B42="","",$G42+$H42+$I42+$J42)
... B130: =IF(INDEX(Properties!$A$6:$A$105,ROW()-ROW($B$30))="","",INDEX(Properties!$A$6:$A$105,ROW()-ROW($B$30))) | G130: =IF($B130="","",SUMPRODUCT(('Compliance Log'!$A$6:$A$1005=$B130)*('Compliance Log'!$H$6:$H$1005="Overdue"))) | H130: =IF($B130="","",SUMPRODUCT(('Compliance Log'!$A$6:$A$1005=$B130)*(('Compliance Log'!$H$6:$H$1005="Due <=30")+('Compliance Log'!$H$6:$H$1005="Due 31-60")))) | I130: =IF($B130="","",SUMPRODUCT(('Compliance Log'!$A$6:$A$1005=$B130)*('Compliance Log'!$H$6:$H$1005="OK"))) | J130: =IF($B130="","",SUMPRODUCT(('Compliance Log'!$A$6:$A$1005=$B130)*('Compliance Log'!$H$6:$H$1005="No date"))) | K130: =IF($B130="","",IF($G130>0,"Overdue",IF(SUMPRODUCT(('Compliance Log'!$A$6:$A$1005=$B130)*('Compliance Log'!$H$6:$H$1005="Due <=30"))>0,"Due <=30",IF($H130>0,"Due 31-60",IF($J130>0,"No date",IF($I130>0,"OK","No checks")))))) | M130: =IF($B130="","",$G130+$H130+$I130+$J130)

Sheet PRS Database Readiness
A1: =IF(TRIM('Start Here'!$C$20)="","HMO Compliance Tracker 2026",TRIM('Start Here'!$C$20))&IF(TRIM('Start Here'!$C$21)="",""," | "&TRIM('Start Here'!$C$21))&IF(TRIM('Start Here'!$C$22)="",""," | "&TRIM('Start Here'!$C$22))&IF(TRIM('Start Here'!$C$23)="",""," | "&TRIM('Start Here'!$C$23)) -> HMO Compliance Tracker 2026
A2: PRS Database Readiness | F2: Regional dates and the landlord checklist are below the table (click)
A3: DRAFT REGULATIONS, NOT YET MADE. The Private Rented Sector Database Regulations 2026 were published as a draft statutory instrument in September 2026 and are subject to approval by Parliament, so dates, fees and data items may still change. This sheet follows the draft (legislation.gov.uk) and the GOV.UK announcement of 9 September 2026. Check GOV.UK before relying on it.
A4: PROPERTIES TRACKED | B4: READY | D4: NEARLY READY | F4: NOT READY | H4: REGISTERED | J4: EARLIEST REGISTER-BY DATE
A5: =COUNTA($A$9:$A$108) -> 2 | B5: =SUMPRODUCT(--($I$9:$I$108="Ready")) -> 0 | D5: =SUMPRODUCT(--($I$9:$I$108="Nearly")) -> 1 | F5: =SUMPRODUCT(--($I$9:$I$108="Not ready")) -> 1 | H5: =SUMPRODUCT(--($I$9:$I$108="Registered")) -> 0 | J5: =IF(COUNT($AJ$9:$AJ$108)=0,"n/a",MIN($AJ$9:$AJ$108)) -> 46460
A6: Fee per property per year (editable): | B6: 65 | C6: Estimated annual fee: | F6: =COUNTA($A$9:$A$108)*$B$6 -> 130 | H6: NRLA (not official) states £65 per property per year; the draft regulations leave the amount to the database operator (reg 14).
A7: READINESS (automatic): Ready = all 17 items done; Nearly = 3 or fewer left; Not ready = 4 or more left | K7: DRAFT SCHEDULE 3, PART 1: DWELLING INFORMATION | R7: DRAFT SCHEDULE 3, PART 2: TENANCY AND HEALTH AND SAFETY (may follow within 28 days of the entry if let; use Yes / No / N/A) | AD7: REGISTRATION AND UPDATES
A8: Property | B8: Region (pick from list) | C8: Registration opens (auto) | D8: Register by (auto) | E8: Days left (auto) | F8: Items ready (of 17) | G8: Items outstanding | H8: Ready % | I8: Status (auto) | J8: Registration status (auto) | K8: 1 Address of dwelling | L8: 2 Landlord name, correspondence address (no PO box), email | M8: 3 Ownership type | N8: 4 Dwelling type | O8: 5 Number of bedrooms | P8: 6 Whether currently let | Q8: 7 Name and email: freehold owner, superior landlord, property manager | R8: 8 Number of occupants | S8: 9 Number of households | T8: 10 HMO / additional / selective licence needed? Licence number(s) | U8: 11 Gas safety record copy (if gas supply) | V8: 11 Gas record issue date | W8: 12 EICR or EIC copy | X8: 12 EICR expiry date (or EIC issue date) | Y8: 13 EPC needed for current tenant? Copy of latest EPC | Z8: 14 If EPC no longer valid: current tenancy start date | AA8: 15 Registered MEES exemption (if EPC below minimum) | AB8: 16 Rent charged, frequency, utilities included? | AC8: 17 Furnished, part furnished or unfurnished | AD8: Registered on | AE8: Database reference | AF8: Next annual renewal (auto: 12 months) | AG8: Last change to registered information | AH8: Update database by (auto: 28-day period) | AI8: Notes
A9: SAMPLE - 12 Acacia Road, Exampleton | B9: West Midlands | C9: =IF($B9="","",IFERROR(VLOOKUP($B9,$A$112:$C$120,2,FALSE),"")) -> 46371 | D9: =IF($B9="","",IFERROR(VLOOKUP($B9,$A$112:$C$120,3,FALSE),"")) -> 46460 | E9: =IF(OR($D9="",ISNUMBER($AD9)),"",$D9-TODAY()) -> 163 | F9: =IF($A9="","",COUNTIF($K9:$T9,"Yes")+COUNTIF($K9:$T9,"N/A")+IF(OR($U9="N/A",AND($U9="Yes",ISNUMBER($V9))),1,0)+IF(OR($W9="N/A",AND($W9="Yes",ISNUMBER($X9))),1,0)+COUNTIF($Y9:$AC9,"Yes")+COUNTIF($Y9:$AC9,"N/A")) -> 15 | G9: =IF($A9="","",17-$F9) -> 2 | H9: =IF($A9="","",$F9/17) -> 0.88235294 | I9: =IF($A9="","",IF(ISNUMBER($AD9),"Registered",IF($G9=0,"Ready",IF($G9<=3,"Nearly","Not ready")))) -> Nearly | J9: =IF($A9="","",IF(ISNUMBER($AD9),"Registered",IF($D9="","Pick a region",IF(TODAY()>$D9,"OVERDUE: register now",IF(TODAY()>=$C9,"Open: register by "&TEXT($D9,"dd/mm/yyyy"),"Opens "&TEXT($C9,"dd/mm/yyyy")))))) -> Opens 15/12/2026 | K9: Yes | L9: Yes | M9: Yes | N9: Yes | O9: Yes | P9: Yes | Q9: Yes | R9: Yes | S9: Yes | T9: Yes | U9: Yes | V9: =TODAY()-(45) -> 46252 | W9: Yes | X9: =TODAY()+(300) -> 46597 | Y9: Yes | Z9: N/A | AA9: N/A | AB9: No | AC9: No | AF9: =IF(ISNUMBER($AD9),EDATE($AD9,12)-1,"") | AH9: =IF(ISNUMBER($AG9),$AG9+27,"") | AI9: SAMPLE ROW: two items outstanding, so 'Nearly' | AJ9: =IF(AND($A9<>"",ISNUMBER($D9),NOT(ISNUMBER($AD9))),$D9,"") -> 46460
A10: SAMPLE - Flat 3, 8 Demo Street, Sampleford | B10: North West | C10: =IF($B10="","",IFERROR(VLOOKUP($B10,$A$112:$C$120,2,FALSE),"")) -> 46522 | D10: =IF($B10="","",IFERROR(VLOOKUP($B10,$A$112:$C$120,3,FALSE),"")) -> 46613 | E10: =IF(OR($D10="",ISNUMBER($AD10)),"",$D10-TODAY()) -> 316 | F10: =IF($A10="","",COUNTIF($K10:$T10,"Yes")+COUNTIF($K10:$T10,"N/A")+IF(OR($U10="N/A",AND($U10="Yes",ISNUMBER($V10))),1,0)+IF(OR($W10="N/A",AND($W10="Yes",ISNUMBER($X10))),1,0)+COUNTIF($Y10:$AC10,"Yes")+COUNTIF($Y10:$AC10,"N/A")) -> 12 | G10: =IF($A10="","",17-$F10) -> 5 | H10: =IF($A10="","",$F10/17) -> 0.70588235 | I10: =IF($A10="","",IF(ISNUMBER($AD10),"Registered",IF($G10=0,"Ready",IF($G10<=3,"Nearly","Not ready")))) -> Not ready | J10: =IF($A10="","",IF(ISNUMBER($AD10),"Registered",IF($D10="","Pick a region",IF(TODAY()>$D10,"OVERDUE: register now",IF(TODAY()>=$C10,"Open: register by "&TEXT($D10,"dd/mm/yyyy"),"Opens "&TEXT($C10,"dd/mm/yyyy")))))) -> Opens 15/05/2027 | K10: Yes | L10: Yes | M10: Yes | N10: Yes | O10: Yes | P10: Yes | Q10: No | R10: Yes | S10: Yes | T10: No | U10: Yes | W10: No | Y10: Yes | Z10: N/A | AA10: N/A | AB10: No | AC10: Yes | AF10: =IF(ISNUMBER($AD10),EDATE($AD10,12)-1,"") | AH10: =IF(ISNUMBER($AG10),$AG10+27,"") | AI10: SAMPLE ROW: several items outstanding, so 'Not ready' | AJ10: =IF(AND($A10<>"",ISNUMBER($D10),NOT(ISNUMBER($AD10))),$D10,"") -> 46613
C11: =IF($B11="","",IFERROR(VLOOKUP($B11,$A$112:$C$120,2,FALSE),"")) | D11: =IF($B11="","",IFERROR(VLOOKUP($B11,$A$112:$C$120,3,FALSE),"")) | E11: =IF(OR($D11="",ISNUMBER($AD11)),"",$D11-TODAY()) | F11: =IF($A11="","",COUNTIF($K11:$T11,"Yes")+COUNTIF($K11:$T11,"N/A")+IF(OR($U11="N/A",AND($U11="Yes",ISNUMBER($V11))),1,0)+IF(OR($W11="N/A",AND($W11="Yes",ISNUMBER($X11))),1,0)+COUNTIF($Y11:$AC11,"Yes")+COUNTIF($Y11:$AC11,"N/A")) | G11: =IF($A11="","",17-$F11) | H11: =IF($A11="","",$F11/17) | I11: =IF($A11="","",IF(ISNUMBER($AD11),"Registered",IF($G11=0,"Ready",IF($G11<=3,"Nearly","Not ready")))) | J11: =IF($A11="","",IF(ISNUMBER($AD11),"Registered",IF($D11="","Pick a region",IF(TODAY()>$D11,"OVERDUE: register now",IF(TODAY()>=$C11,"Open: register by "&TEXT($D11,"dd/mm/yyyy"),"Opens "&TEXT($C11,"dd/mm/yyyy")))))) | AF11: =IF(ISNUMBER($AD11),EDATE($AD11,12)-1,"") | AH11: =IF(ISNUMBER($AG11),$AG11+27,"") | AJ11: =IF(AND($A11<>"",ISNUMBER($D11),NOT(ISNUMBER($AD11))),$D11,"")
C12: =IF($B12="","",IFERROR(VLOOKUP($B12,$A$112:$C$120,2,FALSE),"")) | D12: =IF($B12="","",IFERROR(VLOOKUP($B12,$A$112:$C$120,3,FALSE),"")) | E12: =IF(OR($D12="",ISNUMBER($AD12)),"",$D12-TODAY()) | F12: =IF($A12="","",COUNTIF($K12:$T12,"Yes")+COUNTIF($K12:$T12,"N/A")+IF(OR($U12="N/A",AND($U12="Yes",ISNUMBER($V12))),1,0)+IF(OR($W12="N/A",AND($W12="Yes",ISNUMBER($X12))),1,0)+COUNTIF($Y12:$AC12,"Yes")+COUNTIF($Y12:$AC12,"N/A")) | G12: =IF($A12="","",17-$F12) | H12: =IF($A12="","",$F12/17) | I12: =IF($A12="","",IF(ISNUMBER($AD12),"Registered",IF($G12=0,"Ready",IF($G12<=3,"Nearly","Not ready")))) | J12: =IF($A12="","",IF(ISNUMBER($AD12),"Registered",IF($D12="","Pick a region",IF(TODAY()>$D12,"OVERDUE: register now",IF(TODAY()>=$C12,"Open: register by "&TEXT($D12,"dd/mm/yyyy"),"Opens "&TEXT($C12,"dd/mm/yyyy")))))) | AF12: =IF(ISNUMBER($AD12),EDATE($AD12,12)-1,"") | AH12: =IF(ISNUMBER($AG12),$AG12+27,"") | AJ12: =IF(AND($A12<>"",ISNUMBER($D12),NOT(ISNUMBER($AD12))),$D12,"")
C13: =IF($B13="","",IFERROR(VLOOKUP($B13,$A$112:$C$120,2,FALSE),"")) | D13: =IF($B13="","",IFERROR(VLOOKUP($B13,$A$112:$C$120,3,FALSE),"")) | E13: =IF(OR($D13="",ISNUMBER($AD13)),"",$D13-TODAY()) | F13: =IF($A13="","",COUNTIF($K13:$T13,"Yes")+COUNTIF($K13:$T13,"N/A")+IF(OR($U13="N/A",AND($U13="Yes",ISNUMBER($V13))),1,0)+IF(OR($W13="N/A",AND($W13="Yes",ISNUMBER($X13))),1,0)+COUNTIF($Y13:$AC13,"Yes")+COUNTIF($Y13:$AC13,"N/A")) | G13: =IF($A13="","",17-$F13) | H13: =IF($A13="","",$F13/17) | I13: =IF($A13="","",IF(ISNUMBER($AD13),"Registered",IF($G13=0,"Ready",IF($G13<=3,"Nearly","Not ready")))) | J13: =IF($A13="","",IF(ISNUMBER($AD13),"Registered",IF($D13="","Pick a region",IF(TODAY()>$D13,"OVERDUE: register now",IF(TODAY()>=$C13,"Open: register by "&TEXT($D13,"dd/mm/yyyy"),"Opens "&TEXT($C13,"dd/mm/yyyy")))))) | AF13: =IF(ISNUMBER($AD13),EDATE($AD13,12)-1,"") | AH13: =IF(ISNUMBER($AG13),$AG13+27,"") | AJ13: =IF(AND($A13<>"",ISNUMBER($D13),NOT(ISNUMBER($AD13))),$D13,"")
C14: =IF($B14="","",IFERROR(VLOOKUP($B14,$A$112:$C$120,2,FALSE),"")) | D14: =IF($B14="","",IFERROR(VLOOKUP($B14,$A$112:$C$120,3,FALSE),"")) | E14: =IF(OR($D14="",ISNUMBER($AD14)),"",$D14-TODAY()) | F14: =IF($A14="","",COUNTIF($K14:$T14,"Yes")+COUNTIF($K14:$T14,"N/A")+IF(OR($U14="N/A",AND($U14="Yes",ISNUMBER($V14))),1,0)+IF(OR($W14="N/A",AND($W14="Yes",ISNUMBER($X14))),1,0)+COUNTIF($Y14:$AC14,"Yes")+COUNTIF($Y14:$AC14,"N/A")) | G14: =IF($A14="","",17-$F14) | H14: =IF($A14="","",$F14/17) | I14: =IF($A14="","",IF(ISNUMBER($AD14),"Registered",IF($G14=0,"Ready",IF($G14<=3,"Nearly","Not ready")))) | J14: =IF($A14="","",IF(ISNUMBER($AD14),"Registered",IF($D14="","Pick a region",IF(TODAY()>$D14,"OVERDUE: register now",IF(TODAY()>=$C14,"Open: register by "&TEXT($D14,"dd/mm/yyyy"),"Opens "&TEXT($C14,"dd/mm/yyyy")))))) | AF14: =IF(ISNUMBER($AD14),EDATE($AD14,12)-1,"") | AH14: =IF(ISNUMBER($AG14),$AG14+27,"") | AJ14: =IF(AND($A14<>"",ISNUMBER($D14),NOT(ISNUMBER($AD14))),$D14,"")
C15: =IF($B15="","",IFERROR(VLOOKUP($B15,$A$112:$C$120,2,FALSE),"")) | D15: =IF($B15="","",IFERROR(VLOOKUP($B15,$A$112:$C$120,3,FALSE),"")) | E15: =IF(OR($D15="",ISNUMBER($AD15)),"",$D15-TODAY()) | F15: =IF($A15="","",COUNTIF($K15:$T15,"Yes")+COUNTIF($K15:$T15,"N/A")+IF(OR($U15="N/A",AND($U15="Yes",ISNUMBER($V15))),1,0)+IF(OR($W15="N/A",AND($W15="Yes",ISNUMBER($X15))),1,0)+COUNTIF($Y15:$AC15,"Yes")+COUNTIF($Y15:$AC15,"N/A")) | G15: =IF($A15="","",17-$F15) | H15: =IF($A15="","",$F15/17) | I15: =IF($A15="","",IF(ISNUMBER($AD15),"Registered",IF($G15=0,"Ready",IF($G15<=3,"Nearly","Not ready")))) | J15: =IF($A15="","",IF(ISNUMBER($AD15),"Registered",IF($D15="","Pick a region",IF(TODAY()>$D15,"OVERDUE: register now",IF(TODAY()>=$C15,"Open: register by "&TEXT($D15,"dd/mm/yyyy"),"Opens "&TEXT($C15,"dd/mm/yyyy")))))) | AF15: =IF(ISNUMBER($AD15),EDATE($AD15,12)-1,"") | AH15: =IF(ISNUMBER($AG15),$AG15+27,"") | AJ15: =IF(AND($A15<>"",ISNUMBER($D15),NOT(ISNUMBER($AD15))),$D15,"")
C16: =IF($B16="","",IFERROR(VLOOKUP($B16,$A$112:$C$120,2,FALSE),"")) | D16: =IF($B16="","",IFERROR(VLOOKUP($B16,$A$112:$C$120,3,FALSE),"")) | E16: =IF(OR($D16="",ISNUMBER($AD16)),"",$D16-TODAY()) | F16: =IF($A16="","",COUNTIF($K16:$T16,"Yes")+COUNTIF($K16:$T16,"N/A")+IF(OR($U16="N/A",AND($U16="Yes",ISNUMBER($V16))),1,0)+IF(OR($W16="N/A",AND($W16="Yes",ISNUMBER($X16))),1,0)+COUNTIF($Y16:$AC16,"Yes")+COUNTIF($Y16:$AC16,"N/A")) | G16: =IF($A16="","",17-$F16) | H16: =IF($A16="","",$F16/17) | I16: =IF($A16="","",IF(ISNUMBER($AD16),"Registered",IF($G16=0,"Ready",IF($G16<=3,"Nearly","Not ready")))) | J16: =IF($A16="","",IF(ISNUMBER($AD16),"Registered",IF($D16="","Pick a region",IF(TODAY()>$D16,"OVERDUE: register now",IF(TODAY()>=$C16,"Open: register by "&TEXT($D16,"dd/mm/yyyy"),"Opens "&TEXT($C16,"dd/mm/yyyy")))))) | AF16: =IF(ISNUMBER($AD16),EDATE($AD16,12)-1,"") | AH16: =IF(ISNUMBER($AG16),$AG16+27,"") | AJ16: =IF(AND($A16<>"",ISNUMBER($D16),NOT(ISNUMBER($AD16))),$D16,"")
C17: =IF($B17="","",IFERROR(VLOOKUP($B17,$A$112:$C$120,2,FALSE),"")) | D17: =IF($B17="","",IFERROR(VLOOKUP($B17,$A$112:$C$120,3,FALSE),"")) | E17: =IF(OR($D17="",ISNUMBER($AD17)),"",$D17-TODAY()) | F17: =IF($A17="","",COUNTIF($K17:$T17,"Yes")+COUNTIF($K17:$T17,"N/A")+IF(OR($U17="N/A",AND($U17="Yes",ISNUMBER($V17))),1,0)+IF(OR($W17="N/A",AND($W17="Yes",ISNUMBER($X17))),1,0)+COUNTIF($Y17:$AC17,"Yes")+COUNTIF($Y17:$AC17,"N/A")) | G17: =IF($A17="","",17-$F17) | H17: =IF($A17="","",$F17/17) | I17: =IF($A17="","",IF(ISNUMBER($AD17),"Registered",IF($G17=0,"Ready",IF($G17<=3,"Nearly","Not ready")))) | J17: =IF($A17="","",IF(ISNUMBER($AD17),"Registered",IF($D17="","Pick a region",IF(TODAY()>$D17,"OVERDUE: register now",IF(TODAY()>=$C17,"Open: register by "&TEXT($D17,"dd/mm/yyyy"),"Opens "&TEXT($C17,"dd/mm/yyyy")))))) | AF17: =IF(ISNUMBER($AD17),EDATE($AD17,12)-1,"") | AH17: =IF(ISNUMBER($AG17),$AG17+27,"") | AJ17: =IF(AND($A17<>"",ISNUMBER($D17),NOT(ISNUMBER($AD17))),$D17,"")
C18: =IF($B18="","",IFERROR(VLOOKUP($B18,$A$112:$C$120,2,FALSE),"")) | D18: =IF($B18="","",IFERROR(VLOOKUP($B18,$A$112:$C$120,3,FALSE),"")) | E18: =IF(OR($D18="",ISNUMBER($AD18)),"",$D18-TODAY()) | F18: =IF($A18="","",COUNTIF($K18:$T18,"Yes")+COUNTIF($K18:$T18,"N/A")+IF(OR($U18="N/A",AND($U18="Yes",ISNUMBER($V18))),1,0)+IF(OR($W18="N/A",AND($W18="Yes",ISNUMBER($X18))),1,0)+COUNTIF($Y18:$AC18,"Yes")+COUNTIF($Y18:$AC18,"N/A")) | G18: =IF($A18="","",17-$F18) | H18: =IF($A18="","",$F18/17) | I18: =IF($A18="","",IF(ISNUMBER($AD18),"Registered",IF($G18=0,"Ready",IF($G18<=3,"Nearly","Not ready")))) | J18: =IF($A18="","",IF(ISNUMBER($AD18),"Registered",IF($D18="","Pick a region",IF(TODAY()>$D18,"OVERDUE: register now",IF(TODAY()>=$C18,"Open: register by "&TEXT($D18,"dd/mm/yyyy"),"Opens "&TEXT($C18,"dd/mm/yyyy")))))) | AF18: =IF(ISNUMBER($AD18),EDATE($AD18,12)-1,"") | AH18: =IF(ISNUMBER($AG18),$AG18+27,"") | AJ18: =IF(AND($A18<>"",ISNUMBER($D18),NOT(ISNUMBER($AD18))),$D18,"")
C19: =IF($B19="","",IFERROR(VLOOKUP($B19,$A$112:$C$120,2,FALSE),"")) | D19: =IF($B19="","",IFERROR(VLOOKUP($B19,$A$112:$C$120,3,FALSE),"")) | E19: =IF(OR($D19="",ISNUMBER($AD19)),"",$D19-TODAY()) | F19: =IF($A19="","",COUNTIF($K19:$T19,"Yes")+COUNTIF($K19:$T19,"N/A")+IF(OR($U19="N/A",AND($U19="Yes",ISNUMBER($V19))),1,0)+IF(OR($W19="N/A",AND($W19="Yes",ISNUMBER($X19))),1,0)+COUNTIF($Y19:$AC19,"Yes")+COUNTIF($Y19:$AC19,"N/A")) | G19: =IF($A19="","",17-$F19) | H19: =IF($A19="","",$F19/17) | I19: =IF($A19="","",IF(ISNUMBER($AD19),"Registered",IF($G19=0,"Ready",IF($G19<=3,"Nearly","Not ready")))) | J19: =IF($A19="","",IF(ISNUMBER($AD19),"Registered",IF($D19="","Pick a region",IF(TODAY()>$D19,"OVERDUE: register now",IF(TODAY()>=$C19,"Open: register by "&TEXT($D19,"dd/mm/yyyy"),"Opens "&TEXT($C19,"dd/mm/yyyy")))))) | AF19: =IF(ISNUMBER($AD19),EDATE($AD19,12)-1,"") | AH19: =IF(ISNUMBER($AG19),$AG19+27,"") | AJ19: =IF(AND($A19<>"",ISNUMBER($D19),NOT(ISNUMBER($AD19))),$D19,"")
C20: =IF($B20="","",IFERROR(VLOOKUP($B20,$A$112:$C$120,2,FALSE),"")) | D20: =IF($B20="","",IFERROR(VLOOKUP($B20,$A$112:$C$120,3,FALSE),"")) | E20: =IF(OR($D20="",ISNUMBER($AD20)),"",$D20-TODAY()) | F20: =IF($A20="","",COUNTIF($K20:$T20,"Yes")+COUNTIF($K20:$T20,"N/A")+IF(OR($U20="N/A",AND($U20="Yes",ISNUMBER($V20))),1,0)+IF(OR($W20="N/A",AND($W20="Yes",ISNUMBER($X20))),1,0)+COUNTIF($Y20:$AC20,"Yes")+COUNTIF($Y20:$AC20,"N/A")) | G20: =IF($A20="","",17-$F20) | H20: =IF($A20="","",$F20/17) | I20: =IF($A20="","",IF(ISNUMBER($AD20),"Registered",IF($G20=0,"Ready",IF($G20<=3,"Nearly","Not ready")))) | J20: =IF($A20="","",IF(ISNUMBER($AD20),"Registered",IF($D20="","Pick a region",IF(TODAY()>$D20,"OVERDUE: register now",IF(TODAY()>=$C20,"Open: register by "&TEXT($D20,"dd/mm/yyyy"),"Opens "&TEXT($C20,"dd/mm/yyyy")))))) | AF20: =IF(ISNUMBER($AD20),EDATE($AD20,12)-1,"") | AH20: =IF(ISNUMBER($AG20),$AG20+27,"") | AJ20: =IF(AND($A20<>"",ISNUMBER($D20),NOT(ISNUMBER($AD20))),$D20,"")
C21: =IF($B21="","",IFERROR(VLOOKUP($B21,$A$112:$C$120,2,FALSE),"")) | D21: =IF($B21="","",IFERROR(VLOOKUP($B21,$A$112:$C$120,3,FALSE),"")) | E21: =IF(OR($D21="",ISNUMBER($AD21)),"",$D21-TODAY()) | F21: =IF($A21="","",COUNTIF($K21:$T21,"Yes")+COUNTIF($K21:$T21,"N/A")+IF(OR($U21="N/A",AND($U21="Yes",ISNUMBER($V21))),1,0)+IF(OR($W21="N/A",AND($W21="Yes",ISNUMBER($X21))),1,0)+COUNTIF($Y21:$AC21,"Yes")+COUNTIF($Y21:$AC21,"N/A")) | G21: =IF($A21="","",17-$F21) | H21: =IF($A21="","",$F21/17) | I21: =IF($A21="","",IF(ISNUMBER($AD21),"Registered",IF($G21=0,"Ready",IF($G21<=3,"Nearly","Not ready")))) | J21: =IF($A21="","",IF(ISNUMBER($AD21),"Registered",IF($D21="","Pick a region",IF(TODAY()>$D21,"OVERDUE: register now",IF(TODAY()>=$C21,"Open: register by "&TEXT($D21,"dd/mm/yyyy"),"Opens "&TEXT($C21,"dd/mm/yyyy")))))) | AF21: =IF(ISNUMBER($AD21),EDATE($AD21,12)-1,"") | AH21: =IF(ISNUMBER($AG21),$AG21+27,"") | AJ21: =IF(AND($A21<>"",ISNUMBER($D21),NOT(ISNUMBER($AD21))),$D21,"")
C22: =IF($B22="","",IFERROR(VLOOKUP($B22,$A$112:$C$120,2,FALSE),"")) | D22: =IF($B22="","",IFERROR(VLOOKUP($B22,$A$112:$C$120,3,FALSE),"")) | E22: =IF(OR($D22="",ISNUMBER($AD22)),"",$D22-TODAY()) | F22: =IF($A22="","",COUNTIF($K22:$T22,"Yes")+COUNTIF($K22:$T22,"N/A")+IF(OR($U22="N/A",AND($U22="Yes",ISNUMBER($V22))),1,0)+IF(OR($W22="N/A",AND($W22="Yes",ISNUMBER($X22))),1,0)+COUNTIF($Y22:$AC22,"Yes")+COUNTIF($Y22:$AC22,"N/A")) | G22: =IF($A22="","",17-$F22) | H22: =IF($A22="","",$F22/17) | I22: =IF($A22="","",IF(ISNUMBER($AD22),"Registered",IF($G22=0,"Ready",IF($G22<=3,"Nearly","Not ready")))) | J22: =IF($A22="","",IF(ISNUMBER($AD22),"Registered",IF($D22="","Pick a region",IF(TODAY()>$D22,"OVERDUE: register now",IF(TODAY()>=$C22,"Open: register by "&TEXT($D22,"dd/mm/yyyy"),"Opens "&TEXT($C22,"dd/mm/yyyy")))))) | AF22: =IF(ISNUMBER($AD22),EDATE($AD22,12)-1,"") | AH22: =IF(ISNUMBER($AG22),$AG22+27,"") | AJ22: =IF(AND($A22<>"",ISNUMBER($D22),NOT(ISNUMBER($AD22))),$D22,"")
... C108: =IF($B108="","",IFERROR(VLOOKUP($B108,$A$112:$C$120,2,FALSE),"")) | D108: =IF($B108="","",IFERROR(VLOOKUP($B108,$A$112:$C$120,3,FALSE),"")) | E108: =IF(OR($D108="",ISNUMBER($AD108)),"",$D108-TODAY()) | F108: =IF($A108="","",COUNTIF($K108:$T108,"Yes")+COUNTIF($K108:$T108,"N/A")+IF(OR($U108="N/A",AND($U108="Yes",ISNUMBER($V108))),1,0)+IF(OR($W108="N/A",AND($W108="Yes",ISNUMBER($X108))),1,0)+COUNTIF($Y108:$AC108,"Yes")+COUNTIF($Y108:$AC108,"N/A")) | G108: =IF($A108="","",17-$F108) | H108: =IF($A108="","",$F108/17) | I108: =IF($A108="","",IF(ISNUMBER($AD108),"Registered",IF($G108=0,"Ready",IF($G108<=3,"Nearly","Not ready")))) | J108: =IF($A108="","",IF(ISNUMBER($AD108),"Registered",IF($D108="","Pick a region",IF(TODAY()>$D108,"OVERDUE: register now",IF(TODAY()>=$C108,"Open: register by "&TEXT($D108,"dd/mm/yyyy"),"Opens "&TEXT($C108,"dd/mm/yyyy")))))) | AF108: =IF(ISNUMBER($AD108),EDATE($AD108,12)-1,"") | AH108: =IF(ISNUMBER($AG108),$AG108+27,"") | AJ108: =IF(AND($A108<>"",ISNUMBER($D108),NOT(ISNUMBER($AD108))),$D108,"")
A110: REGIONAL ROLLOUT (draft regulations, reg 1): edit the dates here if the final regulations change them
A111: Region | B111: Registration opens | C111: Register by (opens + 3 months) | D111: Source
A112: West Midlands | B112: 46371 | C112: =EDATE($B112,3)-1 -> 46460 | D112: Draft Private Rented Sector Database Regulations 2026, reg 1(3) and Schedule 1 (list of councils in each region)
A113: East of England | B113: 46402 | C113: =EDATE($B113,3)-1 -> 46491 | D113: Draft Private Rented Sector Database Regulations 2026, reg 1(3) and Schedule 1 (list of councils in each region)
A114: East Midlands | B114: 46433 | C114: =EDATE($B114,3)-1 -> 46521 | D114: Draft Private Rented Sector Database Regulations 2026, reg 1(3) and Schedule 1 (list of councils in each region)
A115: South East | B115: 46461 | C115: =EDATE($B115,3)-1 -> 46552 | D115: Draft Private Rented Sector Database Regulations 2026, reg 1(3) and Schedule 1 (list of councils in each region)
A116: Yorkshire and Humber | B116: 46492 | C116: =EDATE($B116,3)-1 -> 46582 | D116: Draft Private Rented Sector Database Regulations 2026, reg 1(3) and Schedule 1 (list of councils in each region)
A117: North West | B117: 46522 | C117: =EDATE($B117,3)-1 -> 46613 | D117: Draft Private Rented Sector Database Regulations 2026, reg 1(3) and Schedule 1 (list of councils in each region)
A118: North East | B118: 46553 | C118: =EDATE($B118,3)-1 -> 46644 | D118: Draft Private Rented Sector Database Regulations 2026, reg 1(3) and Schedule 1 (list of councils in each region)
A119: London | B119: 46583 | C119: =EDATE($B119,3)-1 -> 46674 | D119: Draft Private Rented Sector Database Regulations 2026, reg 1(3) and Schedule 1 (list of councils in each region)
A120: South West | B120: 46614 | C120: =EDATE($B120,3)-1 -> 46705 | D120: Draft Private Rented Sector Database Regulations 2026, reg 1(3) and Schedule 1 (list of councils in each region)
A121: Register-by is the opening date plus three months, less a day (GOV.UK, 9 September 2026: a three-month period once your area is called; all landlords actively letting must be registered by 14 November 2027). Anything that becomes out of date must be updated within 28 days (the tracker counts the 28-day period as beginning on the day of the change). Entries renew every 12 months.
A122: Official draft regulations: legislation.gov.uk/ukdsi/2026/9780348286861
A123: LANDLORD ENTRY CHECKLIST (draft Schedule 2): one landlord entry covers all the properties you let
A124: Information and documents needed | I124: Ready? | J124: Notes
A125: Individual landlord: name, date of birth, residential address, telephone number and email address.
A126: Organisation: name, type of legal entity, address (not a PO box), telephone number and email address.
A127: Organisation: name, date of birth, email address and telephone number of the individual making the entry.
A128: Organisation: a nominated contact for the database (name, email address and telephone number).
A129: Organisation: Companies House registration number and/or charity number, if applicable.
A130: Organisation with no Companies House number: names, dates of birth and addresses of all directors, trustees, partners or governing-body members.
A131: Trust: name, date of birth, address, email address and telephone number of the lead trustee.
A132: Acting for the landlord (power of attorney, personal representative, receiver, liquidator and similar): your details and a copy of the evidence of your authority.
A133: Draft reg 4: entries are made by the landlord (or by the representatives listed in Schedule 2 para 17, such as an attorney or trustee in bankruptcy); a letting agent or property manager may provide the Part 2 documents on the landlord's behalf (reg 4(5)). Check the final regulations before relying on this.

Sheet Properties
A1: =IF(TRIM('Start Here'!$C$20)="","HMO Compliance Tracker 2026",TRIM('Start Here'!$C$20))&IF(TRIM('Start Here'!$C$21)="",""," | "&TRIM('Start Here'!$C$21))&IF(TRIM('Start Here'!$C$22)="",""," | "&TRIM('Start Here'!$C$22))&IF(TRIM('Start Here'!$C$23)="",""," | "&TRIM('Start Here'!$C$23)) -> HMO Compliance Tracker 2026
A2: Properties
A3: One row per property. The property name in column A must be unique: it feeds the dropdowns on the other sheets. Grey columns are automatic. Rows marked SAMPLE show how it works: clear their white cells and add your own.
A5: Property (address) - must be unique | B5: Council / local authority | C5: Licence type | D5: Licence number | E5: Licence start | F5: Licence expiry | G5: Licence days left (auto) | H5: Licence status (auto) | I5: Max permitted occupants | J5: Current occupants | K5: Over-occupied? (auto) | L5: Storeys | M5: Rooms | N5: EPC rating | O5: EPC expiry | P5: EPC status (auto) | Q5: PRS Database registration ref (new for 2026; auto from PRS Database Readiness) | R5: Manager name | S5: Manager phone | T5: Notes
A6: SAMPLE - 12 Acacia Road, Exampleton | B6: Exampleton Borough Council | C6: Mandatory HMO | D6: SAMPLE-0001 | E6: =TODAY()-(1700) -> 44597 | F6: =TODAY()+(126) -> 46423 | G6: =IF(OR($C6="",NOT(ISNUMBER($F6))),"",$F6-TODAY()) -> 126 | H6: =IF($C6="","",IF($C6="Not licensable","n/a",IF($C6="Applied-pending","Pending",IF(NOT(ISNUMBER($F6)),"No date",IF($G6<0,"Expired",IF($G6<=30,"Expires <=30",IF($G6<=60,"Expires 31-60","Valid"))))))) -> Valid | I6: 5 | J6: 6 | K6: =IF(OR(NOT(ISNUMBER($I6)),NOT(ISNUMBER($J6))),"",IF($J6>$I6,"OVER","OK")) -> OVER | L6: 3 | M6: 5 | N6: D | O6: =TODAY()-(1500) -> 44797 | P6: =IF($N6="","",IF(OR($N6="F",$N6="G"),"Below E - check",IF(NOT(ISNUMBER($O6)),"No date",IF($O6<TODAY(),"Expired",IF($O6-TODAY()<=60,"Expires <=60","Valid"))))) -> Expired | Q6: =IF($A6="","",IFERROR(IF(INDEX('PRS Database Readiness'!$AE$9:$AE$108,MATCH($A6,'PRS Database Readiness'!$A$9:$A$108,0))="","",INDEX('PRS Database Readiness'!$AE$9:$AE$108,MATCH($A6,'PRS Database Readiness'!$A$9:$A$108,0))),"")) | R6: A. Manager | S6: 01234 567890 | T6: SAMPLE ROW - delete the white cells in this row. (6 occupants vs 5 permitted shows the over-occupied flag.)
A7: SAMPLE - Flat 3, 8 Demo Street, Sampleford | B7: Sampleford City Council | C7: Additional | D7: SAMPLE-0002 | E7: =TODAY()-(900) -> 45397 | F7: =TODAY()+(40) -> 46337 | G7: =IF(OR($C7="",NOT(ISNUMBER($F7))),"",$F7-TODAY()) -> 40 | H7: =IF($C7="","",IF($C7="Not licensable","n/a",IF($C7="Applied-pending","Pending",IF(NOT(ISNUMBER($F7)),"No date",IF($G7<0,"Expired",IF($G7<=30,"Expires <=30",IF($G7<=60,"Expires 31-60","Valid"))))))) -> Expires 31-60 | I7: 4 | J7: 4 | K7: =IF(OR(NOT(ISNUMBER($I7)),NOT(ISNUMBER($J7))),"",IF($J7>$I7,"OVER","OK")) -> OK | L7: 2 | M7: 4 | N7: C | O7: =TODAY()-(2000) -> 44297 | P7: =IF($N7="","",IF(OR($N7="F",$N7="G"),"Below E - check",IF(NOT(ISNUMBER($O7)),"No date",IF($O7<TODAY(),"Expired",IF($O7-TODAY()<=60,"Expires <=60","Valid"))))) -> Expired | Q7: =IF($A7="","",IFERROR(IF(INDEX('PRS Database Readiness'!$AE$9:$AE$108,MATCH($A7,'PRS Database Readiness'!$A$9:$A$108,0))="","",INDEX('PRS Database Readiness'!$AE$9:$AE$108,MATCH($A7,'PRS Database Readiness'!$A$9:$A$108,0))),"")) | R7: A. Manager | S7: 01234 567890 | T7: SAMPLE ROW - delete the white cells in this row.
G8: =IF(OR($C8="",NOT(ISNUMBER($F8))),"",$F8-TODAY()) | H8: =IF($C8="","",IF($C8="Not licensable","n/a",IF($C8="Applied-pending","Pending",IF(NOT(ISNUMBER($F8)),"No date",IF($G8<0,"Expired",IF($G8<=30,"Expires <=30",IF($G8<=60,"Expires 31-60","Valid"))))))) | K8: =IF(OR(NOT(ISNUMBER($I8)),NOT(ISNUMBER($J8))),"",IF($J8>$I8,"OVER","OK")) | P8: =IF($N8="","",IF(OR($N8="F",$N8="G"),"Below E - check",IF(NOT(ISNUMBER($O8)),"No date",IF($O8<TODAY(),"Expired",IF($O8-TODAY()<=60,"Expires <=60","Valid"))))) | Q8: =IF($A8="","",IFERROR(IF(INDEX('PRS Database Readiness'!$AE$9:$AE$108,MATCH($A8,'PRS Database Readiness'!$A$9:$A$108,0))="","",INDEX('PRS Database Readiness'!$AE$9:$AE$108,MATCH($A8,'PRS Database Readiness'!$A$9:$A$108,0))),""))
G9: =IF(OR($C9="",NOT(ISNUMBER($F9))),"",$F9-TODAY()) | H9: =IF($C9="","",IF($C9="Not licensable","n/a",IF($C9="Applied-pending","Pending",IF(NOT(ISNUMBER($F9)),"No date",IF($G9<0,"Expired",IF($G9<=30,"Expires <=30",IF($G9<=60,"Expires 31-60","Valid"))))))) | K9: =IF(OR(NOT(ISNUMBER($I9)),NOT(ISNUMBER($J9))),"",IF($J9>$I9,"OVER","OK")) | P9: =IF($N9="","",IF(OR($N9="F",$N9="G"),"Below E - check",IF(NOT(ISNUMBER($O9)),"No date",IF($O9<TODAY(),"Expired",IF($O9-TODAY()<=60,"Expires <=60","Valid"))))) | Q9: =IF($A9="","",IFERROR(IF(INDEX('PRS Database Readiness'!$AE$9:$AE$108,MATCH($A9,'PRS Database Readiness'!$A$9:$A$108,0))="","",INDEX('PRS Database Readiness'!$AE$9:$AE$108,MATCH($A9,'PRS Database Readiness'!$A$9:$A$108,0))),""))
G10: =IF(OR($C10="",NOT(ISNUMBER($F10))),"",$F10-TODAY()) | H10: =IF($C10="","",IF($C10="Not licensable","n/a",IF($C10="Applied-pending","Pending",IF(NOT(ISNUMBER($F10)),"No date",IF($G10<0,"Expired",IF($G10<=30,"Expires <=30",IF($G10<=60,"Expires 31-60","Valid"))))))) | K10: =IF(OR(NOT(ISNUMBER($I10)),NOT(ISNUMBER($J10))),"",IF($J10>$I10,"OVER","OK")) | P10: =IF($N10="","",IF(OR($N10="F",$N10="G"),"Below E - check",IF(NOT(ISNUMBER($O10)),"No date",IF($O10<TODAY(),"Expired",IF($O10-TODAY()<=60,"Expires <=60","Valid"))))) | Q10: =IF($A10="","",IFERROR(IF(INDEX('PRS Database Readiness'!$AE$9:$AE$108,MATCH($A10,'PRS Database Readiness'!$A$9:$A$108,0))="","",INDEX('PRS Database Readiness'!$AE$9:$AE$108,MATCH($A10,'PRS Database Readiness'!$A$9:$A$108,0))),""))
G11: =IF(OR($C11="",NOT(ISNUMBER($F11))),"",$F11-TODAY()) | H11: =IF($C11="","",IF($C11="Not licensable","n/a",IF($C11="Applied-pending","Pending",IF(NOT(ISNUMBER($F11)),"No date",IF($G11<0,"Expired",IF($G11<=30,"Expires <=30",IF($G11<=60,"Expires 31-60","Valid"))))))) | K11: =IF(OR(NOT(ISNUMBER($I11)),NOT(ISNUMBER($J11))),"",IF($J11>$I11,"OVER","OK")) | P11: =IF($N11="","",IF(OR($N11="F",$N11="G"),"Below E - check",IF(NOT(ISNUMBER($O11)),"No date",IF($O11<TODAY(),"Expired",IF($O11-TODAY()<=60,"Expires <=60","Valid"))))) | Q11: =IF($A11="","",IFERROR(IF(INDEX('PRS Database Readiness'!$AE$9:$AE$108,MATCH($A11,'PRS Database Readiness'!$A$9:$A$108,0))="","",INDEX('PRS Database Readiness'!$AE$9:$AE$108,MATCH($A11,'PRS Database Readiness'!$A$9:$A$108,0))),""))
G12: =IF(OR($C12="",NOT(ISNUMBER($F12))),"",$F12-TODAY()) | H12: =IF($C12="","",IF($C12="Not licensable","n/a",IF($C12="Applied-pending","Pending",IF(NOT(ISNUMBER($F12)),"No date",IF($G12<0,"Expired",IF($G12<=30,"Expires <=30",IF($G12<=60,"Expires 31-60","Valid"))))))) | K12: =IF(OR(NOT(ISNUMBER($I12)),NOT(ISNUMBER($J12))),"",IF($J12>$I12,"OVER","OK")) | P12: =IF($N12="","",IF(OR($N12="F",$N12="G"),"Below E - check",IF(NOT(ISNUMBER($O12)),"No date",IF($O12<TODAY(),"Expired",IF($O12-TODAY()<=60,"Expires <=60","Valid"))))) | Q12: =IF($A12="","",IFERROR(IF(INDEX('PRS Database Readiness'!$AE$9:$AE$108,MATCH($A12,'PRS Database Readiness'!$A$9:$A$108,0))="","",INDEX('PRS Database Readiness'!$AE$9:$AE$108,MATCH($A12,'PRS Database Readiness'!$A$9:$A$108,0))),""))
G13: =IF(OR($C13="",NOT(ISNUMBER($F13))),"",$F13-TODAY()) | H13: =IF($C13="","",IF($C13="Not licensable","n/a",IF($C13="Applied-pending","Pending",IF(NOT(ISNUMBER($F13)),"No date",IF($G13<0,"Expired",IF($G13<=30,"Expires <=30",IF($G13<=60,"Expires 31-60","Valid"))))))) | K13: =IF(OR(NOT(ISNUMBER($I13)),NOT(ISNUMBER($J13))),"",IF($J13>$I13,"OVER","OK")) | P13: =IF($N13="","",IF(OR($N13="F",$N13="G"),"Below E - check",IF(NOT(ISNUMBER($O13)),"No date",IF($O13<TODAY(),"Expired",IF($O13-TODAY()<=60,"Expires <=60","Valid"))))) | Q13: =IF($A13="","",IFERROR(IF(INDEX('PRS Database Readiness'!$AE$9:$AE$108,MATCH($A13,'PRS Database Readiness'!$A$9:$A$108,0))="","",INDEX('PRS Database Readiness'!$AE$9:$AE$108,MATCH($A13,'PRS Database Readiness'!$A$9:$A$108,0))),""))
G14: =IF(OR($C14="",NOT(ISNUMBER($F14))),"",$F14-TODAY()) | H14: =IF($C14="","",IF($C14="Not licensable","n/a",IF($C14="Applied-pending","Pending",IF(NOT(ISNUMBER($F14)),"No date",IF($G14<0,"Expired",IF($G14<=30,"Expires <=30",IF($G14<=60,"Expires 31-60","Valid"))))))) | K14: =IF(OR(NOT(ISNUMBER($I14)),NOT(ISNUMBER($J14))),"",IF($J14>$I14,"OVER","OK")) | P14: =IF($N14="","",IF(OR($N14="F",$N14="G"),"Below E - check",IF(NOT(ISNUMBER($O14)),"No date",IF($O14<TODAY(),"Expired",IF($O14-TODAY()<=60,"Expires <=60","Valid"))))) | Q14: =IF($A14="","",IFERROR(IF(INDEX('PRS Database Readiness'!$AE$9:$AE$108,MATCH($A14,'PRS Database Readiness'!$A$9:$A$108,0))="","",INDEX('PRS Database Readiness'!$AE$9:$AE$108,MATCH($A14,'PRS Database Readiness'!$A$9:$A$108,0))),""))
G15: =IF(OR($C15="",NOT(ISNUMBER($F15))),"",$F15-TODAY()) | H15: =IF($C15="","",IF($C15="Not licensable","n/a",IF($C15="Applied-pending","Pending",IF(NOT(ISNUMBER($F15)),"No date",IF($G15<0,"Expired",IF($G15<=30,"Expires <=30",IF($G15<=60,"Expires 31-60","Valid"))))))) | K15: =IF(OR(NOT(ISNUMBER($I15)),NOT(ISNUMBER($J15))),"",IF($J15>$I15,"OVER","OK")) | P15: =IF($N15="","",IF(OR($N15="F",$N15="G"),"Below E - check",IF(NOT(ISNUMBER($O15)),"No date",IF($O15<TODAY(),"Expired",IF($O15-TODAY()<=60,"Expires <=60","Valid"))))) | Q15: =IF($A15="","",IFERROR(IF(INDEX('PRS Database Readiness'!$AE$9:$AE$108,MATCH($A15,'PRS Database Readiness'!$A$9:$A$108,0))="","",INDEX('PRS Database Readiness'!$AE$9:$AE$108,MATCH($A15,'PRS Database Readiness'!$A$9:$A$108,0))),""))
G16: =IF(OR($C16="",NOT(ISNUMBER($F16))),"",$F16-TODAY()) | H16: =IF($C16="","",IF($C16="Not licensable","n/a",IF($C16="Applied-pending","Pending",IF(NOT(ISNUMBER($F16)),"No date",IF($G16<0,"Expired",IF($G16<=30,"Expires <=30",IF($G16<=60,"Expires 31-60","Valid"))))))) | K16: =IF(OR(NOT(ISNUMBER($I16)),NOT(ISNUMBER($J16))),"",IF($J16>$I16,"OVER","OK")) | P16: =IF($N16="","",IF(OR($N16="F",$N16="G"),"Below E - check",IF(NOT(ISNUMBER($O16)),"No date",IF($O16<TODAY(),"Expired",IF($O16-TODAY()<=60,"Expires <=60","Valid"))))) | Q16: =IF($A16="","",IFERROR(IF(INDEX('PRS Database Readiness'!$AE$9:$AE$108,MATCH($A16,'PRS Database Readiness'!$A$9:$A$108,0))="","",INDEX('PRS Database Readiness'!$AE$9:$AE$108,MATCH($A16,'PRS Database Readiness'!$A$9:$A$108,0))),""))
G17: =IF(OR($C17="",NOT(ISNUMBER($F17))),"",$F17-TODAY()) | H17: =IF($C17="","",IF($C17="Not licensable","n/a",IF($C17="Applied-pending","Pending",IF(NOT(ISNUMBER($F17)),"No date",IF($G17<0,"Expired",IF($G17<=30,"Expires <=30",IF($G17<=60,"Expires 31-60","Valid"))))))) | K17: =IF(OR(NOT(ISNUMBER($I17)),NOT(ISNUMBER($J17))),"",IF($J17>$I17,"OVER","OK")) | P17: =IF($N17="","",IF(OR($N17="F",$N17="G"),"Below E - check",IF(NOT(ISNUMBER($O17)),"No date",IF($O17<TODAY(),"Expired",IF($O17-TODAY()<=60,"Expires <=60","Valid"))))) | Q17: =IF($A17="","",IFERROR(IF(INDEX('PRS Database Readiness'!$AE$9:$AE$108,MATCH($A17,'PRS Database Readiness'!$A$9:$A$108,0))="","",INDEX('PRS Database Readiness'!$AE$9:$AE$108,MATCH($A17,'PRS Database Readiness'!$A$9:$A$108,0))),""))
G18: =IF(OR($C18="",NOT(ISNUMBER($F18))),"",$F18-TODAY()) | H18: =IF($C18="","",IF($C18="Not licensable","n/a",IF($C18="Applied-pending","Pending",IF(NOT(ISNUMBER($F18)),"No date",IF($G18<0,"Expired",IF($G18<=30,"Expires <=30",IF($G18<=60,"Expires 31-60","Valid"))))))) | K18: =IF(OR(NOT(ISNUMBER($I18)),NOT(ISNUMBER($J18))),"",IF($J18>$I18,"OVER","OK")) | P18: =IF($N18="","",IF(OR($N18="F",$N18="G"),"Below E - check",IF(NOT(ISNUMBER($O18)),"No date",IF($O18<TODAY(),"Expired",IF($O18-TODAY()<=60,"Expires <=60","Valid"))))) | Q18: =IF($A18="","",IFERROR(IF(INDEX('PRS Database Readiness'!$AE$9:$AE$108,MATCH($A18,'PRS Database Readiness'!$A$9:$A$108,0))="","",INDEX('PRS Database Readiness'!$AE$9:$AE$108,MATCH($A18,'PRS Database Readiness'!$A$9:$A$108,0))),""))
G19: =IF(OR($C19="",NOT(ISNUMBER($F19))),"",$F19-TODAY()) | H19: =IF($C19="","",IF($C19="Not licensable","n/a",IF($C19="Applied-pending","Pending",IF(NOT(ISNUMBER($F19)),"No date",IF($G19<0,"Expired",IF($G19<=30,"Expires <=30",IF($G19<=60,"Expires 31-60","Valid"))))))) | K19: =IF(OR(NOT(ISNUMBER($I19)),NOT(ISNUMBER($J19))),"",IF($J19>$I19,"OVER","OK")) | P19: =IF($N19="","",IF(OR($N19="F",$N19="G"),"Below E - check",IF(NOT(ISNUMBER($O19)),"No date",IF($O19<TODAY(),"Expired",IF($O19-TODAY()<=60,"Expires <=60","Valid"))))) | Q19: =IF($A19="","",IFERROR(IF(INDEX('PRS Database Readiness'!$AE$9:$AE$108,MATCH($A19,'PRS Database Readiness'!$A$9:$A$108,0))="","",INDEX('PRS Database Readiness'!$AE$9:$AE$108,MATCH($A19,'PRS Database Readiness'!$A$9:$A$108,0))),""))
... G105: =IF(OR($C105="",NOT(ISNUMBER($F105))),"",$F105-TODAY()) | H105: =IF($C105="","",IF($C105="Not licensable","n/a",IF($C105="Applied-pending","Pending",IF(NOT(ISNUMBER($F105)),"No date",IF($G105<0,"Expired",IF($G105<=30,"Expires <=30",IF($G105<=60,"Expires 31-60","Valid"))))))) | K105: =IF(OR(NOT(ISNUMBER($I105)),NOT(ISNUMBER($J105))),"",IF($J105>$I105,"OVER","OK")) | P105: =IF($N105="","",IF(OR($N105="F",$N105="G"),"Below E - check",IF(NOT(ISNUMBER($O105)),"No date",IF($O105<TODAY(),"Expired",IF($O105-TODAY()<=60,"Expires <=60","Valid"))))) | Q105: =IF($A105="","",IFERROR(IF(INDEX('PRS Database Readiness'!$AE$9:$AE$108,MATCH($A105,'PRS Database Readiness'!$A$9:$A$108,0))="","",INDEX('PRS Database Readiness'!$AE$9:$AE$108,MATCH($A105,'PRS Database Readiness'!$A$9:$A$108,0))),""))

Sheet Compliance Log
A1: =IF(TRIM('Start Here'!$C$20)="","HMO Compliance Tracker 2026",TRIM('Start Here'!$C$20))&IF(TRIM('Start Here'!$C$21)="",""," | "&TRIM('Start Here'!$C$21))&IF(TRIM('Start Here'!$C$22)="",""," | "&TRIM('Start Here'!$C$22))&IF(TRIM('Start Here'!$C$23)="",""," | "&TRIM('Start Here'!$C$23)) -> HMO Compliance Tracker 2026
A2: Compliance Log
A3: One row per property and check. Pick the Property and Check type, then enter the date it was Last done. Interval, Next due, Days left and Status fill in automatically (grey columns). To use a different interval for one row, type the number of months in 'Override months'. Rows marked SAMPLE show how it works.
B4: Status colours: | C4: Overdue | D4: Due <=30 | E4: Due 31-60 | F4: OK | G4: No date
A5: Property | B5: Check type | C5: Last done | D5: Interval months (auto from Reference) | E5: Override months (optional) | F5: Next due (auto) | G5: Days left (auto) | H5: Status (auto) | I5: Contractor | J5: Certificate / ref no. | K5: Document link (URL) | L5: Notes | M5: key
A6: SAMPLE - 12 Acacia Road, Exampleton | B6: Gas Safety Certificate (CP12) | C6: =TODAY()-(390) -> 45907 | D6: =IF($B6="","",IFERROR(IF(VLOOKUP($B6,Reference!$A$6:$C$27,3,FALSE)>0,VLOOKUP($B6,Reference!$A$6:$C$27,3,FALSE),""),"")) -> 12 | F6: =IF(OR($A6="",$B6="",NOT(ISNUMBER($C6))),"",IF(ISNUMBER($E6),IF($E6>0,EDATE($C6,$E6),""),IF(ISNUMBER($D6),EDATE($C6,$D6),""))) -> 46272 | G6: =IF($F6="","",$F6-TODAY()) -> -25 | H6: =IF(OR($A6="",$B6=""),"",IF($F6="","No date",IF($G6<0,"Overdue",IF($G6<=30,"Due <=30",IF($G6<=60,"Due 31-60","OK"))))) -> Overdue | I6: SAMPLE Gas Engineer Ltd | J6: SAMPLE-CP12-001 | L6: SAMPLE ROW: overdue example (red) | M6: =IF($F6="","",$F6+ROW()/100000) -> 46272
A7: SAMPLE - 12 Acacia Road, Exampleton | B7: Electrical Installation Condition Report (EICR) | C7: =TODAY()-(1500) -> 44797 | D7: =IF($B7="","",IFERROR(IF(VLOOKUP($B7,Reference!$A$6:$C$27,3,FALSE)>0,VLOOKUP($B7,Reference!$A$6:$C$27,3,FALSE),""),"")) -> 60 | F7: =IF(OR($A7="",$B7="",NOT(ISNUMBER($C7))),"",IF(ISNUMBER($E7),IF($E7>0,EDATE($C7,$E7),""),IF(ISNUMBER($D7),EDATE($C7,$D7),""))) -> 46623 | G7: =IF($F7="","",$F7-TODAY()) -> 326 | H7: =IF(OR($A7="",$B7=""),"",IF($F7="","No date",IF($G7<0,"Overdue",IF($G7<=30,"Due <=30",IF($G7<=60,"Due 31-60","OK"))))) -> OK | I7: SAMPLE Electrics Ltd | J7: SAMPLE-EICR-014 | L7: SAMPLE ROW: OK example (green) | M7: =IF($F7="","",$F7+ROW()/100000) -> 46623
A8: SAMPLE - 12 Acacia Road, Exampleton | B8: Fire Risk Assessment - review | C8: =TODAY()-(320) -> 45977 | D8: =IF($B8="","",IFERROR(IF(VLOOKUP($B8,Reference!$A$6:$C$27,3,FALSE)>0,VLOOKUP($B8,Reference!$A$6:$C$27,3,FALSE),""),"")) -> 12 | F8: =IF(OR($A8="",$B8="",NOT(ISNUMBER($C8))),"",IF(ISNUMBER($E8),IF($E8>0,EDATE($C8,$E8),""),IF(ISNUMBER($D8),EDATE($C8,$D8),""))) -> 46342 | G8: =IF($F8="","",$F8-TODAY()) -> 45 | H8: =IF(OR($A8="",$B8=""),"",IF($F8="","No date",IF($G8<0,"Overdue",IF($G8<=30,"Due <=30",IF($G8<=60,"Due 31-60","OK"))))) -> Due 31-60 | I8: SAMPLE Fire Safety Ltd | J8: SAMPLE-FRA-2025 | L8: SAMPLE ROW: due in 31 to 60 days (yellow) | M8: =IF($F8="","",$F8+ROW()/100000) -> 46342
A9: SAMPLE - 12 Acacia Road, Exampleton | B9: Fire alarm system - service | C9: =TODAY()-(60) -> 46237 | D9: =IF($B9="","",IFERROR(IF(VLOOKUP($B9,Reference!$A$6:$C$27,3,FALSE)>0,VLOOKUP($B9,Reference!$A$6:$C$27,3,FALSE),""),"")) -> 6 | F9: =IF(OR($A9="",$B9="",NOT(ISNUMBER($C9))),"",IF(ISNUMBER($E9),IF($E9>0,EDATE($C9,$E9),""),IF(ISNUMBER($D9),EDATE($C9,$D9),""))) -> 46421 | G9: =IF($F9="","",$F9-TODAY()) -> 124 | H9: =IF(OR($A9="",$B9=""),"",IF($F9="","No date",IF($G9<0,"Overdue",IF($G9<=30,"Due <=30",IF($G9<=60,"Due 31-60","OK"))))) -> OK | I9: SAMPLE Fire Safety Ltd | J9: SAMPLE-FA-0526 | L9: SAMPLE ROW | M9: =IF($F9="","",$F9+ROW()/100000) -> 46421
A10: SAMPLE - 12 Acacia Road, Exampleton | B10: Emergency lighting - annual full-discharge test | C10: =TODAY()-(350) -> 45947 | D10: =IF($B10="","",IFERROR(IF(VLOOKUP($B10,Reference!$A$6:$C$27,3,FALSE)>0,VLOOKUP($B10,Reference!$A$6:$C$27,3,FALSE),""),"")) -> 12 | F10: =IF(OR($A10="",$B10="",NOT(ISNUMBER($C10))),"",IF(ISNUMBER($E10),IF($E10>0,EDATE($C10,$E10),""),IF(ISNUMBER($D10),EDATE($C10,$D10),""))) -> 46312 | G10: =IF($F10="","",$F10-TODAY()) -> 15 | H10: =IF(OR($A10="",$B10=""),"",IF($F10="","No date",IF($G10<0,"Overdue",IF($G10<=30,"Due <=30",IF($G10<=60,"Due 31-60","OK"))))) -> Due <=30 | I10: SAMPLE Fire Safety Ltd | J10: SAMPLE-EL-1025 | L10: SAMPLE ROW: due within 30 days (orange) | M10: =IF($F10="","",$F10+ROW()/100000) -> 46312
A11: SAMPLE - 12 Acacia Road, Exampleton | B11: Fire extinguishers - service | C11: =TODAY()-(90) -> 46207 | D11: =IF($B11="","",IFERROR(IF(VLOOKUP($B11,Reference!$A$6:$C$27,3,FALSE)>0,VLOOKUP($B11,Reference!$A$6:$C$27,3,FALSE),""),"")) -> 12 | F11: =IF(OR($A11="",$B11="",NOT(ISNUMBER($C11))),"",IF(ISNUMBER($E11),IF($E11>0,EDATE($C11,$E11),""),IF(ISNUMBER($D11),EDATE($C11,$D11),""))) -> 46572 | G11: =IF($F11="","",$F11-TODAY()) -> 275 | H11: =IF(OR($A11="",$B11=""),"",IF($F11="","No date",IF($G11<0,"Overdue",IF($G11<=30,"Due <=30",IF($G11<=60,"Due 31-60","OK"))))) -> OK | I11: SAMPLE Fire Safety Ltd | J11: SAMPLE-FE-0726 | L11: SAMPLE ROW | M11: =IF($F11="","",$F11+ROW()/100000) -> 46572
A12: SAMPLE - 12 Acacia Road, Exampleton | B12: Portable appliance testing (PAT) | C12: =TODAY()-(700) -> 45597 | D12: =IF($B12="","",IFERROR(IF(VLOOKUP($B12,Reference!$A$6:$C$27,3,FALSE)>0,VLOOKUP($B12,Reference!$A$6:$C$27,3,FALSE),""),"")) -> 12 | F12: =IF(OR($A12="",$B12="",NOT(ISNUMBER($C12))),"",IF(ISNUMBER($E12),IF($E12>0,EDATE($C12,$E12),""),IF(ISNUMBER($D12),EDATE($C12,$D12),""))) -> 45962 | G12: =IF($F12="","",$F12-TODAY()) -> -335 | H12: =IF(OR($A12="",$B12=""),"",IF($F12="","No date",IF($G12<0,"Overdue",IF($G12<=30,"Due <=30",IF($G12<=60,"Due 31-60","OK"))))) -> Overdue | L12: SAMPLE ROW: overdue example (red) | M12: =IF($F12="","",$F12+ROW()/100000) -> 45962
A13: SAMPLE - 12 Acacia Road, Exampleton | B13: HMO licence renewal | C13: =TODAY()-(1700) -> 44597 | D13: =IF($B13="","",IFERROR(IF(VLOOKUP($B13,Reference!$A$6:$C$27,3,FALSE)>0,VLOOKUP($B13,Reference!$A$6:$C$27,3,FALSE),""),"")) -> 60 | F13: =IF(OR($A13="",$B13="",NOT(ISNUMBER($C13))),"",IF(ISNUMBER($E13),IF($E13>0,EDATE($C13,$E13),""),IF(ISNUMBER($D13),EDATE($C13,$D13),""))) -> 46423 | G13: =IF($F13="","",$F13-TODAY()) -> 126 | H13: =IF(OR($A13="",$B13=""),"",IF($F13="","No date",IF($G13<0,"Overdue",IF($G13<=30,"Due <=30",IF($G13<=60,"Due 31-60","OK"))))) -> OK | J13: SAMPLE-0001 | L13: SAMPLE ROW: last done = licence start | M13: =IF($F13="","",$F13+ROW()/100000) -> 46423
A14: SAMPLE - Flat 3, 8 Demo Street, Sampleford | B14: Gas Safety Certificate (CP12) | C14: =TODAY()-(120) -> 46177 | D14: =IF($B14="","",IFERROR(IF(VLOOKUP($B14,Reference!$A$6:$C$27,3,FALSE)>0,VLOOKUP($B14,Reference!$A$6:$C$27,3,FALSE),""),"")) -> 12 | F14: =IF(OR($A14="",$B14="",NOT(ISNUMBER($C14))),"",IF(ISNUMBER($E14),IF($E14>0,EDATE($C14,$E14),""),IF(ISNUMBER($D14),EDATE($C14,$D14),""))) -> 46542 | G14: =IF($F14="","",$F14-TODAY()) -> 245 | H14: =IF(OR($A14="",$B14=""),"",IF($F14="","No date",IF($G14<0,"Overdue",IF($G14<=30,"Due <=30",IF($G14<=60,"Due 31-60","OK"))))) -> OK | I14: SAMPLE Gas Engineer Ltd | J14: SAMPLE-CP12-002 | L14: SAMPLE ROW | M14: =IF($F14="","",$F14+ROW()/100000) -> 46542
A15: SAMPLE - Flat 3, 8 Demo Street, Sampleford | B15: Electrical Installation Condition Report (EICR) | C15: =TODAY()-(1790) -> 44507 | D15: =IF($B15="","",IFERROR(IF(VLOOKUP($B15,Reference!$A$6:$C$27,3,FALSE)>0,VLOOKUP($B15,Reference!$A$6:$C$27,3,FALSE),""),"")) -> 60 | F15: =IF(OR($A15="",$B15="",NOT(ISNUMBER($C15))),"",IF(ISNUMBER($E15),IF($E15>0,EDATE($C15,$E15),""),IF(ISNUMBER($D15),EDATE($C15,$D15),""))) -> 46333 | G15: =IF($F15="","",$F15-TODAY()) -> 36 | H15: =IF(OR($A15="",$B15=""),"",IF($F15="","No date",IF($G15<0,"Overdue",IF($G15<=30,"Due <=30",IF($G15<=60,"Due 31-60","OK"))))) -> Due 31-60 | I15: SAMPLE Electrics Ltd | J15: SAMPLE-EICR-009 | L15: SAMPLE ROW: due in 31 to 60 days (yellow) | M15: =IF($F15="","",$F15+ROW()/100000) -> 46333
A16: SAMPLE - Flat 3, 8 Demo Street, Sampleford | B16: Fire Risk Assessment - review | D16: =IF($B16="","",IFERROR(IF(VLOOKUP($B16,Reference!$A$6:$C$27,3,FALSE)>0,VLOOKUP($B16,Reference!$A$6:$C$27,3,FALSE),""),"")) -> 12 | F16: =IF(OR($A16="",$B16="",NOT(ISNUMBER($C16))),"",IF(ISNUMBER($E16),IF($E16>0,EDATE($C16,$E16),""),IF(ISNUMBER($D16),EDATE($C16,$D16),""))) | G16: =IF($F16="","",$F16-TODAY()) | H16: =IF(OR($A16="",$B16=""),"",IF($F16="","No date",IF($G16<0,"Overdue",IF($G16<=30,"Due <=30",IF($G16<=60,"Due 31-60","OK"))))) -> No date | L16: SAMPLE ROW: no date entered yet (grey) | M16: =IF($F16="","",$F16+ROW()/100000)
A17: SAMPLE - Flat 3, 8 Demo Street, Sampleford | B17: Energy Performance Certificate (EPC) | C17: =TODAY()-(2000) -> 44297 | D17: =IF($B17="","",IFERROR(IF(VLOOKUP($B17,Reference!$A$6:$C$27,3,FALSE)>0,VLOOKUP($B17,Reference!$A$6:$C$27,3,FALSE),""),"")) -> 120 | F17: =IF(OR($A17="",$B17="",NOT(ISNUMBER($C17))),"",IF(ISNUMBER($E17),IF($E17>0,EDATE($C17,$E17),""),IF(ISNUMBER($D17),EDATE($C17,$D17),""))) -> 47949 | G17: =IF($F17="","",$F17-TODAY()) -> 1652 | H17: =IF(OR($A17="",$B17=""),"",IF($F17="","No date",IF($G17<0,"Overdue",IF($G17<=30,"Due <=30",IF($G17<=60,"Due 31-60","OK"))))) -> OK | J17: SAMPLE-EPC-5521 | L17: SAMPLE ROW | M17: =IF($F17="","",$F17+ROW()/100000) -> 47949
A18: SAMPLE - Flat 3, 8 Demo Street, Sampleford | B18: Smoke & CO alarms - check | C18: =TODAY()-(420) -> 45877 | D18: =IF($B18="","",IFERROR(IF(VLOOKUP($B18,Reference!$A$6:$C$27,3,FALSE)>0,VLOOKUP($B18,Reference!$A$6:$C$27,3,FALSE),""),"")) -> 12 | F18: =IF(OR($A18="",$B18="",NOT(ISNUMBER($C18))),"",IF(ISNUMBER($E18),IF($E18>0,EDATE($C18,$E18),""),IF(ISNUMBER($D18),EDATE($C18,$D18),""))) -> 46242 | G18: =IF($F18="","",$F18-TODAY()) -> -55 | H18: =IF(OR($A18="",$B18=""),"",IF($F18="","No date",IF($G18<0,"Overdue",IF($G18<=30,"Due <=30",IF($G18<=60,"Due 31-60","OK"))))) -> Overdue | L18: SAMPLE ROW: overdue example (red) | M18: =IF($F18="","",$F18+ROW()/100000) -> 46242
A19: SAMPLE - Flat 3, 8 Demo Street, Sampleford | B19: Fire extinguishers - service | C19: =TODAY()-(345) -> 45952 | D19: =IF($B19="","",IFERROR(IF(VLOOKUP($B19,Reference!$A$6:$C$27,3,FALSE)>0,VLOOKUP($B19,Reference!$A$6:$C$27,3,FALSE),""),"")) -> 12 | F19: =IF(OR($A19="",$B19="",NOT(ISNUMBER($C19))),"",IF(ISNUMBER($E19),IF($E19>0,EDATE($C19,$E19),""),IF(ISNUMBER($D19),EDATE($C19,$D19),""))) -> 46317 | G19: =IF($F19="","",$F19-TODAY()) -> 20 | H19: =IF(OR($A19="",$B19=""),"",IF($F19="","No date",IF($G19<0,"Overdue",IF($G19<=30,"Due <=30",IF($G19<=60,"Due 31-60","OK"))))) -> Due <=30 | I19: SAMPLE Fire Safety Ltd | J19: SAMPLE-FE-1125 | L19: SAMPLE ROW: due within 30 days (orange) | M19: =IF($F19="","",$F19+ROW()/100000) -> 46317
A20: SAMPLE - Flat 3, 8 Demo Street, Sampleford | B20: HMO licence renewal | C20: =TODAY()-(1786) -> 44511 | D20: =IF($B20="","",IFERROR(IF(VLOOKUP($B20,Reference!$A$6:$C$27,3,FALSE)>0,VLOOKUP($B20,Reference!$A$6:$C$27,3,FALSE),""),"")) -> 60 | F20: =IF(OR($A20="",$B20="",NOT(ISNUMBER($C20))),"",IF(ISNUMBER($E20),IF($E20>0,EDATE($C20,$E20),""),IF(ISNUMBER($D20),EDATE($C20,$D20),""))) -> 46337 | G20: =IF($F20="","",$F20-TODAY()) -> 40 | H20: =IF(OR($A20="",$B20=""),"",IF($F20="","No date",IF($G20<0,"Overdue",IF($G20<=30,"Due <=30",IF($G20<=60,"Due 31-60","OK"))))) -> Due 31-60 | J20: SAMPLE-0002 | L20: SAMPLE ROW: licence ends soon (yellow) | M20: =IF($F20="","",$F20+ROW()/100000) -> 46337
D21: =IF($B21="","",IFERROR(IF(VLOOKUP($B21,Reference!$A$6:$C$27,3,FALSE)>0,VLOOKUP($B21,Reference!$A$6:$C$27,3,FALSE),""),"")) | F21: =IF(OR($A21="",$B21="",NOT(ISNUMBER($C21))),"",IF(ISNUMBER($E21),IF($E21>0,EDATE($C21,$E21),""),IF(ISNUMBER($D21),EDATE($C21,$D21),""))) | G21: =IF($F21="","",$F21-TODAY()) | H21: =IF(OR($A21="",$B21=""),"",IF($F21="","No date",IF($G21<0,"Overdue",IF($G21<=30,"Due <=30",IF($G21<=60,"Due 31-60","OK"))))) | M21: =IF($F21="","",$F21+ROW()/100000)
D22: =IF($B22="","",IFERROR(IF(VLOOKUP($B22,Reference!$A$6:$C$27,3,FALSE)>0,VLOOKUP($B22,Reference!$A$6:$C$27,3,FALSE),""),"")) | F22: =IF(OR($A22="",$B22="",NOT(ISNUMBER($C22))),"",IF(ISNUMBER($E22),IF($E22>0,EDATE($C22,$E22),""),IF(ISNUMBER($D22),EDATE($C22,$D22),""))) | G22: =IF($F22="","",$F22-TODAY()) | H22: =IF(OR($A22="",$B22=""),"",IF($F22="","No date",IF($G22<0,"Overdue",IF($G22<=30,"Due <=30",IF($G22<=60,"Due 31-60","OK"))))) | M22: =IF($F22="","",$F22+ROW()/100000)
D23: =IF($B23="","",IFERROR(IF(VLOOKUP($B23,Reference!$A$6:$C$27,3,FALSE)>0,VLOOKUP($B23,Reference!$A$6:$C$27,3,FALSE),""),"")) | F23: =IF(OR($A23="",$B23="",NOT(ISNUMBER($C23))),"",IF(ISNUMBER($E23),IF($E23>0,EDATE($C23,$E23),""),IF(ISNUMBER($D23),EDATE($C23,$D23),""))) | G23: =IF($F23="","",$F23-TODAY()) | H23: =IF(OR($A23="",$B23=""),"",IF($F23="","No date",IF($G23<0,"Overdue",IF($G23<=30,"Due <=30",IF($G23<=60,"Due 31-60","OK"))))) | M23: =IF($F23="","",$F23+ROW()/100000)
D24: =IF($B24="","",IFERROR(IF(VLOOKUP($B24,Reference!$A$6:$C$27,3,FALSE)>0,VLOOKUP($B24,Reference!$A$6:$C$27,3,FALSE),""),"")) | F24: =IF(OR($A24="",$B24="",NOT(ISNUMBER($C24))),"",IF(ISNUMBER($E24),IF($E24>0,EDATE($C24,$E24),""),IF(ISNUMBER($D24),EDATE($C24,$D24),""))) | G24: =IF($F24="","",$F24-TODAY()) | H24: =IF(OR($A24="",$B24=""),"",IF($F24="","No date",IF($G24<0,"Overdue",IF($G24<=30,"Due <=30",IF($G24<=60,"Due 31-60","OK"))))) | M24: =IF($F24="","",$F24+ROW()/100000)
D25: =IF($B25="","",IFERROR(IF(VLOOKUP($B25,Reference!$A$6:$C$27,3,FALSE)>0,VLOOKUP($B25,Reference!$A$6:$C$27,3,FALSE),""),"")) | F25: =IF(OR($A25="",$B25="",NOT(ISNUMBER($C25))),"",IF(ISNUMBER($E25),IF($E25>0,EDATE($C25,$E25),""),IF(ISNUMBER($D25),EDATE($C25,$D25),""))) | G25: =IF($F25="","",$F25-TODAY()) | H25: =IF(OR($A25="",$B25=""),"",IF($F25="","No date",IF($G25<0,"Overdue",IF($G25<=30,"Due <=30",IF($G25<=60,"Due 31-60","OK"))))) | M25: =IF($F25="","",$F25+ROW()/100000)
D26: =IF($B26="","",IFERROR(IF(VLOOKUP($B26,Reference!$A$6:$C$27,3,FALSE)>0,VLOOKUP($B26,Reference!$A$6:$C$27,3,FALSE),""),"")) | F26: =IF(OR($A26="",$B26="",NOT(ISNUMBER($C26))),"",IF(ISNUMBER($E26),IF($E26>0,EDATE($C26,$E26),""),IF(ISNUMBER($D26),EDATE($C26,$D26),""))) | G26: =IF($F26="","",$F26-TODAY()) | H26: =IF(OR($A26="",$B26=""),"",IF($F26="","No date",IF($G26<0,"Overdue",IF($G26<=30,"Due <=30",IF($G26<=60,"Due 31-60","OK"))))) | M26: =IF($F26="","",$F26+ROW()/100000)
D27: =IF($B27="","",IFERROR(IF(VLOOKUP($B27,Reference!$A$6:$C$27,3,FALSE)>0,VLOOKUP($B27,Reference!$A$6:$C$27,3,FALSE),""),"")) | F27: =IF(OR($A27="",$B27="",NOT(ISNUMBER($C27))),"",IF(ISNUMBER($E27),IF($E27>0,EDATE($C27,$E27),""),IF(ISNUMBER($D27),EDATE($C27,$D27),""))) | G27: =IF($F27="","",$F27-TODAY()) | H27: =IF(OR($A27="",$B27=""),"",IF($F27="","No date",IF($G27<0,"Overdue",IF($G27<=30,"Due <=30",IF($G27<=60,"Due 31-60","OK"))))) | M27: =IF($F27="","",$F27+ROW()/100000)
D28: =IF($B28="","",IFERROR(IF(VLOOKUP($B28,Reference!$A$6:$C$27,3,FALSE)>0,VLOOKUP($B28,Reference!$A$6:$C$27,3,FALSE),""),"")) | F28: =IF(OR($A28="",$B28="",NOT(ISNUMBER($C28))),"",IF(ISNUMBER($E28),IF($E28>0,EDATE($C28,$E28),""),IF(ISNUMBER($D28),EDATE($C28,$D28),""))) | G28: =IF($F28="","",$F28-TODAY()) | H28: =IF(OR($A28="",$B28=""),"",IF($F28="","No date",IF($G28<0,"Overdue",IF($G28<=30,"Due <=30",IF($G28<=60,"Due 31-60","OK"))))) | M28: =IF($F28="","",$F28+ROW()/100000)
D29: =IF($B29="","",IFERROR(IF(VLOOKUP($B29,Reference!$A$6:$C$27,3,FALSE)>0,VLOOKUP($B29,Reference!$A$6:$C$27,3,FALSE),""),"")) | F29: =IF(OR($A29="",$B29="",NOT(ISNUMBER($C29))),"",IF(ISNUMBER($E29),IF($E29>0,EDATE($C29,$E29),""),IF(ISNUMBER($D29),EDATE($C29,$D29),""))) | G29: =IF($F29="","",$F29-TODAY()) | H29: =IF(OR($A29="",$B29=""),"",IF($F29="","No date",IF($G29<0,"Overdue",IF($G29<=30,"Due <=30",IF($G29<=60,"Due 31-60","OK"))))) | M29: =IF($F29="","",$F29+ROW()/100000)
D30: =IF($B30="","",IFERROR(IF(VLOOKUP($B30,Reference!$A$6:$C$27,3,FALSE)>0,VLOOKUP($B30,Reference!$A$6:$C$27,3,FALSE),""),"")) | F30: =IF(OR($A30="",$B30="",NOT(ISNUMBER($C30))),"",IF(ISNUMBER($E30),IF($E30>0,EDATE($C30,$E30),""),IF(ISNUMBER($D30),EDATE($C30,$D30),""))) | G30: =IF($F30="","",$F30-TODAY()) | H30: =IF(OR($A30="",$B30=""),"",IF($F30="","No date",IF($G30<0,"Overdue",IF($G30<=30,"Due <=30",IF($G30<=60,"Due 31-60","OK"))))) | M30: =IF($F30="","",$F30+ROW()/100000)
D31: =IF($B31="","",IFERROR(IF(VLOOKUP($B31,Reference!$A$6:$C$27,3,FALSE)>0,VLOOKUP($B31,Reference!$A$6:$C$27,3,FALSE),""),"")) | F31: =IF(OR($A31="",$B31="",NOT(ISNUMBER($C31))),"",IF(ISNUMBER($E31),IF($E31>0,EDATE($C31,$E31),""),IF(ISNUMBER($D31),EDATE($C31,$D31),""))) | G31: =IF($F31="","",$F31-TODAY()) | H31: =IF(OR($A31="",$B31=""),"",IF($F31="","No date",IF($G31<0,"Overdue",IF($G31<=30,"Due <=30",IF($G31<=60,"Due 31-60","OK"))))) | M31: =IF($F31="","",$F31+ROW()/100000)
D32: =IF($B32="","",IFERROR(IF(VLOOKUP($B32,Reference!$A$6:$C$27,3,FALSE)>0,VLOOKUP($B32,Reference!$A$6:$C$27,3,FALSE),""),"")) | F32: =IF(OR($A32="",$B32="",NOT(ISNUMBER($C32))),"",IF(ISNUMBER($E32),IF($E32>0,EDATE($C32,$E32),""),IF(ISNUMBER($D32),EDATE($C32,$D32),""))) | G32: =IF($F32="","",$F32-TODAY()) | H32: =IF(OR($A32="",$B32=""),"",IF($F32="","No date",IF($G32<0,"Overdue",IF($G32<=30,"Due <=30",IF($G32<=60,"Due 31-60","OK"))))) | M32: =IF($F32="","",$F32+ROW()/100000)
... D1005: =IF($B1005="","",IFERROR(IF(VLOOKUP($B1005,Reference!$A$6:$C$27,3,FALSE)>0,VLOOKUP($B1005,Reference!$A$6:$C$27,3,FALSE),""),"")) | F1005: =IF(OR($A1005="",$B1005="",NOT(ISNUMBER($C1005))),"",IF(ISNUMBER($E1005),IF($E1005>0,EDATE($C1005,$E1005),""),IF(ISNUMBER($D1005),EDATE($C1005,$D1005),""))) | G1005: =IF($F1005="","",$F1005-TODAY()) | H1005: =IF(OR($A1005="",$B1005=""),"",IF($F1005="","No date",IF($G1005<0,"Overdue",IF($G1005<=30,"Due <=30",IF($G1005<=60,"Due 31-60","OK"))))) | M1005: =IF($F1005="","",$F1005+ROW()/100000)

Sheet Fire Safety Log
A1: =IF(TRIM('Start Here'!$C$20)="","HMO Compliance Tracker 2026",TRIM('Start Here'!$C$20))&IF(TRIM('Start Here'!$C$21)="",""," | "&TRIM('Start Here'!$C$21))&IF(TRIM('Start Here'!$C$22)="",""," | "&TRIM('Start Here'!$C$22))&IF(TRIM('Start Here'!$C$23)="",""," | "&TRIM('Start Here'!$C$23)) -> HMO Compliance Tracker 2026
A2: Fire Safety Log
A3: Record each test or check as you do it. Pick Fail if anything is wrong, describe the defect and action, and enter the date fixed: the Defect status column shows OPEN until a fix date is entered. Rows marked SAMPLE show how it works.
A5: Date | B5: Property | C5: Test type | D5: Location / call point | E5: Result | F5: Defect found | G5: Action taken | H5: Date fixed | I5: Signed by | J5: Defect status (auto)
A6: =TODAY()-(3) -> 46294 | B6: SAMPLE - 12 Acacia Road, Exampleton | C6: Weekly alarm test | D6: Call point: ground floor hall | E6: Pass | I6: A. Manager | J6: =IF($E6="Fail",IF(ISNUMBER($H6),"Fixed","OPEN"),"")
A7: =TODAY()-(10) -> 46287 | B7: SAMPLE - 12 Acacia Road, Exampleton | C7: Weekly alarm test | D7: Call point: first floor landing | E7: Pass | I7: A. Manager | J7: =IF($E7="Fail",IF(ISNUMBER($H7),"Fixed","OPEN"),"")
A8: =TODAY()-(17) -> 46280 | B8: SAMPLE - 12 Acacia Road, Exampleton | C8: Weekly alarm test | D8: Call point: kitchen | E8: Fail | F8: SAMPLE: sounder not audible in room 4 | G8: Engineer called, sounder replaced | H8: =TODAY()-(14) -> 46283 | I8: A. Manager | J8: =IF($E8="Fail",IF(ISNUMBER($H8),"Fixed","OPEN"),"") -> Fixed
A9: =TODAY()-(5) -> 46292 | B9: SAMPLE - 12 Acacia Road, Exampleton | C9: Monthly emergency lighting test | D9: Stairwell | E9: Fail | F9: SAMPLE: lamp not lighting | G9: Replacement ordered | I9: A. Manager | J9: =IF($E9="Fail",IF(ISNUMBER($H9),"Fixed","OPEN"),"") -> OPEN
A10: =TODAY()-(12) -> 46285 | B10: SAMPLE - Flat 3, 8 Demo Street, Sampleford | C10: Fire door check | D10: Kitchen door | E10: Pass | I10: A. Manager | J10: =IF($E10="Fail",IF(ISNUMBER($H10),"Fixed","OPEN"),"")
A11: =TODAY()-(30) -> 46267 | B11: SAMPLE - Flat 3, 8 Demo Street, Sampleford | C11: Fire drill | D11: Whole house | E11: Pass | I11: A. Manager | J11: =IF($E11="Fail",IF(ISNUMBER($H11),"Fixed","OPEN"),"")
J12: =IF($E12="Fail",IF(ISNUMBER($H12),"Fixed","OPEN"),"")
J13: =IF($E13="Fail",IF(ISNUMBER($H13),"Fixed","OPEN"),"")
J14: =IF($E14="Fail",IF(ISNUMBER($H14),"Fixed","OPEN"),"")
J15: =IF($E15="Fail",IF(ISNUMBER($H15),"Fixed","OPEN"),"")
J16: =IF($E16="Fail",IF(ISNUMBER($H16),"Fixed","OPEN"),"")
J17: =IF($E17="Fail",IF(ISNUMBER($H17),"Fixed","OPEN"),"")
J18: =IF($E18="Fail",IF(ISNUMBER($H18),"Fixed","OPEN"),"")
J19: =IF($E19="Fail",IF(ISNUMBER($H19),"Fixed","OPEN"),"")
J20: =IF($E20="Fail",IF(ISNUMBER($H20),"Fixed","OPEN"),"")
J21: =IF($E21="Fail",IF(ISNUMBER($H21),"Fixed","OPEN"),"")
J22: =IF($E22="Fail",IF(ISNUMBER($H22),"Fixed","OPEN"),"")
J23: =IF($E23="Fail",IF(ISNUMBER($H23),"Fixed","OPEN"),"")
... J1005: =IF($E1005="Fail",IF(ISNUMBER($H1005),"Fixed","OPEN"),"")

Sheet Licence Conditions
A1: =IF(TRIM('Start Here'!$C$20)="","HMO Compliance Tracker 2026",TRIM('Start Here'!$C$20))&IF(TRIM('Start Here'!$C$21)="",""," | "&TRIM('Start Here'!$C$21))&IF(TRIM('Start Here'!$C$22)="",""," | "&TRIM('Start Here'!$C$22))&IF(TRIM('Start Here'!$C$23)="",""," | "&TRIM('Start Here'!$C$23)) -> HMO Compliance Tracker 2026
A2: Licence Conditions and Room Sizes | I2: Room-size calculator is here (columns I to P)
A3: Work through one checklist per licensed property: pick the property at the top of its block, answer Yes / No / N/A for each condition, and note your evidence. Your council's own licence is what binds you: where it differs from this list, follow your licence. Rows marked SAMPLE show how it works.
A5: #1 | B5: SAMPLE - 12 Acacia Road, Exampleton | C5: =IF($B5="","Pick the property in the yellow cell",COUNTIF($E7:$E31,"Yes")&" yes | "&COUNTIF($E7:$E31,"No")&" NO | "&COUNTIF($E7:$E31,"N/A")&" n/a | "&(ROWS($E7:$E31)-COUNTIF($E7:$E31,"Yes")-COUNTIF($E7:$E31,"No")-COUNTIF($E7:$E31,"N/A"))&" not answered") -> 10 yes | 1 NO | 1 n/a | 13 not answered | I5: ROOM-SIZE CALCULATOR: statutory minimum sleeping-room sizes
A6: Ref | B6: Licence condition | C6: Type | D6: Legal basis | E6: Complies? | F6: Evidence / notes | G6: Date checked | I6: PROVISIONAL
A7: M1 | B7: Gas: produce a gas safety certificate obtained within the last 12 months to the council every year (if gas is supplied to the house). | C7: Mandatory | D7: Housing Act 2004 Sch 4 para 1(2) | E7: Yes | F7: SAMPLE: CP12 on file | G7: =TODAY()-(30) -> 46267 | I7: Property | J7: Room | K7: Floor area (m2) | L7: Persons aged over 10 | M7: Children aged under 10 | N7: Statutory minimum (m2) | O7: Meets minimum? (auto) | P7: Largest use by area (auto)
A8: M2 | B8: Keep electrical appliances and furniture you supply in a safe condition; give the council a declaration of their safety on demand. | C8: Mandatory | D8: Sch 4 para 1(3)(a)-(b) | E8: Yes | F8: SAMPLE: PAT report on file | G8: =TODAY()-(60) -> 46237 | I8: SAMPLE - 12 Acacia Road, Exampleton | J8: Room 1 | K8: 7.8 | L8: 1 | M8: 0 | N8: =IF(OR(NOT(ISNUMBER($K8)),N($L8)+N($M8)=0),"",IF(AND(N($L8)=1,N($M8)=0),6.51,IF(AND(N($L8)=2,N($M8)=0),10.22,IF(AND(N($L8)=0,N($M8)=1),4.64,"Council")))) -> 6.51 | O8: =IF($N8="","",IF($K8<4.64,"NO: under 4.64 m2, cannot be used to sleep",IF($N8="Council","Check council standard",IF($K8>=$N8,"Yes","NO: too small")))) -> Yes | P8: =IF(NOT(ISNUMBER($K8)),"",IF($K8<4.64,"Not for sleeping",IF($K8<6.51,"1 child under 10",IF($K8<10.22,"1 person","2 persons (over 10)")))) -> 1 person
A9: M3 | B9: Make sure every electrical installation is in proper working order and safe for continued use; give the council a declaration on demand. | C9: Mandatory | D9: Sch 4 para 1(3)(c)-(d) (England) | E9: Yes | F9: SAMPLE: EICR on file | G9: =TODAY()-(90) -> 46207 | I9: SAMPLE - 12 Acacia Road, Exampleton | J9: Room 2 | K9: 11.5 | L9: 2 | M9: 0 | N9: =IF(OR(NOT(ISNUMBER($K9)),N($L9)+N($M9)=0),"",IF(AND(N($L9)=1,N($M9)=0),6.51,IF(AND(N($L9)=2,N($M9)=0),10.22,IF(AND(N($L9)=0,N($M9)=1),4.64,"Council")))) -> 10.22 | O9: =IF($N9="","",IF($K9<4.64,"NO: under 4.64 m2, cannot be used to sleep",IF($N9="Council","Check council standard",IF($K9>=$N9,"Yes","NO: too small")))) -> Yes | P9: =IF(NOT(ISNUMBER($K9)),"",IF($K9<4.64,"Not for sleeping",IF($K9<6.51,"1 child under 10",IF($K9<10.22,"1 person","2 persons (over 10)")))) -> 2 persons (over 10)
A10: M4 | B10: Smoke alarm on each storey with living accommodation (halls, landings and bathrooms count), kept in proper working order; declaration on demand. | C10: Mandatory | D10: Sch 4 para 1(4)(za),(b), 1(6)-(7) | E10: Yes | F10: SAMPLE: alarm test log | G10: =TODAY()-(7) -> 46290 | I10: SAMPLE - 12 Acacia Road, Exampleton | J10: Room 3 | K10: 6.2 | L10: 1 | M10: 0 | N10: =IF(OR(NOT(ISNUMBER($K10)),N($L10)+N($M10)=0),"",IF(AND(N($L10)=1,N($M10)=0),6.51,IF(AND(N($L10)=2,N($M10)=0),10.22,IF(AND(N($L10)=0,N($M10)=1),4.64,"Council")))) -> 6.51 | O10: =IF($N10="","",IF($K10<4.64,"NO: under 4.64 m2, cannot be used to sleep",IF($N10="Council","Check council standard",IF($K10>=$N10,"Yes","NO: too small")))) -> NO: too small | P10: =IF(NOT(ISNUMBER($K10)),"",IF($K10<4.64,"Not for sleeping",IF($K10<6.51,"1 child under 10",IF($K10<10.22,"1 person","2 persons (over 10)")))) -> 1 child under 10
A11: M5 | B11: Carbon monoxide alarm in any room used as living accommodation with a fixed combustion appliance (not a gas cooker), kept in proper working order; declaration on demand. | C11: Mandatory | D11: Sch 4 para 1(4A) | E11: N/A | F11: SAMPLE: no fixed combustion appliance | G11: =TODAY()-(90) -> 46207 | I11: SAMPLE - 12 Acacia Road, Exampleton | J11: Room 4 | K11: 4.9 | L11: 0 | M11: 1 | N11: =IF(OR(NOT(ISNUMBER($K11)),N($L11)+N($M11)=0),"",IF(AND(N($L11)=1,N($M11)=0),6.51,IF(AND(N($L11)=2,N($M11)=0),10.22,IF(AND(N($L11)=0,N($M11)=1),4.64,"Council")))) -> 4.64 | O11: =IF($N11="","",IF($K11<4.64,"NO: under 4.64 m2, cannot be used to sleep",IF($N11="Council","Check council standard",IF($K11>=$N11,"Yes","NO: too small")))) -> Yes | P11: =IF(NOT(ISNUMBER($K11)),"",IF($K11<4.64,"Not for sleeping",IF($K11<6.51,"1 child under 10",IF($K11<10.22,"1 person","2 persons (over 10)")))) -> 1 child under 10
A12: M6 | B12: Give every occupier a written statement of the terms on which they occupy. | C12: Mandatory | D12: Sch 4 para 1(5) | E12: Yes | F12: SAMPLE: agreements issued | G12: =TODAY()-(90) -> 46207 | I12: SAMPLE - 12 Acacia Road, Exampleton | J12: Room 5 | K12: 9 | L12: 2 | M12: 0 | N12: =IF(OR(NOT(ISNUMBER($K12)),N($L12)+N($M12)=0),"",IF(AND(N($L12)=1,N($M12)=0),6.51,IF(AND(N($L12)=2,N($M12)=0),10.22,IF(AND(N($L12)=0,N($M12)=1),4.64,"Council")))) -> 10.22 | O12: =IF($N12="","",IF($K12<4.64,"NO: under 4.64 m2, cannot be used to sleep",IF($N12="Council","Check council standard",IF($K12>=$N12,"Yes","NO: too small")))) -> NO: too small | P12: =IF(NOT(ISNUMBER($K12)),"",IF($K12<4.64,"Not for sleeping",IF($K12<6.51,"1 child under 10",IF($K12<10.22,"1 person","2 persons (over 10)")))) -> 1 person
A13: M7 | B13: Sleeping rooms meet the minimum floor area: 6.51 m2 (one person over 10), 10.22 m2 (two people over 10), 4.64 m2 (one person under 10). Floor under a ceiling lower than 1.5 m does not count. | C13: Mandatory | D13: Sch 4 para 1A(2)(a)-(c), (9) | E13: Yes | F13: SAMPLE: rooms measured | G13: =TODAY()-(120) -> 46177 | N13: =IF(OR(NOT(ISNUMBER($K13)),N($L13)+N($M13)=0),"",IF(AND(N($L13)=1,N($M13)=0),6.51,IF(AND(N($L13)=2,N($M13)=0),10.22,IF(AND(N($L13)=0,N($M13)=1),4.64,"Council")))) | O13: =IF($N13="","",IF($K13<4.64,"NO: under 4.64 m2, cannot be used to sleep",IF($N13="Council","Check council standard",IF($K13>=$N13,"Yes","NO: too small")))) | P13: =IF(NOT(ISNUMBER($K13)),"",IF($K13<4.64,"Not for sleeping",IF($K13<6.51,"1 child under 10",IF($K13<10.22,"1 person","2 persons (over 10)"))))
A14: M8 | B14: No room under 4.64 m2 is used for sleeping, and the council has been told about any such room. | C14: Mandatory | D14: Sch 4 para 1A(2)(d), (6) | E14: Yes | F14: SAMPLE: no room under 4.64 m2 | G14: =TODAY()-(120) -> 46177 | N14: =IF(OR(NOT(ISNUMBER($K14)),N($L14)+N($M14)=0),"",IF(AND(N($L14)=1,N($M14)=0),6.51,IF(AND(N($L14)=2,N($M14)=0),10.22,IF(AND(N($L14)=0,N($M14)=1),4.64,"Council")))) | O14: =IF($N14="","",IF($K14<4.64,"NO: under 4.64 m2, cannot be used to sleep",IF($N14="Council","Check council standard",IF($K14>=$N14,"Yes","NO: too small")))) | P14: =IF(NOT(ISNUMBER($K14)),"",IF($K14<4.64,"Not for sleeping",IF($K14<6.51,"1 child under 10",IF($K14<10.22,"1 person","2 persons (over 10)"))))
A15: M9 | B15: No room has more people sleeping in it than the maximum set out in your licence. | C15: Mandatory | D15: Sch 4 para 1A(3) | E15: Yes | F15: SAMPLE: limits shown in licence | G15: =TODAY()-(120) -> 46177 | N15: =IF(OR(NOT(ISNUMBER($K15)),N($L15)+N($M15)=0),"",IF(AND(N($L15)=1,N($M15)=0),6.51,IF(AND(N($L15)=2,N($M15)=0),10.22,IF(AND(N($L15)=0,N($M15)=1),4.64,"Council")))) | O15: =IF($N15="","",IF($K15<4.64,"NO: under 4.64 m2, cannot be used to sleep",IF($N15="Council","Check council standard",IF($K15>=$N15,"Yes","NO: too small")))) | P15: =IF(NOT(ISNUMBER($K15)),"",IF($K15<4.64,"Not for sleeping",IF($K15<6.51,"1 child under 10",IF($K15<10.22,"1 person","2 persons (over 10)"))))
A16: M10 | B16: Comply with the council's scheme for storing and disposing of household waste pending collection. | C16: Mandatory | D16: Sch 4 para 1C | E16: No | F16: SAMPLE: bin arrangements not yet agreed with council | G16: =TODAY()-(14) -> 46283 | N16: =IF(OR(NOT(ISNUMBER($K16)),N($L16)+N($M16)=0),"",IF(AND(N($L16)=1,N($M16)=0),6.51,IF(AND(N($L16)=2,N($M16)=0),10.22,IF(AND(N($L16)=0,N($M16)=1),4.64,"Council")))) | O16: =IF($N16="","",IF($K16<4.64,"NO: under 4.64 m2, cannot be used to sleep",IF($N16="Council","Check council standard",IF($K16>=$N16,"Yes","NO: too small")))) | P16: =IF(NOT(ISNUMBER($K16)),"",IF($K16<4.64,"Not for sleeping",IF($K16<6.51,"1 child under 10",IF($K16<10.22,"1 person","2 persons (over 10)"))))
A17: L1 | B17: Manager's name, address and phone number displayed prominently and given to each household. | C17: Law | D17: Management of HMOs Regs 2006 reg 3 | E17: Yes | F17: SAMPLE: notice in the hallway | G17: =TODAY()-(30) -> 46267 | N17: =IF(OR(NOT(ISNUMBER($K17)),N($L17)+N($M17)=0),"",IF(AND(N($L17)=1,N($M17)=0),6.51,IF(AND(N($L17)=2,N($M17)=0),10.22,IF(AND(N($L17)=0,N($M17)=1),4.64,"Council")))) | O17: =IF($N17="","",IF($K17<4.64,"NO: under 4.64 m2, cannot be used to sleep",IF($N17="Council","Check council standard",IF($K17>=$N17,"Yes","NO: too small")))) | P17: =IF(NOT(ISNUMBER($K17)),"",IF($K17<4.64,"Not for sleeping",IF($K17<6.51,"1 child under 10",IF($K17<10.22,"1 person","2 persons (over 10)"))))
A18: L2 | B18: Escape routes kept clear and in good repair; fire alarms and fire-fighting equipment kept in good working order; escape-route notices displayed (HMOs with 5 or more occupiers). | C18: Law | D18: Management Regs 2006 reg 4 | E18: Yes | F18: SAMPLE: escape routes checked weekly | G18: =TODAY()-(7) -> 46290 | N18: =IF(OR(NOT(ISNUMBER($K18)),N($L18)+N($M18)=0),"",IF(AND(N($L18)=1,N($M18)=0),6.51,IF(AND(N($L18)=2,N($M18)=0),10.22,IF(AND(N($L18)=0,N($M18)=1),4.64,"Council")))) | O18: =IF($N18="","",IF($K18<4.64,"NO: under 4.64 m2, cannot be used to sleep",IF($N18="Council","Check council standard",IF($K18>=$N18,"Yes","NO: too small")))) | P18: =IF(NOT(ISNUMBER($K18)),"",IF($K18<4.64,"Not for sleeping",IF($K18<6.51,"1 child under 10",IF($K18<10.22,"1 person","2 persons (over 10)"))))
A19: L3 | B19: Electrical installation inspected and tested at least every 5 years (EICR held; copies given to tenants and the council as required). | C19: Law | D19: Electrical Safety Standards Regs 2020 reg 3 | N19: =IF(OR(NOT(ISNUMBER($K19)),N($L19)+N($M19)=0),"",IF(AND(N($L19)=1,N($M19)=0),6.51,IF(AND(N($L19)=2,N($M19)=0),10.22,IF(AND(N($L19)=0,N($M19)=1),4.64,"Council")))) | O19: =IF($N19="","",IF($K19<4.64,"NO: under 4.64 m2, cannot be used to sleep",IF($N19="Council","Check council standard",IF($K19>=$N19,"Yes","NO: too small")))) | P19: =IF(NOT(ISNUMBER($K19)),"",IF($K19<4.64,"Not for sleeping",IF($K19<6.51,"1 child under 10",IF($K19<10.22,"1 person","2 persons (over 10)"))))
A20: L4 | B20: Fire risk assessment made for the common parts and reviewed regularly. | C20: Law | D20: Fire Safety Order 2005 art 9 | N20: =IF(OR(NOT(ISNUMBER($K20)),N($L20)+N($M20)=0),"",IF(AND(N($L20)=1,N($M20)=0),6.51,IF(AND(N($L20)=2,N($M20)=0),10.22,IF(AND(N($L20)=0,N($M20)=1),4.64,"Council")))) | O20: =IF($N20="","",IF($K20<4.64,"NO: under 4.64 m2, cannot be used to sleep",IF($N20="Council","Check council standard",IF($K20>=$N20,"Yes","NO: too small")))) | P20: =IF(NOT(ISNUMBER($K20)),"",IF($K20<4.64,"Not for sleeping",IF($K20<6.51,"1 child under 10",IF($K20<10.22,"1 person","2 persons (over 10)"))))
A21: L5 | B21: Common parts and living accommodation kept clean, safe and in repair; water, drainage, gas and electricity supplies not unreasonably interrupted; enough bins for each household. | C21: Law | D21: Management Regs 2006 regs 5, 7, 8, 9 | N21: =IF(OR(NOT(ISNUMBER($K21)),N($L21)+N($M21)=0),"",IF(AND(N($L21)=1,N($M21)=0),6.51,IF(AND(N($L21)=2,N($M21)=0),10.22,IF(AND(N($L21)=0,N($M21)=1),4.64,"Council")))) | O21: =IF($N21="","",IF($K21<4.64,"NO: under 4.64 m2, cannot be used to sleep",IF($N21="Council","Check council standard",IF($K21>=$N21,"Yes","NO: too small")))) | P21: =IF(NOT(ISNUMBER($K21)),"",IF($K21<4.64,"Not for sleeping",IF($K21<6.51,"1 child under 10",IF($K21<10.22,"1 person","2 persons (over 10)"))))
A22: L6 | B22: Right to Rent check done for every adult occupier before the tenancy begins; evidence kept for the tenancy plus one year. | C22: Law | D22: Immigration Act 2014 (Home Office guide) | N22: =IF(OR(NOT(ISNUMBER($K22)),N($L22)+N($M22)=0),"",IF(AND(N($L22)=1,N($M22)=0),6.51,IF(AND(N($L22)=2,N($M22)=0),10.22,IF(AND(N($L22)=0,N($M22)=1),4.64,"Council")))) | O22: =IF($N22="","",IF($K22<4.64,"NO: under 4.64 m2, cannot be used to sleep",IF($N22="Council","Check council standard",IF($K22>=$N22,"Yes","NO: too small")))) | P22: =IF(NOT(ISNUMBER($K22)),"",IF($K22<4.64,"Not for sleeping",IF($K22<6.51,"1 child under 10",IF($K22<10.22,"1 person","2 persons (over 10)"))))
A23: L7 | B23: Deposits protected in an authorised scheme and prescribed information given within 30 days (period begins on the day received). | C23: Law | D23: Housing Act 2004 s.213 | N23: =IF(OR(NOT(ISNUMBER($K23)),N($L23)+N($M23)=0),"",IF(AND(N($L23)=1,N($M23)=0),6.51,IF(AND(N($L23)=2,N($M23)=0),10.22,IF(AND(N($L23)=0,N($M23)=1),4.64,"Council")))) | O23: =IF($N23="","",IF($K23<4.64,"NO: under 4.64 m2, cannot be used to sleep",IF($N23="Council","Check council standard",IF($K23>=$N23,"Yes","NO: too small")))) | P23: =IF(NOT(ISNUMBER($K23)),"",IF($K23<4.64,"Not for sleeping",IF($K23<6.51,"1 child under 10",IF($K23<10.22,"1 person","2 persons (over 10)"))))
A24: C1 | B24: Test the fire alarm weekly, using a different call point each time, and keep a log. | C24: Common | D24: Official fire guidance; often a licence condition | N24: =IF(OR(NOT(ISNUMBER($K24)),N($L24)+N($M24)=0),"",IF(AND(N($L24)=1,N($M24)=0),6.51,IF(AND(N($L24)=2,N($M24)=0),10.22,IF(AND(N($L24)=0,N($M24)=1),4.64,"Council")))) | O24: =IF($N24="","",IF($K24<4.64,"NO: under 4.64 m2, cannot be used to sleep",IF($N24="Council","Check council standard",IF($K24>=$N24,"Yes","NO: too small")))) | P24: =IF(NOT(ISNUMBER($K24)),"",IF($K24<4.64,"Not for sleeping",IF($K24<6.51,"1 child under 10",IF($K24<10.22,"1 person","2 persons (over 10)"))))
A25: C2 | B25: Test emergency lighting monthly, run the annual full-discharge test, and keep records. | C25: Common | D25: Official fire guidance; often a licence condition | N25: =IF(OR(NOT(ISNUMBER($K25)),N($L25)+N($M25)=0),"",IF(AND(N($L25)=1,N($M25)=0),6.51,IF(AND(N($L25)=2,N($M25)=0),10.22,IF(AND(N($L25)=0,N($M25)=1),4.64,"Council")))) | O25: =IF($N25="","",IF($K25<4.64,"NO: under 4.64 m2, cannot be used to sleep",IF($N25="Council","Check council standard",IF($K25>=$N25,"Yes","NO: too small")))) | P25: =IF(NOT(ISNUMBER($K25)),"",IF($K25<4.64,"Not for sleeping",IF($K25<6.51,"1 child under 10",IF($K25<10.22,"1 person","2 persons (over 10)"))))
A26: C3 | B26: Check fire doors regularly (guidance: monthly) and keep them closing properly with intact seals. | C26: Common | D26: Official fire guidance; often a licence condition | N26: =IF(OR(NOT(ISNUMBER($K26)),N($L26)+N($M26)=0),"",IF(AND(N($L26)=1,N($M26)=0),6.51,IF(AND(N($L26)=2,N($M26)=0),10.22,IF(AND(N($L26)=0,N($M26)=1),4.64,"Council")))) | O26: =IF($N26="","",IF($K26<4.64,"NO: under 4.64 m2, cannot be used to sleep",IF($N26="Council","Check council standard",IF($K26>=$N26,"Yes","NO: too small")))) | P26: =IF(NOT(ISNUMBER($K26)),"",IF($K26<4.64,"Not for sleeping",IF($K26<6.51,"1 child under 10",IF($K26<10.22,"1 person","2 persons (over 10)"))))
A27: C4 | B27: Fire extinguishers checked monthly and serviced annually by a competent person. | C27: Common | D27: Official fire guidance; often a licence condition | N27: =IF(OR(NOT(ISNUMBER($K27)),N($L27)+N($M27)=0),"",IF(AND(N($L27)=1,N($M27)=0),6.51,IF(AND(N($L27)=2,N($M27)=0),10.22,IF(AND(N($L27)=0,N($M27)=1),4.64,"Council")))) | O27: =IF($N27="","",IF($K27<4.64,"NO: under 4.64 m2, cannot be used to sleep",IF($N27="Council","Check council standard",IF($K27>=$N27,"Yes","NO: too small")))) | P27: =IF(NOT(ISNUMBER($K27)),"",IF($K27<4.64,"Not for sleeping",IF($K27<6.51,"1 child under 10",IF($K27<10.22,"1 person","2 persons (over 10)"))))
A28: C5 | B28: Give occupiers house rules and key information (emergency numbers, fire procedure, refuse arrangements). | C28: Common | D28: Typical council condition: check yours | N28: =IF(OR(NOT(ISNUMBER($K28)),N($L28)+N($M28)=0),"",IF(AND(N($L28)=1,N($M28)=0),6.51,IF(AND(N($L28)=2,N($M28)=0),10.22,IF(AND(N($L28)=0,N($M28)=1),4.64,"Council")))) | O28: =IF($N28="","",IF($K28<4.64,"NO: under 4.64 m2, cannot be used to sleep",IF($N28="Council","Check council standard",IF($K28>=$N28,"Yes","NO: too small")))) | P28: =IF(NOT(ISNUMBER($K28)),"",IF($K28<4.64,"Not for sleeping",IF($K28<6.51,"1 child under 10",IF($K28<10.22,"1 person","2 persons (over 10)"))))
A29: C6 | B29: Have a procedure for complaints and anti-social behaviour, and keep records. | C29: Common | D29: Typical council condition: check yours | N29: =IF(OR(NOT(ISNUMBER($K29)),N($L29)+N($M29)=0),"",IF(AND(N($L29)=1,N($M29)=0),6.51,IF(AND(N($L29)=2,N($M29)=0),10.22,IF(AND(N($L29)=0,N($M29)=1),4.64,"Council")))) | O29: =IF($N29="","",IF($K29<4.64,"NO: under 4.64 m2, cannot be used to sleep",IF($N29="Council","Check council standard",IF($K29>=$N29,"Yes","NO: too small")))) | P29: =IF(NOT(ISNUMBER($K29)),"",IF($K29<4.64,"Not for sleeping",IF($K29<6.51,"1 child under 10",IF($K29<10.22,"1 person","2 persons (over 10)"))))
A30: C7 | B30: Inspect the property at regular intervals and keep written records. | C30: Common | D30: Typical council condition: check yours | N30: =IF(OR(NOT(ISNUMBER($K30)),N($L30)+N($M30)=0),"",IF(AND(N($L30)=1,N($M30)=0),6.51,IF(AND(N($L30)=2,N($M30)=0),10.22,IF(AND(N($L30)=0,N($M30)=1),4.64,"Council")))) | O30: =IF($N30="","",IF($K30<4.64,"NO: under 4.64 m2, cannot be used to sleep",IF($N30="Council","Check council standard",IF($K30>=$N30,"Yes","NO: too small")))) | P30: =IF(NOT(ISNUMBER($K30)),"",IF($K30<4.64,"Not for sleeping",IF($K30<6.51,"1 child under 10",IF($K30<10.22,"1 person","2 persons (over 10)"))))
A31: C8 | B31: Tell the council about changes (new manager, change of ownership, alterations, change in occupancy). Amenities (kitchens, bathrooms, heating) meet your council's standards. | C31: Common | D31: Typical council condition: check yours | N31: =IF(OR(NOT(ISNUMBER($K31)),N($L31)+N($M31)=0),"",IF(AND(N($L31)=1,N($M31)=0),6.51,IF(AND(N($L31)=2,N($M31)=0),10.22,IF(AND(N($L31)=0,N($M31)=1),4.64,"Council")))) | O31: =IF($N31="","",IF($K31<4.64,"NO: under 4.64 m2, cannot be used to sleep",IF($N31="Council","Check council standard",IF($K31>=$N31,"Yes","NO: too small")))) | P31: =IF(NOT(ISNUMBER($K31)),"",IF($K31<4.64,"Not for sleeping",IF($K31<6.51,"1 child under 10",IF($K31<10.22,"1 person","2 persons (over 10)"))))
A33: #2 | C33: =IF($B33="","Pick the property in the yellow cell",COUNTIF($E35:$E59,"Yes")&" yes | "&COUNTIF($E35:$E59,"No")&" NO | "&COUNTIF($E35:$E59,"N/A")&" n/a | "&(ROWS($E35:$E59)-COUNTIF($E35:$E59,"Yes")-COUNTIF($E35:$E59,"No")-COUNTIF($E35:$E59,"N/A"))&" not answered") -> Pick the property in the yellow cell
A34: Ref | B34: Licence condition | C34: Type | D34: Legal basis | E34: Complies? | F34: Evidence / notes | G34: Date checked
A35: M1 | B35: Gas: produce a gas safety certificate obtained within the last 12 months to the council every year (if gas is supplied to the house). | C35: Mandatory | D35: Housing Act 2004 Sch 4 para 1(2)
A36: M2 | B36: Keep electrical appliances and furniture you supply in a safe condition; give the council a declaration of their safety on demand. | C36: Mandatory | D36: Sch 4 para 1(3)(a)-(b)
A37: M3 | B37: Make sure every electrical installation is in proper working order and safe for continued use; give the council a declaration on demand. | C37: Mandatory | D37: Sch 4 para 1(3)(c)-(d) (England)
A38: M4 | B38: Smoke alarm on each storey with living accommodation (halls, landings and bathrooms count), kept in proper working order; declaration on demand. | C38: Mandatory | D38: Sch 4 para 1(4)(za),(b), 1(6)-(7)
A39: M5 | B39: Carbon monoxide alarm in any room used as living accommodation with a fixed combustion appliance (not a gas cooker), kept in proper working order; declaration on demand. | C39: Mandatory | D39: Sch 4 para 1(4A)
A40: M6 | B40: Give every occupier a written statement of the terms on which they occupy. | C40: Mandatory | D40: Sch 4 para 1(5)
A41: M7 | B41: Sleeping rooms meet the minimum floor area: 6.51 m2 (one person over 10), 10.22 m2 (two people over 10), 4.64 m2 (one person under 10). Floor under a ceiling lower than 1.5 m does not count. | C41: Mandatory | D41: Sch 4 para 1A(2)(a)-(c), (9)
A42: M8 | B42: No room under 4.64 m2 is used for sleeping, and the council has been told about any such room. | C42: Mandatory | D42: Sch 4 para 1A(2)(d), (6)
A43: M9 | B43: No room has more people sleeping in it than the maximum set out in your licence. | C43: Mandatory | D43: Sch 4 para 1A(3)
A44: M10 | B44: Comply with the council's scheme for storing and disposing of household waste pending collection. | C44: Mandatory | D44: Sch 4 para 1C
A45: L1 | B45: Manager's name, address and phone number displayed prominently and given to each household. | C45: Law | D45: Management of HMOs Regs 2006 reg 3
A46: L2 | B46: Escape routes kept clear and in good repair; fire alarms and fire-fighting equipment kept in good working order; escape-route notices displayed (HMOs with 5 or more occupiers). | C46: Law | D46: Management Regs 2006 reg 4
... A59: C8 | B59: Tell the council about changes (new manager, change of ownership, alterations, change in occupancy). Amenities (kitchens, bathrooms, heating) meet your council's standards. | C59: Common | D59: Typical council condition: check yours
A61: #3 | C61: =IF($B61="","Pick the property in the yellow cell",COUNTIF($E63:$E87,"Yes")&" yes | "&COUNTIF($E63:$E87,"No")&" NO | "&COUNTIF($E63:$E87,"N/A")&" n/a | "&(ROWS($E63:$E87)-COUNTIF($E63:$E87,"Yes")-COUNTIF($E63:$E87,"No")-COUNTIF($E63:$E87,"N/A"))&" not answered") -> Pick the property in the yellow cell
A62: Ref | B62: Licence condition | C62: Type | D62: Legal basis | E62: Complies? | F62: Evidence / notes | G62: Date checked
A63: M1 | B63: Gas: produce a gas safety certificate obtained within the last 12 months to the council every year (if gas is supplied to the house). | C63: Mandatory | D63: Housing Act 2004 Sch 4 para 1(2)
A64: M2 | B64: Keep electrical appliances and furniture you supply in a safe condition; give the council a declaration of their safety on demand. | C64: Mandatory | D64: Sch 4 para 1(3)(a)-(b)
A65: M3 | B65: Make sure every electrical installation is in proper working order and safe for continued use; give the council a declaration on demand. | C65: Mandatory | D65: Sch 4 para 1(3)(c)-(d) (England)
A66: M4 | B66: Smoke alarm on each storey with living accommodation (halls, landings and bathrooms count), kept in proper working order; declaration on demand. | C66: Mandatory | D66: Sch 4 para 1(4)(za),(b), 1(6)-(7)
A67: M5 | B67: Carbon monoxide alarm in any room used as living accommodation with a fixed combustion appliance (not a gas cooker), kept in proper working order; declaration on demand. | C67: Mandatory | D67: Sch 4 para 1(4A)
A68: M6 | B68: Give every occupier a written statement of the terms on which they occupy. | C68: Mandatory | D68: Sch 4 para 1(5)
A69: M7 | B69: Sleeping rooms meet the minimum floor area: 6.51 m2 (one person over 10), 10.22 m2 (two people over 10), 4.64 m2 (one person under 10). Floor under a ceiling lower than 1.5 m does not count. | C69: Mandatory | D69: Sch 4 para 1A(2)(a)-(c), (9)
A70: M8 | B70: No room under 4.64 m2 is used for sleeping, and the council has been told about any such room. | C70: Mandatory | D70: Sch 4 para 1A(2)(d), (6)
A71: M9 | B71: No room has more people sleeping in it than the maximum set out in your licence. | C71: Mandatory | D71: Sch 4 para 1A(3)
A72: M10 | B72: Comply with the council's scheme for storing and disposing of household waste pending collection. | C72: Mandatory | D72: Sch 4 para 1C
A73: L1 | B73: Manager's name, address and phone number displayed prominently and given to each household. | C73: Law | D73: Management of HMOs Regs 2006 reg 3
A74: L2 | B74: Escape routes kept clear and in good repair; fire alarms and fire-fighting equipment kept in good working order; escape-route notices displayed (HMOs with 5 or more occupiers). | C74: Law | D74: Management Regs 2006 reg 4
... A87: C8 | B87: Tell the council about changes (new manager, change of ownership, alterations, change in occupancy). Amenities (kitchens, bathrooms, heating) meet your council's standards. | C87: Common | D87: Typical council condition: check yours
A89: #4 | C89: =IF($B89="","Pick the property in the yellow cell",COUNTIF($E91:$E115,"Yes")&" yes | "&COUNTIF($E91:$E115,"No")&" NO | "&COUNTIF($E91:$E115,"N/A")&" n/a | "&(ROWS($E91:$E115)-COUNTIF($E91:$E115,"Yes")-COUNTIF($E91:$E115,"No")-COUNTIF($E91:$E115,"N/A"))&" not answered") -> Pick the property in the yellow cell
A90: Ref | B90: Licence condition | C90: Type | D90: Legal basis | E90: Complies? | F90: Evidence / notes | G90: Date checked
A91: M1 | B91: Gas: produce a gas safety certificate obtained within the last 12 months to the council every year (if gas is supplied to the house). | C91: Mandatory | D91: Housing Act 2004 Sch 4 para 1(2)
A92: M2 | B92: Keep electrical appliances and furniture you supply in a safe condition; give the council a declaration of their safety on demand. | C92: Mandatory | D92: Sch 4 para 1(3)(a)-(b)
A93: M3 | B93: Make sure every electrical installation is in proper working order and safe for continued use; give the council a declaration on demand. | C93: Mandatory | D93: Sch 4 para 1(3)(c)-(d) (England)
A94: M4 | B94: Smoke alarm on each storey with living accommodation (halls, landings and bathrooms count), kept in proper working order; declaration on demand. | C94: Mandatory | D94: Sch 4 para 1(4)(za),(b), 1(6)-(7)
A95: M5 | B95: Carbon monoxide alarm in any room used as living accommodation with a fixed combustion appliance (not a gas cooker), kept in proper working order; declaration on demand. | C95: Mandatory | D95: Sch 4 para 1(4A)
A96: M6 | B96: Give every occupier a written statement of the terms on which they occupy. | C96: Mandatory | D96: Sch 4 para 1(5)
A97: M7 | B97: Sleeping rooms meet the minimum floor area: 6.51 m2 (one person over 10), 10.22 m2 (two people over 10), 4.64 m2 (one person under 10). Floor under a ceiling lower than 1.5 m does not count. | C97: Mandatory | D97: Sch 4 para 1A(2)(a)-(c), (9)
A98: M8 | B98: No room under 4.64 m2 is used for sleeping, and the council has been told about any such room. | C98: Mandatory | D98: Sch 4 para 1A(2)(d), (6)
A99: M9 | B99: No room has more people sleeping in it than the maximum set out in your licence. | C99: Mandatory | D99: Sch 4 para 1A(3)
A100: M10 | B100: Comply with the council's scheme for storing and disposing of household waste pending collection. | C100: Mandatory | D100: Sch 4 para 1C
A101: L1 | B101: Manager's name, address and phone number displayed prominently and given to each household. | C101: Law | D101: Management of HMOs Regs 2006 reg 3
A102: L2 | B102: Escape routes kept clear and in good repair; fire alarms and fire-fighting equipment kept in good working order; escape-route notices displayed (HMOs with 5 or more occupiers). | C102: Law | D102: Management Regs 2006 reg 4
... A115: C8 | B115: Tell the council about changes (new manager, change of ownership, alterations, change in occupancy). Amenities (kitchens, bathrooms, heating) meet your council's standards. | C115: Common | D115: Typical council condition: check yours
A117: #5 | C117: =IF($B117="","Pick the property in the yellow cell",COUNTIF($E119:$E143,"Yes")&" yes | "&COUNTIF($E119:$E143,"No")&" NO | "&COUNTIF($E119:$E143,"N/A")&" n/a | "&(ROWS($E119:$E143)-COUNTIF($E119:$E143,"Yes")-COUNTIF($E119:$E143,"No")-COUNTIF($E119:$E143,"N/A"))&" not answered") -> Pick the property in the yellow cell
A118: Ref | B118: Licence condition | C118: Type | D118: Legal basis | E118: Complies? | F118: Evidence / notes | G118: Date checked
A119: M1 | B119: Gas: produce a gas safety certificate obtained within the last 12 months to the council every year (if gas is supplied to the house). | C119: Mandatory | D119: Housing Act 2004 Sch 4 para 1(2)
A120: M2 | B120: Keep electrical appliances and furniture you supply in a safe condition; give the council a declaration of their safety on demand. | C120: Mandatory | D120: Sch 4 para 1(3)(a)-(b)
A121: M3 | B121: Make sure every electrical installation is in proper working order and safe for continued use; give the council a declaration on demand. | C121: Mandatory | D121: Sch 4 para 1(3)(c)-(d) (England)
A122: M4 | B122: Smoke alarm on each storey with living accommodation (halls, landings and bathrooms count), kept in proper working order; declaration on demand. | C122: Mandatory | D122: Sch 4 para 1(4)(za),(b), 1(6)-(7)
A123: M5 | B123: Carbon monoxide alarm in any room used as living accommodation with a fixed combustion appliance (not a gas cooker), kept in proper working order; declaration on demand. | C123: Mandatory | D123: Sch 4 para 1(4A)
A124: M6 | B124: Give every occupier a written statement of the terms on which they occupy. | C124: Mandatory | D124: Sch 4 para 1(5)
A125: M7 | B125: Sleeping rooms meet the minimum floor area: 6.51 m2 (one person over 10), 10.22 m2 (two people over 10), 4.64 m2 (one person under 10). Floor under a ceiling lower than 1.5 m does not count. | C125: Mandatory | D125: Sch 4 para 1A(2)(a)-(c), (9)
A126: M8 | B126: No room under 4.64 m2 is used for sleeping, and the council has been told about any such room. | C126: Mandatory | D126: Sch 4 para 1A(2)(d), (6)
A127: M9 | B127: No room has more people sleeping in it than the maximum set out in your licence. | C127: Mandatory | D127: Sch 4 para 1A(3)
A128: M10 | B128: Comply with the council's scheme for storing and disposing of household waste pending collection. | C128: Mandatory | D128: Sch 4 para 1C
A129: L1 | B129: Manager's name, address and phone number displayed prominently and given to each household. | C129: Law | D129: Management of HMOs Regs 2006 reg 3
A130: L2 | B130: Escape routes kept clear and in good repair; fire alarms and fire-fighting equipment kept in good working order; escape-route notices displayed (HMOs with 5 or more occupiers). | C130: Law | D130: Management Regs 2006 reg 4
... A143: C8 | B143: Tell the council about changes (new manager, change of ownership, alterations, change in occupancy). Amenities (kitchens, bathrooms, heating) meet your council's standards. | C143: Common | D143: Typical council condition: check yours
A145: #6 | C145: =IF($B145="","Pick the property in the yellow cell",COUNTIF($E147:$E171,"Yes")&" yes | "&COUNTIF($E147:$E171,"No")&" NO | "&COUNTIF($E147:$E171,"N/A")&" n/a | "&(ROWS($E147:$E171)-COUNTIF($E147:$E171,"Yes")-COUNTIF($E147:$E171,"No")-COUNTIF($E147:$E171,"N/A"))&" not answered") -> Pick the property in the yellow cell
A146: Ref | B146: Licence condition | C146: Type | D146: Legal basis | E146: Complies? | F146: Evidence / notes | G146: Date checked
A147: M1 | B147: Gas: produce a gas safety certificate obtained within the last 12 months to the council every year (if gas is supplied to the house). | C147: Mandatory | D147: Housing Act 2004 Sch 4 para 1(2)
A148: M2 | B148: Keep electrical appliances and furniture you supply in a safe condition; give the council a declaration of their safety on demand. | C148: Mandatory | D148: Sch 4 para 1(3)(a)-(b)
A149: M3 | B149: Make sure every electrical installation is in proper working order and safe for continued use; give the council a declaration on demand. | C149: Mandatory | D149: Sch 4 para 1(3)(c)-(d) (England)
A150: M4 | B150: Smoke alarm on each storey with living accommodation (halls, landings and bathrooms count), kept in proper working order; declaration on demand. | C150: Mandatory | D150: Sch 4 para 1(4)(za),(b), 1(6)-(7)
A151: M5 | B151: Carbon monoxide alarm in any room used as living accommodation with a fixed combustion appliance (not a gas cooker), kept in proper working order; declaration on demand. | C151: Mandatory | D151: Sch 4 para 1(4A)
A152: M6 | B152: Give every occupier a written statement of the terms on which they occupy. | C152: Mandatory | D152: Sch 4 para 1(5)
A153: M7 | B153: Sleeping rooms meet the minimum floor area: 6.51 m2 (one person over 10), 10.22 m2 (two people over 10), 4.64 m2 (one person under 10). Floor under a ceiling lower than 1.5 m does not count. | C153: Mandatory | D153: Sch 4 para 1A(2)(a)-(c), (9)
A154: M8 | B154: No room under 4.64 m2 is used for sleeping, and the council has been told about any such room. | C154: Mandatory | D154: Sch 4 para 1A(2)(d), (6)
...

Sheet Tenancies & Renters Rights
A1: =IF(TRIM('Start Here'!$C$20)="","HMO Compliance Tracker 2026",TRIM('Start Here'!$C$20))&IF(TRIM('Start Here'!$C$21)="",""," | "&TRIM('Start Here'!$C$21))&IF(TRIM('Start Here'!$C$22)="",""," | "&TRIM('Start Here'!$C$22))&IF(TRIM('Start Here'!$C$23)="",""," | "&TRIM('Start Here'!$C$23)) -> HMO Compliance Tracker 2026
A2: Tenancies & Renters' Rights
A3: One row per tenancy or room. Use tenant initials or a reference only, not full names. Grey columns are automatic. There are no Section 21 columns: Section 21 notices ended in England on 1 May 2026. Rows marked SAMPLE show how it works.
A5: Tenant ref (initials only) | B5: Property | C5: Room | D5: Tenancy start | E5: Rent (£ per month) | F5: Deposit (£) | G5: Deposit received | H5: Deposit protected on | I5: Prescribed info served on | J5: Deposit check (auto: 30-day rule) | K5: Deposit vs 5-week cap (auto) | L5: Right to Rent checked | M5: Follow-up check due (if right is time-limited) | N5: Right to Rent status (auto) | O5: Written statement of terms given (new tenancies: before signing) | P5: Renters' Rights Act Information Sheet given (existing tenancies: by 31/05/2026) | Q5: Paperwork check (auto) | R5: Last rent increase (date it took effect) | S5: Earliest next increase (auto: 52 weeks later) | T5: Section 13 notice served | U5: Earliest effective date (auto: 2 months after notice) | V5: Pet request received | W5: Pet request answered | X5: Pet request status (auto: reply due in 28 days) | Y5: Notes
A6: SAMPLE AB | B6: SAMPLE - 12 Acacia Road, Exampleton | C6: Room 1 | D6: =TODAY()-(500) -> 45797 | E6: 550 | F6: 600 | G6: =TODAY()-(500) -> 45797 | H6: =TODAY()-(490) -> 45807 | I6: =TODAY()-(490) -> 45807 | J6: =IF(OR($A6="",NOT(ISNUMBER($F6))),"",IF($F6<=0,"No deposit",IF(NOT(ISNUMBER($G6)),"Enter date received",IF(AND(ISNUMBER($H6),ISNUMBER($I6)),IF(MAX($H6,$I6)-$G6<=29,"OK","LATE: protected / info served after day 30"),IF(TODAY()-$G6>29,"OVERDUE: not protected / info not served","Protect + serve info by "&TEXT($G6+29,"dd/mm/yyyy")))))) -> OK | K6: =IF(OR(NOT(ISNUMBER($E6)),NOT(ISNUMBER($F6))),"",IF($F6<=$E6*12/52*5,"OK","Over 5 weeks")) -> OK | L6: =TODAY()-(505) -> 45792 | N6: =IF(OR($A6="",NOT(ISNUMBER($L6))),IF($A6="","","Not recorded"),IF(NOT(ISNUMBER($M6)),"Checked (no follow-up)",IF($M6<TODAY(),"OVERDUE: follow-up check",IF($M6-TODAY()<=60,"Follow-up due "&TEXT($M6,"dd/mm/yyyy"),"Checked")))) -> Checked (no follow-up) | O6: =TODAY()-(500) -> 45797 | P6: =TODAY()-(150) -> 46147 | Q6: =IF($A6="","",IF(NOT(ISNUMBER($D6)),"Enter start date",IF($D6>=DATE(2026,5,1),IF(ISNUMBER($O6),"Complete","Missing: written terms"),IF(OR(ISNUMBER($P6),ISNUMBER($O6)),"Complete","Missing: Information Sheet (was due 31/05/2026)")))) -> Complete | R6: =TODAY()-(200) -> 46097 | S6: =IF(ISNUMBER($R6),$R6+364,IF(ISNUMBER($D6),$D6+364,"")) -> 46461 | U6: =IF(ISNUMBER($T6),IF(ISNUMBER($S6),MAX(EDATE($T6,2),$S6),EDATE($T6,2)),"") | X6: =IF(NOT(ISNUMBER($V6)),"",IF(ISNUMBER($W6),IF($W6-$V6<=28,"Answered in time","LATE: answered after day 28"),IF(TODAY()-$V6>28,"OVERDUE: no reply yet","Reply due by "&TEXT($V6+28,"dd/mm/yyyy")))) | Y6: SAMPLE ROW
A7: SAMPLE CD | B7: SAMPLE - 12 Acacia Road, Exampleton | C7: Room 2 | D7: =TODAY()-(40) -> 46257 | E7: 575 | F7: 650 | G7: =TODAY()-(40) -> 46257 | J7: =IF(OR($A7="",NOT(ISNUMBER($F7))),"",IF($F7<=0,"No deposit",IF(NOT(ISNUMBER($G7)),"Enter date received",IF(AND(ISNUMBER($H7),ISNUMBER($I7)),IF(MAX($H7,$I7)-$G7<=29,"OK","LATE: protected / info served after day 30"),IF(TODAY()-$G7>29,"OVERDUE: not protected / info not served","Protect + serve info by "&TEXT($G7+29,"dd/mm/yyyy")))))) -> OVERDUE: not protected / info not served | K7: =IF(OR(NOT(ISNUMBER($E7)),NOT(ISNUMBER($F7))),"",IF($F7<=$E7*12/52*5,"OK","Over 5 weeks")) -> OK | L7: =TODAY()-(41) -> 46256 | M7: =TODAY()+(100) -> 46397 | N7: =IF(OR($A7="",NOT(ISNUMBER($L7))),IF($A7="","","Not recorded"),IF(NOT(ISNUMBER($M7)),"Checked (no follow-up)",IF($M7<TODAY(),"OVERDUE: follow-up check",IF($M7-TODAY()<=60,"Follow-up due "&TEXT($M7,"dd/mm/yyyy"),"Checked")))) -> Checked | Q7: =IF($A7="","",IF(NOT(ISNUMBER($D7)),"Enter start date",IF($D7>=DATE(2026,5,1),IF(ISNUMBER($O7),"Complete","Missing: written terms"),IF(OR(ISNUMBER($P7),ISNUMBER($O7)),"Complete","Missing: Information Sheet (was due 31/05/2026)")))) -> Missing: written terms | S7: =IF(ISNUMBER($R7),$R7+364,IF(ISNUMBER($D7),$D7+364,"")) -> 46621 | U7: =IF(ISNUMBER($T7),IF(ISNUMBER($S7),MAX(EDATE($T7,2),$S7),EDATE($T7,2)),"") | V7: =TODAY()-(10) -> 46287 | X7: =IF(NOT(ISNUMBER($V7)),"",IF(ISNUMBER($W7),IF($W7-$V7<=28,"Answered in time","LATE: answered after day 28"),IF(TODAY()-$V7>28,"OVERDUE: no reply yet","Reply due by "&TEXT($V7+28,"dd/mm/yyyy")))) -> Reply due by 20/10/2026 | Y7: SAMPLE ROW: deposit not yet protected (red); written terms missing (new tenancy); pet request awaiting reply
A8: SAMPLE EF | B8: SAMPLE - Flat 3, 8 Demo Street, Sampleford | C8: Room A | D8: =TODAY()-(700) -> 45597 | E8: 480 | F8: 480 | G8: =TODAY()-(700) -> 45597 | H8: =TODAY()-(695) -> 45602 | I8: =TODAY()-(695) -> 45602 | J8: =IF(OR($A8="",NOT(ISNUMBER($F8))),"",IF($F8<=0,"No deposit",IF(NOT(ISNUMBER($G8)),"Enter date received",IF(AND(ISNUMBER($H8),ISNUMBER($I8)),IF(MAX($H8,$I8)-$G8<=29,"OK","LATE: protected / info served after day 30"),IF(TODAY()-$G8>29,"OVERDUE: not protected / info not served","Protect + serve info by "&TEXT($G8+29,"dd/mm/yyyy")))))) -> OK | K8: =IF(OR(NOT(ISNUMBER($E8)),NOT(ISNUMBER($F8))),"",IF($F8<=$E8*12/52*5,"OK","Over 5 weeks")) -> OK | L8: =TODAY()-(705) -> 45592 | M8: =TODAY()+(20) -> 46317 | N8: =IF(OR($A8="",NOT(ISNUMBER($L8))),IF($A8="","","Not recorded"),IF(NOT(ISNUMBER($M8)),"Checked (no follow-up)",IF($M8<TODAY(),"OVERDUE: follow-up check",IF($M8-TODAY()<=60,"Follow-up due "&TEXT($M8,"dd/mm/yyyy"),"Checked")))) -> Follow-up due 22/10/2026 | O8: =TODAY()-(700) -> 45597 | P8: =TODAY()-(140) -> 46157 | Q8: =IF($A8="","",IF(NOT(ISNUMBER($D8)),"Enter start date",IF($D8>=DATE(2026,5,1),IF(ISNUMBER($O8),"Complete","Missing: written terms"),IF(OR(ISNUMBER($P8),ISNUMBER($O8)),"Complete","Missing: Information Sheet (was due 31/05/2026)")))) -> Complete | R8: =TODAY()-(400) -> 45897 | S8: =IF(ISNUMBER($R8),$R8+364,IF(ISNUMBER($D8),$D8+364,"")) -> 46261 | T8: =TODAY()-(15) -> 46282 | U8: =IF(ISNUMBER($T8),IF(ISNUMBER($S8),MAX(EDATE($T8,2),$S8),EDATE($T8,2)),"") -> 46343 | X8: =IF(NOT(ISNUMBER($V8)),"",IF(ISNUMBER($W8),IF($W8-$V8<=28,"Answered in time","LATE: answered after day 28"),IF(TODAY()-$V8>28,"OVERDUE: no reply yet","Reply due by "&TEXT($V8+28,"dd/mm/yyyy")))) | Y8: SAMPLE ROW: Right to Rent follow-up due soon; Section 13 notice served
A9: SAMPLE GH | B9: SAMPLE - Flat 3, 8 Demo Street, Sampleford | C9: Room B | D9: =TODAY()-(30) -> 46267 | E9: 520 | F9: 900 | G9: =TODAY()-(30) -> 46267 | H9: =TODAY()-(28) -> 46269 | I9: =TODAY()-(28) -> 46269 | J9: =IF(OR($A9="",NOT(ISNUMBER($F9))),"",IF($F9<=0,"No deposit",IF(NOT(ISNUMBER($G9)),"Enter date received",IF(AND(ISNUMBER($H9),ISNUMBER($I9)),IF(MAX($H9,$I9)-$G9<=29,"OK","LATE: protected / info served after day 30"),IF(TODAY()-$G9>29,"OVERDUE: not protected / info not served","Protect + serve info by "&TEXT($G9+29,"dd/mm/yyyy")))))) -> OK | K9: =IF(OR(NOT(ISNUMBER($E9)),NOT(ISNUMBER($F9))),"",IF($F9<=$E9*12/52*5,"OK","Over 5 weeks")) -> Over 5 weeks | L9: =TODAY()-(30) -> 46267 | N9: =IF(OR($A9="",NOT(ISNUMBER($L9))),IF($A9="","","Not recorded"),IF(NOT(ISNUMBER($M9)),"Checked (no follow-up)",IF($M9<TODAY(),"OVERDUE: follow-up check",IF($M9-TODAY()<=60,"Follow-up due "&TEXT($M9,"dd/mm/yyyy"),"Checked")))) -> Checked (no follow-up) | O9: =TODAY()-(30) -> 46267 | P9: =TODAY()-(30) -> 46267 | Q9: =IF($A9="","",IF(NOT(ISNUMBER($D9)),"Enter start date",IF($D9>=DATE(2026,5,1),IF(ISNUMBER($O9),"Complete","Missing: written terms"),IF(OR(ISNUMBER($P9),ISNUMBER($O9)),"Complete","Missing: Information Sheet (was due 31/05/2026)")))) -> Complete | S9: =IF(ISNUMBER($R9),$R9+364,IF(ISNUMBER($D9),$D9+364,"")) -> 46631 | U9: =IF(ISNUMBER($T9),IF(ISNUMBER($S9),MAX(EDATE($T9,2),$S9),EDATE($T9,2)),"") | V9: =TODAY()-(60) -> 46237 | W9: =TODAY()-(40) -> 46257 | X9: =IF(NOT(ISNUMBER($V9)),"",IF(ISNUMBER($W9),IF($W9-$V9<=28,"Answered in time","LATE: answered after day 28"),IF(TODAY()-$V9>28,"OVERDUE: no reply yet","Reply due by "&TEXT($V9+28,"dd/mm/yyyy")))) -> Answered in time | Y9: SAMPLE ROW: deposit above the 5-week cap (flag shown)
J10: =IF(OR($A10="",NOT(ISNUMBER($F10))),"",IF($F10<=0,"No deposit",IF(NOT(ISNUMBER($G10)),"Enter date received",IF(AND(ISNUMBER($H10),ISNUMBER($I10)),IF(MAX($H10,$I10)-$G10<=29,"OK","LATE: protected / info served after day 30"),IF(TODAY()-$G10>29,"OVERDUE: not protected / info not served","Protect + serve info by "&TEXT($G10+29,"dd/mm/yyyy")))))) | K10: =IF(OR(NOT(ISNUMBER($E10)),NOT(ISNUMBER($F10))),"",IF($F10<=$E10*12/52*5,"OK","Over 5 weeks")) | N10: =IF(OR($A10="",NOT(ISNUMBER($L10))),IF($A10="","","Not recorded"),IF(NOT(ISNUMBER($M10)),"Checked (no follow-up)",IF($M10<TODAY(),"OVERDUE: follow-up check",IF($M10-TODAY()<=60,"Follow-up due "&TEXT($M10,"dd/mm/yyyy"),"Checked")))) | Q10: =IF($A10="","",IF(NOT(ISNUMBER($D10)),"Enter start date",IF($D10>=DATE(2026,5,1),IF(ISNUMBER($O10),"Complete","Missing: written terms"),IF(OR(ISNUMBER($P10),ISNUMBER($O10)),"Complete","Missing: Information Sheet (was due 31/05/2026)")))) | S10: =IF(ISNUMBER($R10),$R10+364,IF(ISNUMBER($D10),$D10+364,"")) | U10: =IF(ISNUMBER($T10),IF(ISNUMBER($S10),MAX(EDATE($T10,2),$S10),EDATE($T10,2)),"") | X10: =IF(NOT(ISNUMBER($V10)),"",IF(ISNUMBER($W10),IF($W10-$V10<=28,"Answered in time","LATE: answered after day 28"),IF(TODAY()-$V10>28,"OVERDUE: no reply yet","Reply due by "&TEXT($V10+28,"dd/mm/yyyy"))))
J11: =IF(OR($A11="",NOT(ISNUMBER($F11))),"",IF($F11<=0,"No deposit",IF(NOT(ISNUMBER($G11)),"Enter date received",IF(AND(ISNUMBER($H11),ISNUMBER($I11)),IF(MAX($H11,$I11)-$G11<=29,"OK","LATE: protected / info served after day 30"),IF(TODAY()-$G11>29,"OVERDUE: not protected / info not served","Protect + serve info by "&TEXT($G11+29,"dd/mm/yyyy")))))) | K11: =IF(OR(NOT(ISNUMBER($E11)),NOT(ISNUMBER($F11))),"",IF($F11<=$E11*12/52*5,"OK","Over 5 weeks")) | N11: =IF(OR($A11="",NOT(ISNUMBER($L11))),IF($A11="","","Not recorded"),IF(NOT(ISNUMBER($M11)),"Checked (no follow-up)",IF($M11<TODAY(),"OVERDUE: follow-up check",IF($M11-TODAY()<=60,"Follow-up due "&TEXT($M11,"dd/mm/yyyy"),"Checked")))) | Q11: =IF($A11="","",IF(NOT(ISNUMBER($D11)),"Enter start date",IF($D11>=DATE(2026,5,1),IF(ISNUMBER($O11),"Complete","Missing: written terms"),IF(OR(ISNUMBER($P11),ISNUMBER($O11)),"Complete","Missing: Information Sheet (was due 31/05/2026)")))) | S11: =IF(ISNUMBER($R11),$R11+364,IF(ISNUMBER($D11),$D11+364,"")) | U11: =IF(ISNUMBER($T11),IF(ISNUMBER($S11),MAX(EDATE($T11,2),$S11),EDATE($T11,2)),"") | X11: =IF(NOT(ISNUMBER($V11)),"",IF(ISNUMBER($W11),IF($W11-$V11<=28,"Answered in time","LATE: answered after day 28"),IF(TODAY()-$V11>28,"OVERDUE: no reply yet","Reply due by "&TEXT($V11+28,"dd/mm/yyyy"))))
J12: =IF(OR($A12="",NOT(ISNUMBER($F12))),"",IF($F12<=0,"No deposit",IF(NOT(ISNUMBER($G12)),"Enter date received",IF(AND(ISNUMBER($H12),ISNUMBER($I12)),IF(MAX($H12,$I12)-$G12<=29,"OK","LATE: protected / info served after day 30"),IF(TODAY()-$G12>29,"OVERDUE: not protected / info not served","Protect + serve info by "&TEXT($G12+29,"dd/mm/yyyy")))))) | K12: =IF(OR(NOT(ISNUMBER($E12)),NOT(ISNUMBER($F12))),"",IF($F12<=$E12*12/52*5,"OK","Over 5 weeks")) | N12: =IF(OR($A12="",NOT(ISNUMBER($L12))),IF($A12="","","Not recorded"),IF(NOT(ISNUMBER($M12)),"Checked (no follow-up)",IF($M12<TODAY(),"OVERDUE: follow-up check",IF($M12-TODAY()<=60,"Follow-up due "&TEXT($M12,"dd/mm/yyyy"),"Checked")))) | Q12: =IF($A12="","",IF(NOT(ISNUMBER($D12)),"Enter start date",IF($D12>=DATE(2026,5,1),IF(ISNUMBER($O12),"Complete","Missing: written terms"),IF(OR(ISNUMBER($P12),ISNUMBER($O12)),"Complete","Missing: Information Sheet (was due 31/05/2026)")))) | S12: =IF(ISNUMBER($R12),$R12+364,IF(ISNUMBER($D12),$D12+364,"")) | U12: =IF(ISNUMBER($T12),IF(ISNUMBER($S12),MAX(EDATE($T12,2),$S12),EDATE($T12,2)),"") | X12: =IF(NOT(ISNUMBER($V12)),"",IF(ISNUMBER($W12),IF($W12-$V12<=28,"Answered in time","LATE: answered after day 28"),IF(TODAY()-$V12>28,"OVERDUE: no reply yet","Reply due by "&TEXT($V12+28,"dd/mm/yyyy"))))
J13: =IF(OR($A13="",NOT(ISNUMBER($F13))),"",IF($F13<=0,"No deposit",IF(NOT(ISNUMBER($G13)),"Enter date received",IF(AND(ISNUMBER($H13),ISNUMBER($I13)),IF(MAX($H13,$I13)-$G13<=29,"OK","LATE: protected / info served after day 30"),IF(TODAY()-$G13>29,"OVERDUE: not protected / info not served","Protect + serve info by "&TEXT($G13+29,"dd/mm/yyyy")))))) | K13: =IF(OR(NOT(ISNUMBER($E13)),NOT(ISNUMBER($F13))),"",IF($F13<=$E13*12/52*5,"OK","Over 5 weeks")) | N13: =IF(OR($A13="",NOT(ISNUMBER($L13))),IF($A13="","","Not recorded"),IF(NOT(ISNUMBER($M13)),"Checked (no follow-up)",IF($M13<TODAY(),"OVERDUE: follow-up check",IF($M13-TODAY()<=60,"Follow-up due "&TEXT($M13,"dd/mm/yyyy"),"Checked")))) | Q13: =IF($A13="","",IF(NOT(ISNUMBER($D13)),"Enter start date",IF($D13>=DATE(2026,5,1),IF(ISNUMBER($O13),"Complete","Missing: written terms"),IF(OR(ISNUMBER($P13),ISNUMBER($O13)),"Complete","Missing: Information Sheet (was due 31/05/2026)")))) | S13: =IF(ISNUMBER($R13),$R13+364,IF(ISNUMBER($D13),$D13+364,"")) | U13: =IF(ISNUMBER($T13),IF(ISNUMBER($S13),MAX(EDATE($T13,2),$S13),EDATE($T13,2)),"") | X13: =IF(NOT(ISNUMBER($V13)),"",IF(ISNUMBER($W13),IF($W13-$V13<=28,"Answered in time","LATE: answered after day 28"),IF(TODAY()-$V13>28,"OVERDUE: no reply yet","Reply due by "&TEXT($V13+28,"dd/mm/yyyy"))))
J14: =IF(OR($A14="",NOT(ISNUMBER($F14))),"",IF($F14<=0,"No deposit",IF(NOT(ISNUMBER($G14)),"Enter date received",IF(AND(ISNUMBER($H14),ISNUMBER($I14)),IF(MAX($H14,$I14)-$G14<=29,"OK","LATE: protected / info served after day 30"),IF(TODAY()-$G14>29,"OVERDUE: not protected / info not served","Protect + serve info by "&TEXT($G14+29,"dd/mm/yyyy")))))) | K14: =IF(OR(NOT(ISNUMBER($E14)),NOT(ISNUMBER($F14))),"",IF($F14<=$E14*12/52*5,"OK","Over 5 weeks")) | N14: =IF(OR($A14="",NOT(ISNUMBER($L14))),IF($A14="","","Not recorded"),IF(NOT(ISNUMBER($M14)),"Checked (no follow-up)",IF($M14<TODAY(),"OVERDUE: follow-up check",IF($M14-TODAY()<=60,"Follow-up due "&TEXT($M14,"dd/mm/yyyy"),"Checked")))) | Q14: =IF($A14="","",IF(NOT(ISNUMBER($D14)),"Enter start date",IF($D14>=DATE(2026,5,1),IF(ISNUMBER($O14),"Complete","Missing: written terms"),IF(OR(ISNUMBER($P14),ISNUMBER($O14)),"Complete","Missing: Information Sheet (was due 31/05/2026)")))) | S14: =IF(ISNUMBER($R14),$R14+364,IF(ISNUMBER($D14),$D14+364,"")) | U14: =IF(ISNUMBER($T14),IF(ISNUMBER($S14),MAX(EDATE($T14,2),$S14),EDATE($T14,2)),"") | X14: =IF(NOT(ISNUMBER($V14)),"",IF(ISNUMBER($W14),IF($W14-$V14<=28,"Answered in time","LATE: answered after day 28"),IF(TODAY()-$V14>28,"OVERDUE: no reply yet","Reply due by "&TEXT($V14+28,"dd/mm/yyyy"))))
J15: =IF(OR($A15="",NOT(ISNUMBER($F15))),"",IF($F15<=0,"No deposit",IF(NOT(ISNUMBER($G15)),"Enter date received",IF(AND(ISNUMBER($H15),ISNUMBER($I15)),IF(MAX($H15,$I15)-$G15<=29,"OK","LATE: protected / info served after day 30"),IF(TODAY()-$G15>29,"OVERDUE: not protected / info not served","Protect + serve info by "&TEXT($G15+29,"dd/mm/yyyy")))))) | K15: =IF(OR(NOT(ISNUMBER($E15)),NOT(ISNUMBER($F15))),"",IF($F15<=$E15*12/52*5,"OK","Over 5 weeks")) | N15: =IF(OR($A15="",NOT(ISNUMBER($L15))),IF($A15="","","Not recorded"),IF(NOT(ISNUMBER($M15)),"Checked (no follow-up)",IF($M15<TODAY(),"OVERDUE: follow-up check",IF($M15-TODAY()<=60,"Follow-up due "&TEXT($M15,"dd/mm/yyyy"),"Checked")))) | Q15: =IF($A15="","",IF(NOT(ISNUMBER($D15)),"Enter start date",IF($D15>=DATE(2026,5,1),IF(ISNUMBER($O15),"Complete","Missing: written terms"),IF(OR(ISNUMBER($P15),ISNUMBER($O15)),"Complete","Missing: Information Sheet (was due 31/05/2026)")))) | S15: =IF(ISNUMBER($R15),$R15+364,IF(ISNUMBER($D15),$D15+364,"")) | U15: =IF(ISNUMBER($T15),IF(ISNUMBER($S15),MAX(EDATE($T15,2),$S15),EDATE($T15,2)),"") | X15: =IF(NOT(ISNUMBER($V15)),"",IF(ISNUMBER($W15),IF($W15-$V15<=28,"Answered in time","LATE: answered after day 28"),IF(TODAY()-$V15>28,"OVERDUE: no reply yet","Reply due by "&TEXT($V15+28,"dd/mm/yyyy"))))
J16: =IF(OR($A16="",NOT(ISNUMBER($F16))),"",IF($F16<=0,"No deposit",IF(NOT(ISNUMBER($G16)),"Enter date received",IF(AND(ISNUMBER($H16),ISNUMBER($I16)),IF(MAX($H16,$I16)-$G16<=29,"OK","LATE: protected / info served after day 30"),IF(TODAY()-$G16>29,"OVERDUE: not protected / info not served","Protect + serve info by "&TEXT($G16+29,"dd/mm/yyyy")))))) | K16: =IF(OR(NOT(ISNUMBER($E16)),NOT(ISNUMBER($F16))),"",IF($F16<=$E16*12/52*5,"OK","Over 5 weeks")) | N16: =IF(OR($A16="",NOT(ISNUMBER($L16))),IF($A16="","","Not recorded"),IF(NOT(ISNUMBER($M16)),"Checked (no follow-up)",IF($M16<TODAY(),"OVERDUE: follow-up check",IF($M16-TODAY()<=60,"Follow-up due "&TEXT($M16,"dd/mm/yyyy"),"Checked")))) | Q16: =IF($A16="","",IF(NOT(ISNUMBER($D16)),"Enter start date",IF($D16>=DATE(2026,5,1),IF(ISNUMBER($O16),"Complete","Missing: written terms"),IF(OR(ISNUMBER($P16),ISNUMBER($O16)),"Complete","Missing: Information Sheet (was due 31/05/2026)")))) | S16: =IF(ISNUMBER($R16),$R16+364,IF(ISNUMBER($D16),$D16+364,"")) | U16: =IF(ISNUMBER($T16),IF(ISNUMBER($S16),MAX(EDATE($T16,2),$S16),EDATE($T16,2)),"") | X16: =IF(NOT(ISNUMBER($V16)),"",IF(ISNUMBER($W16),IF($W16-$V16<=28,"Answered in time","LATE: answered after day 28"),IF(TODAY()-$V16>28,"OVERDUE: no reply yet","Reply due by "&TEXT($V16+28,"dd/mm/yyyy"))))
J17: =IF(OR($A17="",NOT(ISNUMBER($F17))),"",IF($F17<=0,"No deposit",IF(NOT(ISNUMBER($G17)),"Enter date received",IF(AND(ISNUMBER($H17),ISNUMBER($I17)),IF(MAX($H17,$I17)-$G17<=29,"OK","LATE: protected / info served after day 30"),IF(TODAY()-$G17>29,"OVERDUE: not protected / info not served","Protect + serve info by "&TEXT($G17+29,"dd/mm/yyyy")))))) | K17: =IF(OR(NOT(ISNUMBER($E17)),NOT(ISNUMBER($F17))),"",IF($F17<=$E17*12/52*5,"OK","Over 5 weeks")) | N17: =IF(OR($A17="",NOT(ISNUMBER($L17))),IF($A17="","","Not recorded"),IF(NOT(ISNUMBER($M17)),"Checked (no follow-up)",IF($M17<TODAY(),"OVERDUE: follow-up check",IF($M17-TODAY()<=60,"Follow-up due "&TEXT($M17,"dd/mm/yyyy"),"Checked")))) | Q17: =IF($A17="","",IF(NOT(ISNUMBER($D17)),"Enter start date",IF($D17>=DATE(2026,5,1),IF(ISNUMBER($O17),"Complete","Missing: written terms"),IF(OR(ISNUMBER($P17),ISNUMBER($O17)),"Complete","Missing: Information Sheet (was due 31/05/2026)")))) | S17: =IF(ISNUMBER($R17),$R17+364,IF(ISNUMBER($D17),$D17+364,"")) | U17: =IF(ISNUMBER($T17),IF(ISNUMBER($S17),MAX(EDATE($T17,2),$S17),EDATE($T17,2)),"") | X17: =IF(NOT(ISNUMBER($V17)),"",IF(ISNUMBER($W17),IF($W17-$V17<=28,"Answered in time","LATE: answered after day 28"),IF(TODAY()-$V17>28,"OVERDUE: no reply yet","Reply due by "&TEXT($V17+28,"dd/mm/yyyy"))))
J18: =IF(OR($A18="",NOT(ISNUMBER($F18))),"",IF($F18<=0,"No deposit",IF(NOT(ISNUMBER($G18)),"Enter date received",IF(AND(ISNUMBER($H18),ISNUMBER($I18)),IF(MAX($H18,$I18)-$G18<=29,"OK","LATE: protected / info served after day 30"),IF(TODAY()-$G18>29,"OVERDUE: not protected / info not served","Protect + serve info by "&TEXT($G18+29,"dd/mm/yyyy")))))) | K18: =IF(OR(NOT(ISNUMBER($E18)),NOT(ISNUMBER($F18))),"",IF($F18<=$E18*12/52*5,"OK","Over 5 weeks")) | N18: =IF(OR($A18="",NOT(ISNUMBER($L18))),IF($A18="","","Not recorded"),IF(NOT(ISNUMBER($M18)),"Checked (no follow-up)",IF($M18<TODAY(),"OVERDUE: follow-up check",IF($M18-TODAY()<=60,"Follow-up due "&TEXT($M18,"dd/mm/yyyy"),"Checked")))) | Q18: =IF($A18="","",IF(NOT(ISNUMBER($D18)),"Enter start date",IF($D18>=DATE(2026,5,1),IF(ISNUMBER($O18),"Complete","Missing: written terms"),IF(OR(ISNUMBER($P18),ISNUMBER($O18)),"Complete","Missing: Information Sheet (was due 31/05/2026)")))) | S18: =IF(ISNUMBER($R18),$R18+364,IF(ISNUMBER($D18),$D18+364,"")) | U18: =IF(ISNUMBER($T18),IF(ISNUMBER($S18),MAX(EDATE($T18,2),$S18),EDATE($T18,2)),"") | X18: =IF(NOT(ISNUMBER($V18)),"",IF(ISNUMBER($W18),IF($W18-$V18<=28,"Answered in time","LATE: answered after day 28"),IF(TODAY()-$V18>28,"OVERDUE: no reply yet","Reply due by "&TEXT($V18+28,"dd/mm/yyyy"))))
J19: =IF(OR($A19="",NOT(ISNUMBER($F19))),"",IF($F19<=0,"No deposit",IF(NOT(ISNUMBER($G19)),"Enter date received",IF(AND(ISNUMBER($H19),ISNUMBER($I19)),IF(MAX($H19,$I19)-$G19<=29,"OK","LATE: protected / info served after day 30"),IF(TODAY()-$G19>29,"OVERDUE: not protected / info not served","Protect + serve info by "&TEXT($G19+29,"dd/mm/yyyy")))))) | K19: =IF(OR(NOT(ISNUMBER($E19)),NOT(ISNUMBER($F19))),"",IF($F19<=$E19*12/52*5,"OK","Over 5 weeks")) | N19: =IF(OR($A19="",NOT(ISNUMBER($L19))),IF($A19="","","Not recorded"),IF(NOT(ISNUMBER($M19)),"Checked (no follow-up)",IF($M19<TODAY(),"OVERDUE: follow-up check",IF($M19-TODAY()<=60,"Follow-up due "&TEXT($M19,"dd/mm/yyyy"),"Checked")))) | Q19: =IF($A19="","",IF(NOT(ISNUMBER($D19)),"Enter start date",IF($D19>=DATE(2026,5,1),IF(ISNUMBER($O19),"Complete","Missing: written terms"),IF(OR(ISNUMBER($P19),ISNUMBER($O19)),"Complete","Missing: Information Sheet (was due 31/05/2026)")))) | S19: =IF(ISNUMBER($R19),$R19+364,IF(ISNUMBER($D19),$D19+364,"")) | U19: =IF(ISNUMBER($T19),IF(ISNUMBER($S19),MAX(EDATE($T19,2),$S19),EDATE($T19,2)),"") | X19: =IF(NOT(ISNUMBER($V19)),"",IF(ISNUMBER($W19),IF($W19-$V19<=28,"Answered in time","LATE: answered after day 28"),IF(TODAY()-$V19>28,"OVERDUE: no reply yet","Reply due by "&TEXT($V19+28,"dd/mm/yyyy"))))
J20: =IF(OR($A20="",NOT(ISNUMBER($F20))),"",IF($F20<=0,"No deposit",IF(NOT(ISNUMBER($G20)),"Enter date received",IF(AND(ISNUMBER($H20),ISNUMBER($I20)),IF(MAX($H20,$I20)-$G20<=29,"OK","LATE: protected / info served after day 30"),IF(TODAY()-$G20>29,"OVERDUE: not protected / info not served","Protect + serve info by "&TEXT($G20+29,"dd/mm/yyyy")))))) | K20: =IF(OR(NOT(ISNUMBER($E20)),NOT(ISNUMBER($F20))),"",IF($F20<=$E20*12/52*5,"OK","Over 5 weeks")) | N20: =IF(OR($A20="",NOT(ISNUMBER($L20))),IF($A20="","","Not recorded"),IF(NOT(ISNUMBER($M20)),"Checked (no follow-up)",IF($M20<TODAY(),"OVERDUE: follow-up check",IF($M20-TODAY()<=60,"Follow-up due "&TEXT($M20,"dd/mm/yyyy"),"Checked")))) | Q20: =IF($A20="","",IF(NOT(ISNUMBER($D20)),"Enter start date",IF($D20>=DATE(2026,5,1),IF(ISNUMBER($O20),"Complete","Missing: written terms"),IF(OR(ISNUMBER($P20),ISNUMBER($O20)),"Complete","Missing: Information Sheet (was due 31/05/2026)")))) | S20: =IF(ISNUMBER($R20),$R20+364,IF(ISNUMBER($D20),$D20+364,"")) | U20: =IF(ISNUMBER($T20),IF(ISNUMBER($S20),MAX(EDATE($T20,2),$S20),EDATE($T20,2)),"") | X20: =IF(NOT(ISNUMBER($V20)),"",IF(ISNUMBER($W20),IF($W20-$V20<=28,"Answered in time","LATE: answered after day 28"),IF(TODAY()-$V20>28,"OVERDUE: no reply yet","Reply due by "&TEXT($V20+28,"dd/mm/yyyy"))))
J21: =IF(OR($A21="",NOT(ISNUMBER($F21))),"",IF($F21<=0,"No deposit",IF(NOT(ISNUMBER($G21)),"Enter date received",IF(AND(ISNUMBER($H21),ISNUMBER($I21)),IF(MAX($H21,$I21)-$G21<=29,"OK","LATE: protected / info served after day 30"),IF(TODAY()-$G21>29,"OVERDUE: not protected / info not served","Protect + serve info by "&TEXT($G21+29,"dd/mm/yyyy")))))) | K21: =IF(OR(NOT(ISNUMBER($E21)),NOT(ISNUMBER($F21))),"",IF($F21<=$E21*12/52*5,"OK","Over 5 weeks")) | N21: =IF(OR($A21="",NOT(ISNUMBER($L21))),IF($A21="","","Not recorded"),IF(NOT(ISNUMBER($M21)),"Checked (no follow-up)",IF($M21<TODAY(),"OVERDUE: follow-up check",IF($M21-TODAY()<=60,"Follow-up due "&TEXT($M21,"dd/mm/yyyy"),"Checked")))) | Q21: =IF($A21="","",IF(NOT(ISNUMBER($D21)),"Enter start date",IF($D21>=DATE(2026,5,1),IF(ISNUMBER($O21),"Complete","Missing: written terms"),IF(OR(ISNUMBER($P21),ISNUMBER($O21)),"Complete","Missing: Information Sheet (was due 31/05/2026)")))) | S21: =IF(ISNUMBER($R21),$R21+364,IF(ISNUMBER($D21),$D21+364,"")) | U21: =IF(ISNUMBER($T21),IF(ISNUMBER($S21),MAX(EDATE($T21,2),$S21),EDATE($T21,2)),"") | X21: =IF(NOT(ISNUMBER($V21)),"",IF(ISNUMBER($W21),IF($W21-$V21<=28,"Answered in time","LATE: answered after day 28"),IF(TODAY()-$V21>28,"OVERDUE: no reply yet","Reply due by "&TEXT($V21+28,"dd/mm/yyyy"))))
... J505: =IF(OR($A505="",NOT(ISNUMBER($F505))),"",IF($F505<=0,"No deposit",IF(NOT(ISNUMBER($G505)),"Enter date received",IF(AND(ISNUMBER($H505),ISNUMBER($I505)),IF(MAX($H505,$I505)-$G505<=29,"OK","LATE: protected / info served after day 30"),IF(TODAY()-$G505>29,"OVERDUE: not protected / info not served","Protect + serve info by "&TEXT($G505+29,"dd/mm/yyyy")))))) | K505: =IF(OR(NOT(ISNUMBER($E505)),NOT(ISNUMBER($F505))),"",IF($F505<=$E505*12/52*5,"OK","Over 5 weeks")) | N505: =IF(OR($A505="",NOT(ISNUMBER($L505))),IF($A505="","","Not recorded"),IF(NOT(ISNUMBER($M505)),"Checked (no follow-up)",IF($M505<TODAY(),"OVERDUE: follow-up check",IF($M505-TODAY()<=60,"Follow-up due "&TEXT($M505,"dd/mm/yyyy"),"Checked")))) | Q505: =IF($A505="","",IF(NOT(ISNUMBER($D505)),"Enter start date",IF($D505>=DATE(2026,5,1),IF(ISNUMBER($O505),"Complete","Missing: written terms"),IF(OR(ISNUMBER($P505),ISNUMBER($O505)),"Complete","Missing: Information Sheet (was due 31/05/2026)")))) | S505: =IF(ISNUMBER($R505),$R505+364,IF(ISNUMBER($D505),$D505+364,"")) | U505: =IF(ISNUMBER($T505),IF(ISNUMBER($S505),MAX(EDATE($T505,2),$S505),EDATE($T505,2)),"") | X505: =IF(NOT(ISNUMBER($V505)),"",IF(ISNUMBER($W505),IF($W505-$V505<=28,"Answered in time","LATE: answered after day 28"),IF(TODAY()-$V505>28,"OVERDUE: no reply yet","Reply due by "&TEXT($V505+28,"dd/mm/yyyy"))))

Sheet Contractors
A1: =IF(TRIM('Start Here'!$C$20)="","HMO Compliance Tracker 2026",TRIM('Start Here'!$C$20))&IF(TRIM('Start Here'!$C$21)="",""," | "&TRIM('Start Here'!$C$21))&IF(TRIM('Start Here'!$C$22)="",""," | "&TRIM('Start Here'!$C$22))&IF(TRIM('Start Here'!$C$23)="",""," | "&TRIM('Start Here'!$C$23)) -> HMO Compliance Tracker 2026
A2: Contractors
A3: Your trusted tradespeople. Check registrations on the relevant register before use (for example the Gas Safe Register for gas work). Rows marked SAMPLE show how it works.
A5: Name | B5: Trade | C5: Registered with (e.g. Gas Safe, NICEIC, NAPIT) | D5: Registration no. | E5: Phone | F5: Email | G5: Last used | H5: Notes
A6: SAMPLE Gas Engineer Ltd | B6: Gas engineer | C6: Gas Safe | D6: SAMPLE-000000 | E6: 01632 960001 | F6: sample@example.com | G6: =TODAY()-(120) -> 46177 | H6: SAMPLE ROW. Always check the Gas Safe Register.
A7: SAMPLE Electrics Ltd | B7: Electrician | C7: NICEIC | D7: SAMPLE-000000 | E7: 01632 960002 | F7: sample@example.com | G7: =TODAY()-(365) -> 45932 | H7: SAMPLE ROW
A8: SAMPLE Fire Safety Ltd | B8: Fire alarm engineer | C8: BAFE | D8: SAMPLE-000000 | E8: 01632 960003 | F8: sample@example.com | G8: =TODAY()-(90) -> 46207 | H8: SAMPLE ROW

Sheet Reference
A1: =IF(TRIM('Start Here'!$C$20)="","HMO Compliance Tracker 2026",TRIM('Start Here'!$C$20))&IF(TRIM('Start Here'!$C$21)="",""," | "&TRIM('Start Here'!$C$21))&IF(TRIM('Start Here'!$C$22)="",""," | "&TRIM('Start Here'!$C$22))&IF(TRIM('Start Here'!$C$23)="",""," | "&TRIM('Start Here'!$C$23)) -> HMO Compliance Tracker 2026
A2: Reference: what to check, how often, and why
A3: Column C (months) is the interval the Compliance Log uses; change it here and every row using that check updates. Type shows whether each item is LAW, official GUIDANCE, BEST PRACTICE or a typical LICENCE CONDITION. Where we could not confirm something from an official source it says CHECK LOCALLY. Add your own checks in the yellow rows.
A5: Requirement / check | B5: Applies to | C5: Interval (months) | D5: Typical frequency | E5: Type | F5: Legal basis | G5: Notes and penalty | H5: Official source URL | I5: Last checked
A6: Gas Safety Certificate (CP12) | B6: Any let home with a gas appliance, flue or pipework | C6: 12 | D6: Every 12 months | E6: LAW | F6: Gas Safety (Installation and Use) Regulations 1998 reg 36 and reg 3(3). Licensed HMOs: Housing Act 2004 Sch 4 para 1(2). Management of HMOs Regs 2006 reg 6(1). | G6: Check by a Gas Safe registered engineer at least every 12 months. A check done in the 2 months before the deadline keeps the same renewal date (reg 36A). Give existing tenants a copy within 28 days of the check and new tenants a copy before they move in; keep records for at least 2 years (HSE). Licensed HMOs: show the council a certificate under 12 months old every year; the manager must supply the latest certificate within 7 days of a written request. Penalties: not verified here, see HSE and your council. | H6: https://www.legislation.gov.uk/uksi/1998/2451/regulation/36 | I6: 02/10/2026
A7: Electrical Installation Condition Report (EICR) | B7: All privately rented homes in England, including HMOs | C7: 60 | D7: At least every 5 years (sooner if the report says) | E7: LAW | F7: Electrical Safety Standards in the Private Rented Sector (England) Regulations 2020 reg 3. Licensed HMOs: Housing Act 2004 Sch 4 para 1(3)(c). | G7: A qualified person inspects and tests the fixed electrical installation. Give existing tenants a copy within 28 days, new tenants before they move in, and the council within 7 days of a written request. Remedial work must be done within 28 days (or sooner if the report says). Civil penalty up to £40,000 (cap shown in the regulations from 1 May 2026). The old 5-yearly duty in the 2006 Management of HMOs Regs (reg 6(3) as made) was removed in 2020; these regulations replaced it. | H7: https://www.legislation.gov.uk/uksi/2020/312/regulation/3 | I7: 02/10/2026
A8: Energy Performance Certificate (EPC) | B8: Let homes that need an EPC (HMOs let room by room: check with your council) | C8: 120 | D8: Valid for 10 years | E8: LAW | F8: Energy Performance of Buildings (England and Wales) Regulations 2012; Domestic Minimum Energy Efficiency Standard (MEES) Regulations (band E). | G8: An EPC is valid if it was entered on the register no more than 10 years before it is made available. Official guidance: MEES applies to assured tenancies where an EPC is legally required; a property rated F or G needs improvements or a registered exemption (cost cap £3,500 including VAT). EPC band C by 2030 is a government aim, not yet law. Whether a room-by-room HMO needs an EPC: CHECK LOCALLY. | H8: https://www.gov.uk/guidance/domestic-private-rented-property-minimum-energy-efficiency-standard-landlord-guidance | I8: 02/10/2026
A9: Fire Risk Assessment - review | B9: Common parts of every HMO (the Fire Safety Order covers the non-domestic parts) | C9: 12 | D9: Review regularly; 12 months is common practice | E9: LAW (interval = practice) | F9: Regulatory Reform (Fire Safety) Order 2005 arts 9 and 17. | G9: The responsible person must make a suitable and sufficient fire risk assessment and review it regularly, particularly if it may no longer be valid or after significant change (art 9). The Order sets no fixed interval: the 12-month default is common practice, so change it if your assessor advises otherwise. The fire and rescue authority generally enforces the Order (art 25); penalties: not verified here. HM Government's sleeping-accommodation guide covers HMO common areas. | H9: https://www.legislation.gov.uk/uksi/2005/1541/article/9 | I9: 02/10/2026
A10: Fire alarm system - service | B10: HMOs with a fire detection and alarm system | C10: 6 | D10: Every 6 months by a competent person | E10: GUIDANCE | F10: RRO 2005 art 17 (maintenance); Management of HMOs Regs 2006 reg 4(2); HM Government guide 'Fire safety risk assessment: sleeping accommodation'. | G10: Official guidance: six-monthly testing and maintenance of the detection and warning system and emergency lighting by a competent person, and annual testing of installed fire systems. This is guidance, not a fixed legal interval; your licence or fire risk assessment may say differently, so follow it. Weekly alarm tests go on the Fire Safety Log. | H10: https://www.gov.uk/government/publications/fire-safety-risk-assessment-sleeping-accommodation/fire-safety-risk-assessment-sleeping-accommodation-accessible | I10: 02/10/2026
A11: Emergency lighting - monthly test | B11: HMOs with emergency escape lighting | C11: 1 | D11: Monthly function test | E11: GUIDANCE | F11: RRO 2005 art 17; HM Government guide 'Fire safety risk assessment: sleeping accommodation'. | G11: Official guidance: a monthly function test that makes each emergency lamp light, at a time when the lighting will not be needed straight after. Guidance, not statute. Your licence may require records. | H11: https://www.gov.uk/government/publications/fire-safety-risk-assessment-sleeping-accommodation/fire-safety-risk-assessment-sleeping-accommodation-accessible | I11: 02/10/2026
A12: Emergency lighting - annual full-discharge test | B12: HMOs with emergency escape lighting | C12: 12 | D12: Annually | E12: GUIDANCE | F12: RRO 2005 art 17; HM Government guide 'Fire safety risk assessment: sleeping accommodation' (points to BS 5266-8). | G12: Official guidance lists an annual full discharge test. Batteries typically take about 24 hours to recharge afterwards, so plan the test so the building is not left unprotected. Guidance, not statute. | H12: https://www.gov.uk/government/publications/fire-safety-risk-assessment-sleeping-accommodation/fire-safety-risk-assessment-sleeping-accommodation-accessible | I12: 02/10/2026
A13: Fire extinguishers - service | B13: HMOs with portable fire extinguishers | C13: 12 | D13: Annual service; monthly visual check | E13: GUIDANCE | F13: RRO 2005 art 17; HM Government guide 'Fire safety risk assessment: sleeping accommodation'. | G13: Official guidance: in normal conditions a monthly check should be enough, with maintenance by a competent person annually. Guidance, not statute. | H13: https://www.gov.uk/government/publications/fire-safety-risk-assessment-sleeping-accommodation/fire-safety-risk-assessment-sleeping-accommodation-accessible | I13: 02/10/2026
A14: Fire doors - monthly check | B14: HMO common parts with fire doors | C14: 1 | D14: Monthly check | E14: GUIDANCE | F14: HM Government guide 'Fire safety risk assessment: sleeping accommodation'. Fire Safety (England) Regulations 2022 reg 10 (taller buildings only). | G14: Official guidance: monthly check that fire doors close properly and frames and seals are intact. The law sets fixed intervals only for buildings above 11 metres with two or more sets of domestic premises (communal fire doors every 3 months; flat entrance doors every 12 months, best endeavours). Whether that applies to your building: CHECK LOCALLY. | H14: https://www.gov.uk/government/publications/fire-safety-risk-assessment-sleeping-accommodation/fire-safety-risk-assessment-sleeping-accommodation-accessible | I14: 02/10/2026
A15: Smoke & CO alarms - check | B15: All rented homes; licensed HMOs must also give the council a declaration on demand | C15: 12 | D15: Check on day 1 of each new tenancy; 12 months is a sensible repeat | E15: LAW (interval = practice) | F15: Smoke and Carbon Monoxide Alarm (England) Regulations 2015 reg 4 (as amended 2022). Licensed HMOs: Housing Act 2004 Sch 4 para 1(4) and 1(4A). | G15: Law: a smoke alarm on each storey used as living accommodation; a carbon monoxide alarm in any room used as living accommodation that has a fixed combustion appliance (not a gas cooker). Halls, landings, bathrooms and lavatories count as rooms. The landlord must check the alarms work on the first day of a new tenancy and repair or replace one a tenant reports faulty. Penalty charge up to £5,000. The 12-month repeat check is good practice; weekly alarm-system tests belong on the Fire Safety Log. | H15: https://www.legislation.gov.uk/uksi/2015/1693/regulation/4 | I15: 02/10/2026
A16: Portable appliance testing (PAT) | B16: Appliances and furniture you supply | C16: 12 | D16: Annually is common; no legal interval | E16: BEST PRACTICE | F16: Licensed HMOs: Housing Act 2004 Sch 4 para 1(3)(a)-(b) (keep supplied appliances and furniture safe). HSE position on PAT. | G16: HSE says the Electricity at Work Regulations do not make testing of electrical appliances a legal requirement, nor annual testing (workplace guidance). You must still keep supplied appliances safe and, for licensed HMOs, give the council a declaration on demand. Some licences ask for regular testing: CHECK LOCALLY. | H16: https://www.hse.gov.uk/electricity/faq-portable-appliance-testing.htm | I16: 02/10/2026
A17: Legionella risk assessment - review | B17: All rented homes | C17: 24 | D17: Review periodically; 24 months is a prompt, not a rule | E17: BEST PRACTICE | F17: Health and Safety at Work etc. Act 1974 and COSHH (HSE landlord guidance). | G17: HSE: landlords must assess the risk, but for most homes a simple assessment is enough. The law does not prescribe that the assessment is reviewed annually or every two years; review it periodically and whenever something changes. HSE does not require a 'legionella test certificate'. The 24-month default is only a reminder: set your own. | H17: https://www.hse.gov.uk/legionnaires/legionella-landlords-responsibilities.htm | I17: 02/10/2026
... A21: Property inspection (manager's visit) | B21: HMOs | C21: 6 | D21: Every 6 months is a common routine | E21: BEST PRACTICE | F21: Management of HMOs Regs 2006 regs 7 and 8 (keep common parts and living accommodation in repair). | G21: No fixed legal inspection interval was found. Many councils set inspection frequencies in licence conditions: CHECK LOCALLY and follow your licence. The 6-month default is a suggestion only. | H21: https://www.legislation.gov.uk/uksi/2006/372/contents | I21: 02/10/2026
A30: OTHER DUTIES AND RULES TO KNOW (no fixed re-check date: record them on the Tenancies, Fire Safety and Licence Conditions sheets)
A31: Requirement / check | B31: Applies to | C31: Interval (months) | D31: Typical frequency | E31: Type | F31: Legal basis | G31: Notes and penalty | H31: Official source URL | I31: Last checked
A32: HMO Management Regulations 2006 duties | B32: Managers of HMOs (licensed or not) | C32: n/a | D32: Ongoing | E32: LAW | F32: Management of Houses in Multiple Occupation (England) Regulations 2006 (SI 2006/372) regs 3-10; Housing Act 2004 s.234. | G32: Reg 3: display the manager's name, address and phone number prominently and give them to each household. Reg 4: keep escape routes clear and in repair; keep fire alarms and fire-fighting equipment in good working order; display escape-route notices (not required for HMOs with four or fewer occupiers). Reg 5: water supply and drainage. Reg 6: gas certificate to the council within 7 days of a written request. Reg 7: common parts. Reg 8: living accommodation. Reg 9: enough bins for each household. Reg 10: occupiers' duties. Failing to comply is an offence (fine up to level 5 on the standard scale, s.234); councils can instead impose a financial penalty (s.249A). | H32: https://www.legislation.gov.uk/uksi/2006/372/contents | I32: 02/10/2026
A33: HMO licence: mandatory conditions (Schedule 4) | B33: Licensed HMOs in England | C33: n/a | D33: Ongoing; see the Licence Conditions sheet | E33: LAW | F33: Housing Act 2004 Schedule 4 (text current to 2 Oct 2026). | G33: Every Part 2 licence in England must include: annual gas safety certificate; supplied appliances and furniture safe; electrical installations safe (declaration on demand); smoke alarms on each storey and CO alarms where there is a fixed combustion appliance (declarations on demand); a written statement of terms for each occupier; minimum bedroom sizes and room limits; and compliance with the council's household waste scheme. Part 3 (selective) licences must also require references from people who wish to occupy. | H33: https://www.legislation.gov.uk/ukpga/2004/34/schedule/4 | I33: 02/10/2026
A34: HMO bedroom sizes and room limits | B34: Licensed HMOs in England (Part 2 licences) | C34: n/a | D34: Ongoing | E34: LAW | F34: Housing Act 2004 Sch 4 para 1A. | G34: Minimum floor area for a sleeping room: 6.51 m2 for one person over 10; 10.22 m2 for two people over 10; 4.64 m2 for one person under 10; a room under 4.64 m2 must not be used for sleeping and the council must be told about it. Floor space under a ceiling lower than 1.5 m does not count. Your licence sets the maximum number of people per room. A breach you did not knowingly permit must be put right within the period the council sets (not more than 18 months). The statute gives no floor-area figure for other combinations (such as three people, or an adult and a child): follow the maximum numbers in your licence, which your council sets. Use the calculator on the Licence Conditions sheet. | H34: https://www.legislation.gov.uk/ukpga/2004/34/schedule/4 | I34: 02/10/2026
A35: Which HMOs need a licence | B35: Landlords and managers of HMOs | C35: n/a | D35: Check with your council | E35: LAW | F35: Housing Act 2004 ss.55, 56, 61, 79; Licensing of Houses in Multiple Occupation (Prescribed Descriptions) (England) Order 2018 art 4. | G35: Mandatory licensing applies to an HMO occupied by five or more people living in two or more separate households (and meeting the HMO definition tests). Councils may also designate areas for additional licensing of other HMOs (s.56) and selective licensing (Part 3, s.79-80): CHECK LOCALLY which applies to you. Running a licensable HMO without a licence is an offence (s.72); an application that is still effective can be a defence (s.72(4)(b)) but do not rely on it. | H35: https://www.legislation.gov.uk/uksi/2018/221/article/4 | I35: 02/10/2026
A36: Deposit protection and deposit cap | B36: Landlords who take a tenancy deposit | C36: n/a | D36: Within 30 days of receipt | E36: LAW | F36: Housing Act 2004 ss.213-214; Tenant Fees Act 2019 Sch 1 para 2. | G36: Comply with an authorised scheme's initial requirements AND give the prescribed information within the 30-day period that begins on the day you receive the deposit (so the last day is 29 days after receipt; the tracker uses this). If not, the court must order you to pay between 1 and 3 times the deposit (s.214(4)). Cap: 5 weeks' rent if the annual rent is under £50,000 (6 weeks if £50,000 or more); a week's rent is the annual rent divided by 52. Lodgers or resident-landlord arrangements: CHECK LOCALLY. | H36: https://www.legislation.gov.uk/ukpga/2004/34/section/213 | I36: 02/10/2026
A37: Right to Rent checks | B37: Every adult occupier in England, including lodgers and room tenants | C37: n/a | D37: Before the tenancy; follow-up if time-limited | E37: LAW | F37: Immigration Act 2014 Right to Rent scheme; Home Office 'Landlord's guide to right to rent checks' (1 October 2026). | G37: Check every adult who will occupy the home as their only or main home before the tenancy begins. Keep a copy of the evidence and the check date for the tenancy and at least one year after. Where the right is time-limited, do a follow-up check before it expires. Civil penalties (first / repeat): lodger £5,000 / £10,000; occupier £10,000 / £20,000. Use the official GOV.UK service for online checks. | H37: https://www.gov.uk/government/publications/landlords-guide-to-right-to-rent-checks | I37: 02/10/2026
A38: Renters' Rights Act: what changed on 1 May 2026 | B38: Landlords and agents of assured tenancies in England | C38: n/a | D38: In force since 1 May 2026 | E38: LAW | F38: Renters' Rights Act 2025; gov.uk 'Renters' Rights Act: an overview for landlords' (1 May 2026). | G38: Section 21 'no fault' evictions can no longer be used: you need a legal ground. Existing ASTs became assured periodic tenancies and new tenancies are assured periodic (no end date). No asking for, encouraging or accepting rent before the agreement is signed; publish an asking price and do not accept offers above it; no discrimination against people on benefits or with children. Existing tenancies with a written record: give the Information Sheet by 31 May 2026 (fine up to £7,000; not needed for lodgers). New tenancies: give written key terms before signing. Verbal tenancies agreed before 1 May 2026: written key terms by 31 May 2026. | H38: https://www.gov.uk/guidance/renters-rights-act-an-overview-for-landlords | I38: 02/10/2026
A39: Rent increases (section 13) | B39: Assured periodic tenancies | C39: n/a | D39: Once a year at most | E39: LAW | F39: Housing Act 1988 s.13 as amended by the Renters' Rights Act 2025 s.6. | G39: Serve a Form 4A (section 13 notice). The new rent can start no earlier than two months after the notice is served, and no earlier than 52 weeks after the first period of the tenancy began or after the last increase took effect (53 weeks in a rare case, s.13(3B)); the tracker shows 52 weeks and, where there has been no increase yet, counts 52 weeks from the tenancy start as a cautious default (the first-period rule does not apply to statutory periodic tenancies). Tenants can challenge an increase above open-market rent at the First-tier Tribunal; gov.uk (Sep 2026) says HMRC's Valuation Office will take over rent determinations in future. Allow time for service. | H39: https://www.legislation.gov.uk/ukpga/1988/50/section/13 | I39: 02/10/2026
A40: Pet requests | B40: Assured tenancies other than social housing | C40: n/a | D40: Reply within 28 days | E40: LAW | F40: Housing Act 1988 s.16A (inserted by Renters' Rights Act 2025 s.11). | G40: A tenant can ask in writing, describing the pet. The landlord must give or refuse consent in writing on or before the 28th day after the request, and must not unreasonably refuse. The deadline can extend if you reasonably ask for more information in time, need a superior landlord's consent, or agree a later date with the tenant. | H40: https://www.legislation.gov.uk/ukpga/2025/26/section/11 | I40: 02/10/2026
A41: PRS Database ('Register your rental property') | B41: All private-rented-sector landlords in England | C41: n/a | D41: Rolling out from 15 Dec 2026 | E41: LAW (rolling out) | F41: Renters' Rights Act 2025 (Part 2 Chapter 3); gov.uk news 9 Sep 2026; Implementation roadmap (13 Nov 2025). | G41: Registration is mandatory. The service launches on 15 December 2026, region by region starting in the West Midlands over 12 months; when your area is called you have three months to sign up; all landlords actively letting must be registered by 14 November 2027, and failing to register risks a fine (gov.uk, 9 Sep 2026). The tracker's PRS Database Readiness sheet works through what you need. Fee: see the next two rows; confirm on GOV.UK before paying or budgeting. | H41: https://www.gov.uk/government/news/stronger-protections-and-greater-confidence-for-renters | I41: 02/10/2026
A42: PRS Database: draft regulations 2026 (dates, data items, updates) | B42: All private-rented-sector landlords in England | C42: n/a | D42: Entries renew every 12 months | E42: LAW (DRAFT, not yet made) | F42: The Private Rented Sector Database Regulations 2026 (draft statutory instrument on legislation.gov.uk). | G42: DRAFT: not yet made as a statutory instrument at 2 Oct 2026, so details may change. Regional start dates: West Midlands 15 Dec 2026, East of England 15 Jan 2027, East Midlands 15 Feb 2027, South East 15 Mar 2027, Yorkshire and Humber 15 Apr 2027, North West 15 May 2027, North East 15 Jun 2027, London 15 Jul 2027, South West 15 Aug 2027 (reg 1). Each landlord needs a landlord entry (Schedule 2) and each dwelling a dwelling entry (Schedule 3). Part 2 of Schedule 3 (tenancy and health and safety documents) may follow within 28 days of the entry (reg 6(2)). Anything out of date must be updated within 28 days (regs 8, 9(4)). Entries renew every 12 months (reg 10). The fee is set by the database operator (reg 14); no amount appears in the regulations. | H42: https://www.legislation.gov.uk/ukdsi/2026/9780348286861 | I42: 02/10/2026
... A46: Awaab's Law and Decent Homes Standard (not yet in force) | B46: Private rented sector | C46: n/a | D46: Timescales to be set | E46: GUIDANCE | F46: Implementation roadmap (13 Nov 2025), phase 3. | G46: The roadmap says phase 3 will extend Awaab's Law and a modernised Decent Homes Standard to the private rented sector, with timescales subject to consultation. Not in force: CHECK GOV.UK for updates. | H46: https://www.gov.uk/government/publications/renters-rights-act-2025-implementation-roadmap/implementing-the-renters-rights-act-2025-our-roadmap-for-reforming-the-private-rented-sector | I46: 02/10/2026
A48: Always check the current law and your own council's licence conditions. This sheet is a summary for organisation, not legal advice.
